Workbook

Sheet 3-Statement Model
A4: x | C4: Income Statement | E4: 2020 | F4: =E4+1 -> 2021 | G4: =F4+1 -> 2022 | H4: =G4+1 -> 2023 | I4: =H4+1 -> 2024 | J4: =I4+1 -> 2025 | K4: =J4+1 -> 2026 | L4: =K4+1 -> 2027 | M4: =L4+1 -> 2028 | ... S4: =R4+1 -> 2034
B6: x | C6: Revenue | E6: 2020 | F6: =E6+1 -> 2021 | G6: =F6+1 -> 2022 | H6: =G6+1 -> 2023 | I6: =H6+1 -> 2024 | J6: =I6+1 -> 2025 | K6: =J6+1 -> 2026 | L6: =K6+1 -> 2027 | M6: =L6+1 -> 2028 | ... S6: =R6+1 -> 2034
C8: EMEA | E8: 3495.4 | F8: 4071.4 | G8: 4143.5 | H8: 4879.7 | I8: 5095.2 | J8: =I8*(1+J9) -> 5033.8156 | K8: =J8*(1+K9) -> 5298.0229 | L8: =K8*(1+L9) -> 5596.4305 | M8: =L8*(1+M9) -> 5899.5453 | N8: =M8*(1+N9) -> 6215.1595 | O8: =N8*(1+O9) -> 6515.9637 | P8: =O8*(1+P9) -> 6798.0973 | Q8: =P8*(1+Q9) -> 7057.7794 | ... S8: =R8*(1+S9) -> 7495.5481
C9: % growth | E9: =IF(ISNUMBER(B8),(E8-B8)/B8, "--") -> -- | F9: =IF(ISNUMBER(E8),(F8-E8)/E8, "--") -> 0.16478801 | G9: =IF(ISNUMBER(F8),(G8-F8)/F8, "--") -> 0.017708896 | H9: =IF(ISNUMBER(G8),(H8-G8)/G8, "--") -> 0.17767588 | I9: =IF(ISNUMBER(H8),(I8-H8)/H8, "--") -> 0.044162551 | J9: =Assumptions!J10 -> -0.01204749 | K9: =Assumptions!K10 -> 0.052486486 | L9: =Assumptions!L10 -> 0.056324324 | M9: =Assumptions!M10 -> 0.054162162 | N9: =Assumptions!N10 -> 0.053498069 | O9: =Assumptions!O10 -> 0.048398456 | P9: =Assumptions!P10 -> 0.043298842 | Q9: =Assumptions!Q10 -> 0.038199228 | ... S9: =Assumptions!S10 -> 0.028
C10: % of revenue | E10: =E8/E24 -> 0.44371382 | F10: =F8/F24 -> 0.44004194 | G10: =G8/G24 -> 0.39492747 | H10: =H8/H24 -> 0.43419109 | I10: =I8/I24 -> 0.43315113 | J10: =J8/J24 -> 0.44487169 | K10: =K8/K24 -> 0.44478295 | L10: =L8/L24 -> 0.44044314 | ... S10: =S8/S24 -> 0.43548745
C12: Americas | E12: 2012.2 | F12: 2427.4 | G12: 3193.5 | H12: 3735.9 | I12: 4096.9 | J12: =I12*(1+J13) -> 3928.9271 | K12: =J12*(1+K13) -> 4105.7288 | L12: =K12*(1+L13) -> 4434.1871 | M12: =L12*(1+M13) -> 4753.4486 | N12: =M12*(1+N13) -> 5033.9021 | O12: =N12*(1+O13) -> 5300.3968 | P12: =O12*(1+P13) -> 5548.8794 | Q12: =P12*(1+Q13) -> 5775.3847 | ... S12: =R12*(1+S13) -> 6147.6522
C13: % growth | E13: =IF(ISNUMBER(B12),(E12-B12)/B12, "--") -> -- | F13: =IF(ISNUMBER(E12),(F12-E12)/E12, "--") -> 0.20634132 | G13: =IF(ISNUMBER(F12),(G12-F12)/F12, "--") -> 0.31560517 | H13: =IF(ISNUMBER(G12),(H12-G12)/G12, "--") -> 0.169845 | I13: =IF(ISNUMBER(H12),(I12-H12)/H12, "--") -> 0.096629995 | J13: =Assumptions!J11 -> -0.041 | K13: =Assumptions!K11 -> 0.045 | L13: =Assumptions!L11 -> 0.08 | M13: =Assumptions!M11 -> 0.072 | N13: =Assumptions!N11 -> 0.059 | O13: =Assumptions!O11 -> 0.05294 | P13: =Assumptions!P11 -> 0.04688 | Q13: =Assumptions!Q11 -> 0.04082 | ... S13: =Assumptions!S11 -> 0.0287
C14: % of revenue | E14: =E12/E24 -> 0.25543313 | F14: =F12/F24 -> 0.26235639 | G14: =G12/G24 -> 0.30438056 | H14: =H12/H24 -> 0.33241685 | I14: =I12/I24 -> 0.34828404 | J14: =J12/J24 -> 0.34722536 | K14: =K12/K24 -> 0.34468672 | L14: =L12/L24 -> 0.34897375 | ... S14: =S12/S24 -> 0.3571754
C16: Asia/Pacific | E16: 1723.3 | F16: 2080.9 | G16: 2350.6 | H16: 2623 | I16: 2571 | J16: =I16*(1+J17) -> 2352.465 | K16: =J16*(1+K17) -> 2507.7277 | L16: =K16*(1+L17) -> 2675.7454 | M16: =L16*(1+M17) -> 2828.2629 | N16: =M16*(1+N17) -> 2975.3326 | O16: =N16*(1+O17) -> 3115.2327 | P16: =O16*(1+P17) -> 3246.1971 | Q16: =P16*(1+Q17) -> 3366.5012 | ... S16: =R16*(1+S17) -> 3568.6575
C17: % growth | E17: =IF(ISNUMBER(B16),(E16-B16)/B16, "--") -> -- | F17: =IF(ISNUMBER(E16),(F16-E16)/E16, "--") -> 0.20750885 | G17: =IF(ISNUMBER(F16),(G16-F16)/F16, "--") -> 0.12960738 | H17: =IF(ISNUMBER(G16),(H16-G16)/G16, "--") -> 0.11588531 | I17: =IF(ISNUMBER(H16),(I16-H16)/H16, "--") -> -0.019824628 | J17: =Assumptions!J12 -> -0.085 | K17: =Assumptions!K12 -> 0.066 | L17: =Assumptions!L12 -> 0.067 | M17: =Assumptions!M12 -> 0.057 | N17: =Assumptions!N12 -> 0.052 | O17: =Assumptions!O12 -> 0.04702 | P17: =Assumptions!P12 -> 0.04204 | Q17: =Assumptions!Q12 -> 0.03706 | ... S17: =Assumptions!S12 -> 0.0271
C18: % of revenue | E18: =E16/E24 -> 0.21875952 | F18: =F16/F24 -> 0.22490624 | G18: =G16/G24 -> 0.22404163 | H18: =H16/H24 -> 0.23339206 | I18: =I16/I24 -> 0.21856483 | J18: =J16/J24 -> 0.20790294 | K18: =K16/K24 -> 0.21053033 | L18: =L16/L24 -> 0.21058311 | ... S18: =S16/S24 -> 0.20733715
C20: Global Business | E20: 646.7 | F20: 672.6 | G20: 804.2 | H20: 0 | I20: 0 | J20: =I20*(1+J21) -> 0 | K20: =J20*(1+K21) -> 0 | L20: =K20*(1+L21) -> 0 | M20: =L20*(1+M21) -> 0 | N20: =M20*(1+N21) -> 0 | O20: =N20*(1+O21) -> 0 | P20: =O20*(1+P21) -> 0 | Q20: =P20*(1+Q21) -> 0 | ... S20: =R20*(1+S21) -> 0
C21: % growth | E21: =IF(ISNUMBER(B20),(E20-B20)/B20, "--") -> -- | F21: =IF(ISNUMBER(E20),(F20-E20)/E20, "--") -> 0.040049482 | G21: =IF(ISNUMBER(F20),(G20-F20)/F20, "--") -> 0.19565864 | H21: =IF(ISNUMBER(G20),(H20-G20)/G20, "--") -> -1 | I21: =IF(ISNUMBER(H20), IF(H20=0, "--", (I20-H20)/H20), "--") -> -- | J21: =Assumptions!J13 -> 0 | K21: =Assumptions!K13 -> 0 | L21: =Assumptions!L13 -> 0 | M21: =Assumptions!M13 -> 0 | N21: =Assumptions!N13 -> 0 | O21: =Assumptions!O13 -> 0 | P21: =Assumptions!P13 -> 0 | Q21: =Assumptions!Q13 -> 0 | ... S21: =Assumptions!S13 -> 0
C22: % of revenue | E22: =E20/E24 -> 0.082093531 | F22: =F20/F24 -> 0.072695438 | G22: =G20/G24 -> 0.076650336 | H22: =H20/H24 -> 0 | I22: =I20/I24 -> 0 | J22: =J20/J24 -> 0 | K22: =K20/K24 -> 0 | L22: =L20/L24 -> 0 | ... S22: =S20/S24 -> 0
C24: Revenue | E24: =E8+E12+E16+E20 -> 7877.6 | F24: =F8+F12+F16+F20 -> 9252.3 | G24: =G8+G12+G16+G20 -> 10491.8 | H24: =H8+H12+H16+H20 -> 11238.6 | I24: =I8+I12+I16+I20 -> 11763.1 | J24: =J8+J12+J16+J20 -> 11315.208 | K24: =K8+K12+K16+K20 -> 11911.479 | L24: =L8+L12+L16+L20 -> 12706.363 | ... S24: =S8+S12+S16+S20 -> 17211.858
C25: % growth | E25: =IF(ISNUMBER(B24),(E24-B24)/B24, "--") -> -- | F25: =IF(ISNUMBER(E24),(F24-E24)/E24, "--") -> 0.17450746 | G25: =IF(ISNUMBER(F24),(G24-F24)/F24, "--") -> 0.13396669 | H25: =IF(ISNUMBER(G24),(H24-G24)/G24, "--") -> 0.071179397 | I25: =IF(ISNUMBER(H24),(I24-H24)/H24, "--") -> 0.046669514 | J25: =IF(ISNUMBER(I24),(J24-I24)/I24, "--") -> -0.038076041 | K25: =IF(ISNUMBER(J24),(K24-J24)/J24, "--") -> 0.052696488 | L25: =IF(ISNUMBER(K24),(L24-K24)/K24, "--") -> 0.066732569 | M25: =IF(ISNUMBER(L24),(M24-L24)/L24, "--") -> 0.0609847 | ... S25: =IF(ISNUMBER(R24),(S24-R24)/R24, "--") -> 0.02806309
B27: x | C27: COGS | E27: 2020 | F27: =E27+1 -> 2021 | G27: =F27+1 -> 2022 | H27: =G27+1 -> 2023 | I27: =H27+1 -> 2024 | J27: =I27+1 -> 2025 | K27: =J27+1 -> 2026 | L27: =K27+1 -> 2027 | M27: =L27+1 -> 2028 | ... S27: =R27+1 -> 2034
C29: Cost of Goods Sold | E29: 3562.7 | F29: 4461 | G29: 5312 | H29: 5213.8 | I29: 5347.1 | J29: =J30*J24 -> 5091.8435 | K29: =K30*K24 -> 5360.1657 | L29: =L30*L24 -> 5717.8634 | M29: =M30*M24 -> 6066.5656 | N29: =N30*N24 -> 6400.9774 | O29: =O30*O24 -> 6719.217 | P29: =P30*P24 -> 7016.9283 | Q29: =Q30*Q24 -> 7289.8494 | ... S29: =S30*S24 -> 7745.336
C30: % of revenue | E30: =E29/E24 -> 0.45225703 | F30: =F29/F24 -> 0.48215038 | G30: =G29/G24 -> 0.50630016 | H30: =H29/H24 -> 0.46391899 | I30: =I29/I24 -> 0.45456555 | J30: =Assumptions!J16 -> 0.45 | K30: =Assumptions!K16 -> 0.45 | L30: =Assumptions!L16 -> 0.45 | M30: =Assumptions!M16 -> 0.45 | N30: =Assumptions!N16 -> 0.45 | O30: =Assumptions!O16 -> 0.45 | P30: =Assumptions!P16 -> 0.45 | Q30: =Assumptions!Q16 -> 0.45 | ... S30: =Assumptions!S16 -> 0.45
C32: Gross Profit | E32: =E24-E29 -> 4314.9 | F32: =F24-F29 -> 4791.3 | G32: =G24-G29 -> 5179.8 | H32: =H24-H29 -> 6024.8 | I32: =I24-I29 -> 6416 | J32: =J24-J29 -> 6223.3642 | K32: =K24-K29 -> 6551.3137 | L32: =L24-L29 -> 6988.4997 | ... S32: =S24-S29 -> 9466.5218
C33: Gross margin % | E33: =E32/E24 -> 0.54774297 | F33: =F32/F24 -> 0.51784962 | G33: =G32/G24 -> 0.49369984 | H33: =H32/H24 -> 0.53608101 | I33: =I32/I24 -> 0.54543445 | J33: =J32/J24 -> 0.55 | K33: =K32/K24 -> 0.55 | L33: =L32/L24 -> 0.55 | ... S33: =S32/S24 -> 0.55
B35: x | C35: OpEx | E35: 2020 | F35: =E35+1 -> 2021 | G35: =F35+1 -> 2022 | H35: =G35+1 -> 2023 | I35: =H35+1 -> 2024 | J35: =I35+1 -> 2025 | K35: =J35+1 -> 2026 | L35: =K35+1 -> 2027 | M35: =L35+1 -> 2028 | ... S35: =R35+1 -> 2034
C37: Personnel Expenses | E37: 1525.9 | F37: 1635.3 | G37: 1710.5 | H37: 2006.8 | I37: 2143.6 | J37: =J38*J24 -> 2138.5743 | K37: =K38*K24 -> 2167.8893 | L37: =L38*L24 -> 2249.0263 | M37: =M38*M24 -> 2386.1825 | N37: =N38*N24 -> 2517.7178 | O37: =O38*O24 -> 2642.892 | P37: =P38*P24 -> 2759.9918 | Q37: =Q38*Q24 -> 2867.3408 | ... S37: =S38*S24 -> 3046.4988
C38: % of revenue | E38: =E37/E24 -> 0.19370113 | F38: =F37/F24 -> 0.17674524 | G38: =G37/G24 -> 0.16303208 | H38: =H37/H24 -> 0.17856317 | I38: =I37/I24 -> 0.18223087 | J38: =Assumptions!J19 -> 0.189 | K38: =Assumptions!K19 -> 0.182 | L38: =Assumptions!L19 -> 0.177 | M38: =Assumptions!M19 -> 0.177 | N38: =Assumptions!N19 -> 0.177 | O38: =Assumptions!O19 -> 0.177 | P38: =Assumptions!P19 -> 0.177 | Q38: =Assumptions!Q19 -> 0.177 | ... S38: =Assumptions!S19 -> 0.177
C40: Production and Operations | E40: 399.5 | F40: 466.5 | G40: 498.5 | H40: 573.5 | I40: 621.6 | J40: =J41*J24 -> 588.3908 | K40: =K41*K24 -> 607.48545 | L40: =L41*L24 -> 635.31815 | M40: =M41*M24 -> 660.58158 | N40: =N41*N24 -> 696.99532 | O40: =O41*O24 -> 731.64807 | P40: =P41*P24 -> 764.06552 | Q40: =Q41*Q24 -> 793.7836 | ... S40: =S41*S24 -> 843.38103
C41: % of revenue | E41: =E40/E24 -> 0.050713415 | F41: =F40/F24 -> 0.050419896 | G41: =G40/G24 -> 0.047513296 | H41: =H40/H24 -> 0.051029488 | I41: =I40/I24 -> 0.052843213 | J41: =Assumptions!J20 -> 0.052 | K41: =Assumptions!K20 -> 0.051 | L41: =Assumptions!L20 -> 0.05 | M41: =Assumptions!M20 -> 0.049 | N41: =Assumptions!N20 -> 0.049 | O41: =Assumptions!O20 -> 0.049 | P41: =Assumptions!P20 -> 0.049 | Q41: =Assumptions!Q20 -> 0.049 | ... S41: =Assumptions!S20 -> 0.049
C43: Logistics and Distribution | E43: 401.6 | F43: 477 | G43: 519.4 | H43: 566.1 | I43: 605.3 | J43: =J44*J24 -> 565.76039 | K43: =K44*K24 -> 583.66249 | L43: =L44*L24 -> 622.61179 | M43: =M44*M24 -> 647.10033 | N43: =N44*N24 -> 682.77092 | O43: =O44*O24 -> 716.71648 | P43: =P44*P24 -> 748.47235 | Q43: =Q44*Q24 -> 777.58394 | ... S43: =S44*S24 -> 826.16917
C44: % of revenue | E44: =E43/E24 -> 0.050979994 | F44: =F43/F24 -> 0.051554749 | G44: =G43/G24 -> 0.049505328 | H44: =H43/H24 -> 0.050371043 | I44: =I43/I24 -> 0.051457524 | J44: =Assumptions!J21 -> 0.05 | K44: =Assumptions!K21 -> 0.049 | L44: =Assumptions!L21 -> 0.049 | M44: =Assumptions!M21 -> 0.048 | N44: =Assumptions!N21 -> 0.048 | O44: =Assumptions!O21 -> 0.048 | P44: =Assumptions!P21 -> 0.048 | Q44: =Assumptions!Q21 -> 0.048 | ... S44: =Assumptions!S21 -> 0.048
C46: Sales, Marketing and Travel Costs | E46: 212 | F46: 235.1 | G46: 303.5 | H46: 370.5 | I46: 370.9 | J46: =J47*J24 -> 350.77144 | K46: =K47*K24 -> 357.34438 | L46: =L47*L24 -> 368.48453 | M46: =M47*M24 -> 390.95645 | N46: =N47*N24 -> 412.50743 | O46: =O47*O24 -> 433.0162 | P46: =P47*P24 -> 452.20204 | Q46: =Q47*Q24 -> 469.79029 | ... S46: =S47*S24 -> 499.14388
C47: % of revenue | E47: =E46/E24 -> 0.02691175 | F47: =F46/F24 -> 0.025409898 | G47: =G46/G24 -> 0.028927353 | H47: =H46/H24 -> 0.03296674 | I47: =I46/I24 -> 0.031530804 | J47: =Assumptions!J22 -> 0.031 | K47: =Assumptions!K22 -> 0.03 | L47: =Assumptions!L22 -> 0.029 | M47: =Assumptions!M22 -> 0.029 | N47: =Assumptions!N22 -> 0.029 | O47: =Assumptions!O22 -> 0.029 | P47: =Assumptions!P22 -> 0.029 | Q47: =Assumptions!Q22 -> 0.029 | ... S47: =Assumptions!S22 -> 0.029
C49: Administration Costs | E49: 278.2 | F49: 239.4 | G49: 183.7 | H49: 463.2 | I49: 405.1 | J49: =J50*J24 -> 407.34748 | K49: =K50*K24 -> 416.90178 | L49: =L50*L24 -> 444.72271 | M49: =M50*M24 -> 458.36273 | N49: =N50*N24 -> 483.6294 | O49: =O50*O24 -> 507.67417 | P49: =P50*P24 -> 530.16791 | Q49: =Q50*Q24 -> 550.78862 | ... S49: =S50*S24 -> 585.20316
C50: % of revenue | E50: =E49/E24 -> 0.035315324 | F50: =F49/F24 -> 0.025874647 | G50: =G49/G24 -> 0.017508912 | H50: =H49/H24 -> 0.041215098 | I50: =I49/I24 -> 0.034438201 | J50: =Assumptions!J23 -> 0.036 | K50: =Assumptions!K23 -> 0.035 | L50: =Assumptions!L23 -> 0.035 | M50: =Assumptions!M23 -> 0.034 | N50: =Assumptions!N23 -> 0.034 | O50: =Assumptions!O23 -> 0.034 | P50: =Assumptions!P23 -> 0.034 | Q50: =Assumptions!Q23 -> 0.034 | ... S50: =Assumptions!S23 -> 0.034
C52: Operating Expenses | E52: =E37+E40+E43+E46+E49 -> 2817.2 | F52: =F37+F40+F43+F46+F49 -> 3053.3 | G52: =G37+G40+G43+G46+G49 -> 3215.6 | H52: =H37+H40+H43+H46+H49 -> 3980.1 | I52: =I37+I40+I43+I46+I49 -> 4146.5 | J52: =J37+J40+J43+J46+J49 -> 4050.8444 | K52: =K37+K40+K43+K46+K49 -> 4133.2834 | L52: =L37+L40+L43+L46+L49 -> 4320.1634 | ... S52: =S37+S40+S43+S46+S49 -> 5800.3961
C53: % of revenue | E53: =E52/E24 -> 0.35762161 | F53: =F52/F24 -> 0.33000443 | G53: =G52/G24 -> 0.30648697 | H53: =H52/H24 -> 0.35414553 | I53: =I52/I24 -> 0.35250062 | J53: =J52/J24 -> 0.358 | K53: =K52/K24 -> 0.347 | L53: =L52/L24 -> 0.34 | ... S53: =S52/S24 -> 0.337
C55: EBITDA | E55: =E32-E52 -> 1497.7 | F55: =F32-F52 -> 1738 | G55: =G32-G52 -> 1964.2 | H55: =H32-H52 -> 2044.7 | I55: =I32-I52 -> 2269.5 | J55: =J32-J52 -> 2172.5199 | K55: =K32-K52 -> 2418.0303 | L55: =L32-L52 -> 2668.3362 | ... S55: =S32-S52 -> 3666.1257
C56: % of revenue | E56: =E55/E24 -> 0.19012136 | F56: =F55/F24 -> 0.18784518 | G56: =G55/G24 -> 0.18721287 | H56: =H55/H24 -> 0.18193547 | I56: =I55/I24 -> 0.19293384 | J56: =J55/J24 -> 0.192 | K56: =K55/K24 -> 0.203 | L56: =L55/L24 -> 0.21 | ... S56: =S55/S24 -> 0.213
B58: x | C58: Depreciation and Amortization | E58: 2020 | F58: =E58+1 -> 2021 | G58: =F58+1 -> 2022 | H58: =G58+1 -> 2023 | I58: =H58+1 -> 2024 | J58: =I58+1 -> 2025 | K58: =J58+1 -> 2026 | L58: =K58+1 -> 2027 | M58: =L58+1 -> 2028 | ... S58: =R58+1 -> 2034
C60: Depreciation | E60: =169.3+85.5 -> 254.8 | F60: =165.8+84.5 -> 250.3 | G60: =174.5+86.1 -> 260.6 | H60: =200+106 -> 306 | I60: =220.7+120.8 -> 341.5 | J60: =J300 -> 383.24313 | K60: =K300 -> 423.62303 | L60: =L300 -> 465.19318 | M60: =M300 -> 474.04774 | N60: =N300 -> 438.18835 | O60: =O300 -> 481.25332 | P60: =P300 -> 502.07297 | Q60: =Q300 -> 521.07452 | ... S60: =S300 -> 320.73894
C61: % of revenue | E61: =E60/E24 -> 0.032344877 | F61: =F60/F24 -> 0.027052733 | G61: =G60/G24 -> 0.024838445 | H61: =H60/H24 -> 0.027227591 | I61: =I60/I24 -> 0.029031463 | J61: =J60/J24 -> 0.033869739 | K61: =K60/K24 -> 0.035564267 | L61: =L60/L24 -> 0.036611041 | ... S61: =S60/S24 -> 0.018634766
C63: Amortization | E63: 112.3 | F63: 116.3 | G63: 123.9 | H63: 179.3 | I63: 214.1 | J63: =J303 -> 215.29748 | K63: =K303 -> 217.062 | L63: =L303 -> 218.94426 | M63: =M303 -> 220.94131 | N63: =N303 -> 223.04844 | O63: =O303 -> 225.26034 | P63: =P303 -> 227.57024 | Q63: =Q303 -> 229.96999 | ... S63: =S303 -> 145.48674
C64: % of revenue | E64: =E63/E24 -> 0.014255611 | F64: =F63/F24 -> 0.012569847 | G64: =G63/G24 -> 0.011809222 | H64: =H63/H24 -> 0.015953944 | I64: =I63/I24 -> 0.018200984 | J64: =J63/J24 -> 0.019027267 | K64: =K63/K24 -> 0.018222925 | L64: =L63/L24 -> 0.017231072 | ... S64: =S63/S24 -> 0.0084527041
C66: Depreciation and Amortization | E66: =E60+E63 -> 367.1 | F66: =F60+F63 -> 366.6 | G66: =G60+G63 -> 384.5 | H66: =H60+H63 -> 485.3 | I66: =I60+I63 -> 555.6 | J66: =J60+J63 -> 598.54062 | K66: =K60+K63 -> 640.68503 | L66: =L60+L63 -> 684.13744 | ... S66: =S60+S63 -> 466.22568
C67: % of revenue | E67: =E66/E24 -> 0.046600487 | F67: =F66/F24 -> 0.03962258 | G67: =G66/G24 -> 0.036647668 | H67: =H66/H24 -> 0.043181535 | I67: =I66/I24 -> 0.047232447 | J67: =J66/J24 -> 0.052897007 | K67: =K66/K24 -> 0.053787192 | L67: =L66/L24 -> 0.053842113 | ... S67: =S66/S24 -> 0.02708747
B69: x | C69: Impairment | E69: 0 | F69: 0 | G69: 0 | H69: 10.3 | I69: 0 | J69: =J70*J24 -> 0 | K69: =K70*K24 -> 0 | L69: =L70*L24 -> 0 | M69: =M70*M24 -> 0 | N69: =N70*N24 -> 0 | O69: =O70*O24 -> 0 | P69: =P70*P24 -> 0 | Q69: =Q70*Q24 -> 0 | ... S69: =S70*S24 -> 0
C70: % of revenue | E70: =E69/E24 -> 0 | F70: =F69/F24 -> 0 | G70: =G69/G24 -> 0 | H70: =H69/H24 -> 0.00091648426 | I70: =I69/I24 -> 0 | J70: =Assumptions!J53 -> 0 | K70: =Assumptions!K53 -> 0 | L70: =Assumptions!L53 -> 0 | M70: =Assumptions!M53 -> 0 | N70: =Assumptions!N53 -> 0 | O70: =Assumptions!O53 -> 0 | P70: =Assumptions!P53 -> 0 | Q70: =Assumptions!Q53 -> 0 | ... S70: =Assumptions!S53 -> 0
C72: EBIT | E72: =E55-E66-E69 -> 1130.6 | F72: =F55-F66-F69 -> 1371.4 | G72: =G55-G66-G69 -> 1579.7 | H72: =H55-H66-H69 -> 1549.1 | I72: =I55-I66-I69 -> 1713.9 | J72: =J55-J66-J69 -> 1573.9793 | K72: =K55-K66-K69 -> 1777.3453 | L72: =L55-L66-L69 -> 1984.1988 | ... S72: =S55-S66-S69 -> 3199.9
C73: % of revenue | E73: =E72/E24 -> 0.14352087 | F73: =F72/F24 -> 0.1482226 | G73: =G72/G24 -> 0.1505652 | H73: =H72/H24 -> 0.13783745 | I73: =I72/I24 -> 0.14570139 | J73: =J72/J24 -> 0.13910299 | K73: =K72/K24 -> 0.14921281 | L73: =L72/L24 -> 0.15615789 | ... S73: =S72/S24 -> 0.18591253
B75: x | C75: Interest and Taxes | E75: 2020 | F75: =E75+1 -> 2021 | G75: =F75+1 -> 2022 | H75: =G75+1 -> 2023 | I75: =H75+1 -> 2024 | J75: =I75+1 -> 2025 | K75: =J75+1 -> 2026 | L75: =K75+1 -> 2027 | M75: =L75+1 -> 2028 | ... S75: =R75+1 -> 2034
C77: Interest Expense | E77: 57.4 | F77: 56.9 | G77: 59.4 | H77: 165.7 | I77: 185.9 | J77: =J341 -> 146.68659 | K77: =K341 -> 144.67415 | L77: =L341 -> 141.1895 | M77: =M341 -> 136.22237 | N77: =N341 -> 136.22237 | O77: =O341 -> 136.22237 | P77: =P341 -> 136.22237 | Q77: =Q341 -> 136.22237 | ... S77: =S341 -> 136.22237
C78: % of revenue | E78: =E77/E24 -> 0.0072864832 | F78: =F77/F24 -> 0.0061498222 | G78: =G77/G24 -> 0.0056615643 | H78: =H77/H24 -> 0.014743829 | I78: =I77/I24 -> 0.015803657 | J78: =J77/J24 -> 0.012963668 | K78: =K77/K24 -> 0.012145775 | L78: =L77/L24 -> 0.011111716 | ... S78: =S77/S24 -> 0.0079144491
C80: Interest Income | E80: 5.5 | F80: 11.5 | G80: 19 | H80: 30.9 | I80: 26.6 | J80: =Assumptions!J40 -> 14.626968 | K80: =Assumptions!K40 -> 20.415726 | L80: =Assumptions!L40 -> 27.410596 | M80: =Assumptions!M40 -> 34.655265 | N80: =Assumptions!N40 -> 42.212816 | O80: =Assumptions!O40 -> 49.497181 | P80: =Assumptions!P40 -> 57.945803 | Q80: =Assumptions!Q40 -> 68.360129 | ... S80: =Assumptions!S40 -> 97.553834
C81: % of revenue | E81: =E80/E24 -> 0.00069818219 | F81: =F80/F24 -> 0.0012429342 | G81: =G80/G24 -> 0.0018109381 | H81: =H80/H24 -> 0.0027494528 | I81: =I80/I24 -> 0.0022613087 | J81: =J80/J24 -> 0.0012926823 | K81: =K80/K24 -> 0.0017139538 | L81: =L80/L24 -> 0.0021572338 | ... S81: =S80/S24 -> 0.0056678271
C83: Other Financial Income | E83: 6 | F83: 7 | G83: 6.9 | H83: 7.3 | I83: 7.3 | J83: =Assumptions!J43 -> 6.9 | K83: =Assumptions!K43 -> 6.9 | L83: =Assumptions!L43 -> 6.9 | M83: =Assumptions!M43 -> 6.9 | N83: =Assumptions!N43 -> 6.9 | O83: =Assumptions!O43 -> 6.9 | P83: =Assumptions!P43 -> 6.9 | Q83: =Assumptions!Q43 -> 6.9 | ... S83: =Assumptions!S43 -> 6.9
C84: % of revenue | E84: =E83/E24 -> 0.0007616533 | F84: =F83/F24 -> 0.00075656864 | G84: =G83/G24 -> 0.00065765646 | H84: =H83/H24 -> 0.0006495471 | I84: =I83/I24 -> 0.00062058471 | J84: =J83/J24 -> 0.00060979879 | K84: =K83/K24 -> 0.00057927313 | L84: =L83/L24 -> 0.00054303501 | ... S84: =S83/S24 -> 0.00040088642
C86: Other Financial Expenses | E86: 24.7 | F86: 17.8 | G86: 48.4 | H86: 86.3 | I86: 2.5 | J86: =Assumptions!J44 -> 23.35 | K86: =Assumptions!K44 -> 23.35 | L86: =Assumptions!L44 -> 23.35 | M86: =Assumptions!M44 -> 23.35 | N86: =Assumptions!N44 -> 23.35 | O86: =Assumptions!O44 -> 23.35 | P86: =Assumptions!P44 -> 23.35 | Q86: =Assumptions!Q44 -> 23.35 | ... S86: =Assumptions!S44 -> 23.35
C87: % of revenue | E87: =E86/E24 -> 0.0031354727 | F87: =F86/F24 -> 0.001923846 | G87: =G86/G24 -> 0.0046131264 | H87: =H86/H24 -> 0.0076788924 | I87: =I86/I24 -> 0.00021252901 | J87: =J86/J24 -> 0.0020635945 | K87: =K86/K24 -> 0.0019602939 | L87: =L86/L24 -> 0.001837662 | ... S87: =S86/S24 -> 0.0013566229
C89: Income from Associated Companies | E89: 0.5 | F89: 0.4 | G89: 0.4 | H89: 1.1 | I89: 3.6 | J89: =Assumptions!J46 -> 3.6 | K89: =Assumptions!K46 -> 3.6 | L89: =Assumptions!L46 -> 3.6 | M89: =Assumptions!M46 -> 3.6 | N89: =Assumptions!N46 -> 3.6 | O89: =Assumptions!O46 -> 3.6 | P89: =Assumptions!P46 -> 3.6 | Q89: =Assumptions!Q46 -> 3.6 | ... S89: =Assumptions!S46 -> 3.6
C90: % of revenue | E90: =E89/E24 -> 6.3471108e-05 | F90: =F89/F24 -> 4.3232494e-05 | G90: =G89/G24 -> 3.8125012e-05 | H90: =H89/H24 -> 9.787696e-05 | I90: =I89/I24 -> 0.00030604177 | J90: =J89/J24 -> 0.00031815589 | K90: =K89/K24 -> 0.00030222946 | L90: =L89/L24 -> 0.00028332261 | ... S90: =S89/S24 -> 0.00020915813
B92: x | C92: EBT | E92: =E72-E77+E80+E83-E86+E89 -> 1060.5 | F92: =F72-F77+F80+F83-F86+F89 -> 1315.6 | G92: =G72-G77+G80+G83-G86+G89 -> 1498.2 | H92: =H72-H77+H80+H83-H86+H89 -> 1336.4 | I92: =I72-I77+I80+I83-I86+I89 -> 1563 | J92: =J72-J77+J80+J83-J86+J89 -> 1429.0696 | K92: =K72-K77+K80+K83-K86+K89 -> 1640.2369 | L92: =L72-L77+L80+L83-L86+L89 -> 1857.5699 | ... S92: =S72-S77+S80+S83-S86+S89 -> 3148.3815
C93: % of revenue | E93: =E92/E24 -> 0.13462222 | F93: =F92/F24 -> 0.14219167 | G93: =G92/G24 -> 0.14279723 | H93: =H92/H24 -> 0.11891161 | I93: =I92/I24 -> 0.13287314 | J93: =J92/J24 -> 0.12629637 | K93: =K92/K24 -> 0.1377022 | L93: =L92/L24 -> 0.1461921 | ... S93: =S92/S24 -> 0.18291933
C95: Taxes | E95: 235.3 | F95: 287.1 | G95: 335.7 | H95: 273.8 | I95: 315.4 | J95: =J92*Assumptions!J159 -> 288.374 | K95: =K92*Assumptions!K159 -> 330.98574 | L95: =L92*Assumptions!L159 -> 374.84168 | M95: =M92*Assumptions!M159 -> 416.11441 | N95: =N92*Assumptions!N159 -> 456.39159 | O95: =O92*Assumptions!O159 -> 479.12156 | P95: =P92*Assumptions!P159 -> 504.59485 | Q95: =Q92*Assumptions!Q159 -> 528.44573 | ... S95: =S92*Assumptions!S159 -> 635.31639
C96: % tax rate | E96: =E95/E92 -> 0.22187647 | F96: =F95/F92 -> 0.21822742 | G96: =G95/G92 -> 0.22406888 | H96: =H95/H92 -> 0.20487878 | I96: =I95/I92 -> 0.20179143 | J96: =J95/J92 -> 0.20179143 | K96: =K95/K92 -> 0.20179143 | L96: =L95/L92 -> 0.20179143 | ... S96: =S95/S92 -> 0.20179143
B98: x | C98: Net Income | E98: =E92-E95 -> 825.2 | F98: =F92-F95 -> 1028.5 | G98: =G92-G95 -> 1162.5 | H98: =H92-H95 -> 1062.6 | I98: =I92-I95 -> 1247.6 | J98: =J92-J95 -> 1140.6956 | K98: =K92-K95 -> 1309.2511 | L98: =L92-L95 -> 1482.7282 | ... S98: =S92-S95 -> 2513.0651
C99: % of revenue | E99: =E98/E24 -> 0.10475272 | F99: =F98/F24 -> 0.11116155 | G99: =G98/G24 -> 0.11080082 | H99: =H98/H24 -> 0.094549143 | I99: =I98/I24 -> 0.10606048 | J99: =J98/J24 -> 0.10081084 | K99: =K98/K24 -> 0.10991507 | L99: =L98/L24 -> 0.11669179 | ... S99: =S98/S24 -> 0.14600778
B101: x | C101: Net income to NCI | E101: 0.6 | F101: 0.6 | G101: 0 | H101: 0.6 | I101: 2.1 | J101: =J102*J24 -> 2.0933134 | K101: =K102*K24 -> 2.2631811 | L101: =L102*L24 -> 2.4777408 | M101: =M102*M24 -> 2.6962514 | N101: =N102*N24 -> 2.9160008 | O101: =O102*O24 -> 3.1356346 | P101: =P102*P24 -> 3.3525324 | Q101: =Q102*Q24 -> 3.5639264 | ... S101: =S102*S24 -> 3.9587273
C102: % of revenue | E102: =E101/E24 -> 7.616533e-05 | F102: =F101/F24 -> 6.484874e-05 | G102: =G101/G24 -> 0 | H102: =H101/H24 -> 5.3387433e-05 | I102: =I101/I24 -> 0.00017852437 | J102: =Assumptions!J57 -> 0.000185 | K102: =Assumptions!K57 -> 0.00019 | L102: =Assumptions!L57 -> 0.000195 | M102: =Assumptions!M57 -> 0.0002 | N102: =Assumptions!N57 -> 0.000205 | O102: =Assumptions!O57 -> 0.00021 | P102: =Assumptions!P57 -> 0.000215 | Q102: =Assumptions!Q57 -> 0.00022 | ... S102: =Assumptions!S57 -> 0.00023
B104: x | C104: Net income to parent | E104: =E98-E101 -> 824.6 | F104: =F98-F101 -> 1027.9 | G104: =G98-G101 -> 1162.5 | H104: =H98-H101 -> 1062 | I104: =I98-I101 -> 1245.5 | J104: =J98-J101 -> 1138.6023 | K104: =K98-K101 -> 1306.988 | L104: =L98-L101 -> 1480.2505 | ... S104: =S98-S101 -> 2509.1064
C105: % of revenue | E105: =E104/E24 -> 0.10467655 | F105: =F104/F24 -> 0.1110967 | G105: =G104/G24 -> 0.11080082 | H105: =H104/H24 -> 0.094495756 | I105: =I104/I24 -> 0.10588195 | J105: =J104/J24 -> 0.10062584 | K105: =K104/K24 -> 0.10972507 | L105: =L104/L24 -> 0.11649679 | ... S105: =S104/S24 -> 0.14577778
C107: Days in period | E107: 365 | F107: =E107 -> 365 | G107: =F107 -> 365 | H107: =G107 -> 365 | I107: =H107 -> 365 | J107: =I107 -> 365 | K107: =J107 -> 365 | L107: =K107 -> 365 | M107: =L107 -> 365 | ... S107: =R107 -> 365
A109: X | C109: Balance Sheet | E109: 2020 | F109: =E109+1 -> 2021 | G109: =F109+1 -> 2022 | H109: =G109+1 -> 2023 | I109: =H109+1 -> 2024 | J109: =I109+1 -> 2025 | K109: =J109+1 -> 2026 | L109: =K109+1 -> 2027 | M109: =L109+1 -> 2028 | ... S109: =R109+1 -> 2034
C111: Cash and cash equivalents | E111: 1318.7 | F111: 1175 | G111: 1873.3 | H111: 643.9 | I111: 707.5 | J111: =I111+J191 -> 987.49964 | K111: =J111+K191 -> 1325.8385 | L111: =K111+L191 -> 1676.2599 | M111: =L111+M191 -> 2041.8153 | N111: =M111+N191 -> 2394.1568 | O111: =N111+O191 -> 2802.8129 | P111: =O111+P191 -> 3306.5492 | Q111: =P111+Q191 -> 3942.1665 | ... S111: =R111+S191 -> 5430.6121
C112: Accounts receivable | E112: 1361.8 | F112: 1576.8 | G112: 1719.6 | H112: 2009.2 | I112: 2175 | J112: =J311 -> 2139.0393 | K112: =K311 -> 2186.4907 | L112: =L311 -> 2259.862 | M112: =M311 -> 2397.679 | N112: =N311 -> 2529.848 | O112: =O311 -> 2655.6253 | P112: =P311 -> 2773.2893 | Q112: =Q311 -> 2881.1555 | ... S112: =S311 -> 3061.1767
C113: Inventories | E113: 814 | F113: 1158.3 | G113: 1212.8 | H113: 1240.7 | I113: 1348.9 | J113: =J314 -> 1395.0256 | K113: =K314 -> 1395.1116 | L113: =L314 -> 1384.5803 | M113: =M314 -> 1469.0185 | N113: =N314 -> 1549.9964 | O113: =O314 -> 1627.0581 | P113: =P314 -> 1699.1488 | Q113: =Q314 -> 1765.2367 | ... S113: =S314 -> 1875.5327
C114: Prepaid expense and accrued income | E114: 120.7 | F114: 190.4 | G114: 190.1 | H114: 243.8 | I114: 273.5 | J114: =J317 -> 248.80163 | K114: =K317 -> 261.9126 | L114: =L317 -> 279.39071 | M114: =M317 -> 296.42926 | N114: =N317 -> 312.76956 | O114: =O317 -> 328.31963 | P114: =P317 -> 342.86663 | Q114: =Q317 -> 356.20231 | ... S114: =S317 -> 378.45866
C115: Other current assets | E115: 19.4 | F115: 30.9 | G115: 25.5 | H115: 63.8 | I115: 58.4 | J115: =Assumptions!J90 -> 58.4 | K115: =Assumptions!K90 -> 58.4 | L115: =Assumptions!L90 -> 58.4 | M115: =Assumptions!M90 -> 58.4 | N115: =Assumptions!N90 -> 58.4 | O115: =Assumptions!O90 -> 58.4 | P115: =Assumptions!P90 -> 58.4 | Q115: =Assumptions!Q90 -> 58.4 | ... S115: =Assumptions!S90 -> 58.4
C116: Assets classified as held for sale | E116: 0 | F116: 33.7 | G116: 0 | H116: 0 | I116: 0 | J116: =Assumptions!J91 -> 0 | K116: =Assumptions!K91 -> 0 | L116: =Assumptions!L91 -> 0 | M116: =Assumptions!M91 -> 0 | N116: =Assumptions!N91 -> 0 | O116: =Assumptions!O91 -> 0 | P116: =Assumptions!P91 -> 0 | Q116: =Assumptions!Q91 -> 0 | ... S116: =Assumptions!S91 -> 0
C117: Current assets | E117: =SUM(E111:E116) -> 3634.6 | F117: =SUM(F111:F116) -> 4165.1 | G117: =SUM(G111:G116) -> 5021.3 | H117: =SUM(H111:H116) -> 4201.4 | I117: =SUM(I111:I116) -> 4563.3 | J117: =SUM(J111:J116) -> 4828.7662 | K117: =SUM(K111:K116) -> 5227.7534 | L117: =SUM(L111:L116) -> 5658.4929 | ... S117: =SUM(S111:S116) -> 10804.18
C119: Property, plant and equipment | E119: 1702.6 | F119: 1776.6 | G119: 2257.3 | H119: 2257.3 | I119: 2458.5 | J119: =J200+J205 -> 2573.4653 | K119: =K200+K205 -> 2672.526 | L119: =L200+L205 -> 2762.6444 | M119: =M200+M205 -> 2875.7154 | N119: =N200+N205 -> 3014.1754 | O119: =O200+O205 -> 3130.6564 | P119: =P200+P205 -> 3194.2045 | Q119: =Q200+Q205 -> 3199.8744 | ... S119: =S200+S205 -> 3294.8597
C120: Intangible assets | E120: 4172.3 | F120: 4373 | G120: 4229.1 | H120: 8223.6 | I120: 8616.1 | J120: =J210+J215 -> 8679.6303 | K120: =K210+K215 -> 8805.9734 | L120: =L210+L215 -> 8948.9006 | M120: =M210+M215 -> 9113.8177 | N120: =N210+N215 -> 9299.9842 | O120: =O210+O215 -> 9449.1622 | P120: =P210+P215 -> 9554.7412 | Q120: =Q210+Q215 -> 9578.9355 | ... S120: =S210+S215 -> 9373.3577
C121: Investments in associated companies | E121: 2.5 | F121: 9.2 | G121: 9.5 | H121: 19.1 | I121: 24.1 | J121: =Assumptions!J93 -> 24.1 | K121: =Assumptions!K93 -> 24.1 | L121: =Assumptions!L93 -> 24.1 | M121: =Assumptions!M93 -> 24.1 | N121: =Assumptions!N93 -> 24.1 | O121: =Assumptions!O93 -> 24.1 | P121: =Assumptions!P93 -> 24.1 | Q121: =Assumptions!Q93 -> 24.1 | ... S121: =Assumptions!S93 -> 24.1
C122: Deferred tax assets | E122: 194.7 | F122: 142.5 | G122: 144.8 | H122: 188.6 | I122: 150.7 | J122: =Assumptions!J94 -> 150.7 | K122: =Assumptions!K94 -> 150.7 | L122: =Assumptions!L94 -> 150.7 | M122: =Assumptions!M94 -> 150.7 | N122: =Assumptions!N94 -> 150.7 | O122: =Assumptions!O94 -> 150.7 | P122: =Assumptions!P94 -> 150.7 | Q122: =Assumptions!Q94 -> 150.7 | ... S122: =Assumptions!S94 -> 150.7
C123: Other non-current assets | E123: 87.3 | F123: 233.5 | G123: 92.2 | H123: 160.8 | I123: 164.5 | J123: =Assumptions!J95 -> 164.5 | K123: =Assumptions!K95 -> 164.5 | L123: =Assumptions!L95 -> 164.5 | M123: =Assumptions!M95 -> 164.5 | N123: =Assumptions!N95 -> 164.5 | O123: =Assumptions!O95 -> 164.5 | P123: =Assumptions!P95 -> 164.5 | Q123: =Assumptions!Q95 -> 164.5 | ... S123: =Assumptions!S95 -> 164.5
C124: Non-current assets | E124: =SUM(E119:E123) -> 6159.4 | F124: =SUM(F119:F123) -> 6534.8 | G124: =SUM(G119:G123) -> 6732.9 | H124: =SUM(H119:H123) -> 10849.4 | I124: =SUM(I119:I123) -> 11413.9 | J124: =SUM(J119:J123) -> 11592.396 | K124: =SUM(K119:K123) -> 11817.799 | L124: =SUM(L119:L123) -> 12050.845 | ... S124: =SUM(S119:S123) -> 13007.517
B126: x | C126: Assets | E126: =E117+E124 -> 9794 | F126: =F117+F124 -> 10699.9 | G126: =G117+G124 -> 11754.2 | H126: =H117+H124 -> 15050.8 | I126: =I117+I124 -> 15977.2 | J126: =J117+J124 -> 16421.162 | K126: =K117+K124 -> 17045.553 | L126: =L117+L124 -> 17709.338 | ... S126: =S117+S124 -> 23811.698
C128: Accounts payable | E128: 846.3 | F128: 1033.2 | G128: 1016.6 | H128: 1108.2 | I128: 1212.3 | J128: =J320 -> 1116.0205 | K128: =K320 -> 1163.0851 | L128: =L320 -> 1240.7008 | M128: =M320 -> 1316.3645 | N128: =N320 -> 1388.9275 | O128: =O320 -> 1457.9812 | P128: =P320 -> 1522.5807 | Q128: =Q320 -> 1581.8009 | ... S128: =S320 -> 1680.6355
C129: Accrued expenses and deferred income | E129: 454 | F129: 519.9 | G129: 489 | H129: 678.2 | I129: 623.9 | J129: =J323 -> 626.26059 | K129: =K323 -> 659.26233 | L129: =L323 -> 703.2566 | M129: =M323 -> 746.14449 | N129: =N323 -> 787.27477 | O129: =O323 -> 826.41598 | P129: =P323 -> 863.03235 | Q129: =Q323 -> 896.59971 | ... S129: =S323 -> 952.62133
C130: Financial liabilities | E130: 334.7 | F130: 334.9 | G130: 303 | H130: 1217.9 | I130: 337.4 | J130: =Assumptions!J97 -> 337.4 | K130: =Assumptions!K97 -> 337.4 | L130: =Assumptions!L97 -> 337.4 | M130: =Assumptions!M97 -> 337.4 | N130: =Assumptions!N97 -> 337.4 | O130: =Assumptions!O97 -> 337.4 | P130: =Assumptions!P97 -> 337.4 | Q130: =Assumptions!Q97 -> 337.4 | ... S130: =Assumptions!S97 -> 337.4
C131: Income tax liabilities | E131: 163.3 | F131: 170.3 | G131: 205.9 | H131: 365.4 | I131: 367.7 | J131: =Assumptions!J98 -> 367.7 | K131: =Assumptions!K98 -> 367.7 | L131: =Assumptions!L98 -> 367.7 | M131: =Assumptions!M98 -> 367.7 | N131: =Assumptions!N98 -> 367.7 | O131: =Assumptions!O98 -> 367.7 | P131: =Assumptions!P98 -> 367.7 | Q131: =Assumptions!Q98 -> 367.7 | ... S131: =Assumptions!S98 -> 367.7
C132: Provisions | E132: 26.8 | F132: 26 | G132: 26.9 | H132: 46.3 | I132: 44.1 | J132: =J326 -> 43.478963 | K132: =K326 -> 45.770152 | L132: =L326 -> 48.824511 | M132: =M326 -> 51.80206 | N132: =N326 -> 54.657583 | O132: =O326 -> 57.375013 | P132: =P326 -> 59.917153 | Q132: =Q326 -> 62.247611 | ... S132: =S326 -> 66.136985
C133: Liabilities classified as held for sale | E133: 0 | F133: 3.7 | G133: 0 | H133: 0 | I133: 0 | J133: =Assumptions!J99 -> 0 | K133: =Assumptions!K99 -> 0 | L133: =Assumptions!L99 -> 0 | M133: =Assumptions!M99 -> 0 | N133: =Assumptions!N99 -> 0 | O133: =Assumptions!O99 -> 0 | P133: =Assumptions!P99 -> 0 | Q133: =Assumptions!Q99 -> 0 | ... S133: =Assumptions!S99 -> 0
C134: Current liabilities | E134: =SUM(E128:E133) -> 1825.1 | F134: =SUM(F128:F133) -> 2088 | G134: =SUM(G128:G133) -> 2041.4 | H134: =SUM(H128:H133) -> 3416 | I134: =SUM(I128:I133) -> 2585.4 | J134: =SUM(J128:J133) -> 2490.86 | K134: =SUM(K128:K133) -> 2573.2176 | L134: =SUM(L128:L133) -> 2697.8819 | ... S134: =SUM(S128:S133) -> 3404.4938
C136: Financial liabilities | E136: 3851.9 | F136: 3393.9 | G136: 3634.2 | H136: 4732 | I136: 5424.8 | J136: =I136+J180 -> 5350.3754 | K136: =J136+K180 -> 5221.5052 | L136: =K136+L180 -> 5037.8096 | M136: =L136+M180 -> 5037.8096 | N136: =M136+N180 -> 5037.8096 | O136: =N136+O180 -> 5037.8096 | P136: =O136+P180 -> 5037.8096 | Q136: =P136+Q180 -> 5037.8096 | ... S136: =R136+S180 -> 5037.8096
C137: Provisions | E137: 98.3 | F137: 95.6 | G137: 78 | H137: 200.5 | I137: 183.1 | J137: =Assumptions!J101 -> 183.1 | K137: =Assumptions!K101 -> 183.1 | L137: =Assumptions!L101 -> 183.1 | M137: =Assumptions!M101 -> 183.1 | N137: =Assumptions!N101 -> 183.1 | O137: =Assumptions!O101 -> 183.1 | P137: =Assumptions!P101 -> 183.1 | Q137: =Assumptions!Q101 -> 183.1 | ... S137: =Assumptions!S101 -> 183.1
C138: Deferred tax liabilities | E138: 379.9 | F138: 367.2 | G138: 322.5 | H138: 404.7 | I138: 338.9 | J138: =Assumptions!J102 -> 338.9 | K138: =Assumptions!K102 -> 338.9 | L138: =Assumptions!L102 -> 338.9 | M138: =Assumptions!M102 -> 338.9 | N138: =Assumptions!N102 -> 338.9 | O138: =Assumptions!O102 -> 338.9 | P138: =Assumptions!P102 -> 338.9 | Q138: =Assumptions!Q102 -> 338.9 | ... S138: =Assumptions!S102 -> 338.9
C139: Employee benefit obligations | E139: 319.5 | F139: 322.9 | G139: 239.9 | H139: 328.6 | I139: 357.2 | J139: =Assumptions!J100 -> 357.2 | K139: =Assumptions!K100 -> 357.2 | L139: =Assumptions!L100 -> 357.2 | M139: =Assumptions!M100 -> 357.2 | N139: =Assumptions!N100 -> 357.2 | O139: =Assumptions!O100 -> 357.2 | P139: =Assumptions!P100 -> 357.2 | Q139: =Assumptions!Q100 -> 357.2 | ... S139: =Assumptions!S100 -> 357.2
C140: Other liabilities | E140: 31.3 | F140: 36.4 | G140: 36.1 | H140: 35.7 | I140: 41 | J140: =Assumptions!J104 -> 41 | K140: =Assumptions!K104 -> 41 | L140: =Assumptions!L104 -> 41 | M140: =Assumptions!M104 -> 41 | N140: =Assumptions!N104 -> 41 | O140: =Assumptions!O104 -> 41 | P140: =Assumptions!P104 -> 41 | Q140: =Assumptions!Q104 -> 41 | ... S140: =Assumptions!S104 -> 41
C141: Non-current liabilities | E141: =SUM(E136:E140) -> 4680.9 | F141: =SUM(F136:F140) -> 4216 | G141: =SUM(G136:G140) -> 4310.7 | H141: =SUM(H136:H140) -> 5701.5 | I141: =SUM(I136:I140) -> 6345 | J141: =SUM(J136:J140) -> 6270.5754 | K141: =SUM(K136:K140) -> 6141.7052 | L141: =SUM(L136:L140) -> 5958.0096 | ... S141: =SUM(S136:S140) -> 5958.0096
C143: Capital stock | E143: 1.4 | F143: 1.4 | G143: 1.5 | H143: 1.6 | I143: 1.6 | J143: =Assumptions!J114 -> 1.6 | K143: =Assumptions!K114 -> 1.6 | L143: =Assumptions!L114 -> 1.6 | M143: =Assumptions!M114 -> 1.6 | N143: =Assumptions!N114 -> 1.6 | O143: =Assumptions!O114 -> 1.6 | P143: =Assumptions!P114 -> 1.6 | Q143: =Assumptions!Q114 -> 1.6 | ... S143: =Assumptions!S114 -> 1.6
C144: Treasury shares | E144: -5.2 | F144: -10.7 | G144: -15.1 | H144: -11.9 | I144: -8.8 | J144: =I144+J184 -> -8.8 | K144: =J144+K184 -> -8.8 | L144: =K144+L184 -> -8.8 | M144: =L144+M184 -> -8.8 | N144: =M144+N184 -> -8.8 | O144: =N144+O184 -> -8.8 | P144: =O144+P184 -> -8.8 | Q144: =P144+Q184 -> -8.8 | ... S144: =R144+S184 -> -8.8
C145: Reserves | E145: 3289.6 | F145: 4403.1 | G145: 4979.8 | H145: 5930.7 | I145: 7040 | J145: =I145+J156+J183+J189 -> 7655.9756 | K145: =J145+K156+K183+K189 -> 8330.24 | L145: =K145+L156+L183+L189 -> 9056.7768 | M145: =L145+M156+M183+M189 -> 9822.1608 | N145: =M145+N156+N183+N189 -> 10616.496 | O145: =N145+O156+O183+O189 -> 11403.012 | P145: =O145+P156+P183+P189 -> 12181.445 | Q145: =P145+Q156+Q183+Q189 -> 12944.414 | ... S145: =R145+S156+S183+S189 -> 14487.78
...

Sheet DCF
B2: Free Cash Flow to Firm | E2: 2025 | F2: =E2+1 -> 2026 | G2: =F2+1 -> 2027 | H2: =G2+1 -> 2028 | I2: =H2+1 -> 2029 | J2: =I2+1 -> 2030 | K2: =J2+1 -> 2031 | L2: =K2+1 -> 2032 | M2: =L2+1 -> 2033 | N2: =M2+1 -> 2034
B4: Revenue | E4: ='3-Statement Model'!J24 -> 11315.208 | F4: ='3-Statement Model'!K24 -> 11911.479 | G4: ='3-Statement Model'!L24 -> 12706.363 | H4: ='3-Statement Model'!M24 -> 13481.257 | I4: ='3-Statement Model'!N24 -> 14224.394 | J4: ='3-Statement Model'!O24 -> 14931.593 | K4: ='3-Statement Model'!P24 -> 15593.174 | L4: ='3-Statement Model'!Q24 -> 16199.665 | ... N4: ='3-Statement Model'!S24 -> 17211.858
B5: % growth | E5: ='3-Statement Model'!J25 -> -0.038076041 | F5: ='3-Statement Model'!K25 -> 0.052696488 | G5: ='3-Statement Model'!L25 -> 0.066732569 | H5: ='3-Statement Model'!M25 -> 0.0609847 | I5: ='3-Statement Model'!N25 -> 0.055123749 | J5: ='3-Statement Model'!O25 -> 0.04971734 | K5: ='3-Statement Model'!P25 -> 0.04430744 | L5: ='3-Statement Model'!Q25 -> 0.038894673 | ... N5: ='3-Statement Model'!S25 -> 0.02806309
B7: EBITDA | E7: ='3-Statement Model'!J55 -> 2172.5199 | F7: ='3-Statement Model'!K55 -> 2418.0303 | G7: ='3-Statement Model'!L55 -> 2668.3362 | H7: ='3-Statement Model'!M55 -> 2871.5077 | I7: =I8*I4 -> 3029.796 | J7: =J8*J4 -> 3180.4294 | K7: =K8*K4 -> 3321.346 | L7: =L8*L4 -> 3450.5287 | M7: =M8*M4 -> 3566.0513 | N7: =N8*N4 -> 3666.1257
B8: % of revenue | E8: =E7/E4 -> 0.192 | F8: =F7/F4 -> 0.203 | G8: =G7/G4 -> 0.21 | H8: =H7/H4 -> 0.213 | I8: 0.213 | J8: =I8 -> 0.213 | K8: =J8 -> 0.213 | L8: =K8 -> 0.213 | M8: =L8 -> 0.213 | N8: =M8 -> 0.213
B10: D&A | E10: ='3-Statement Model'!J66 -> 598.54062 | F10: ='3-Statement Model'!K66 -> 640.68503 | G10: ='3-Statement Model'!L66 -> 684.13744 | H10: ='3-Statement Model'!M66 -> 694.98905 | I10: ='3-Statement Model'!N66 -> 661.2368 | J10: ='3-Statement Model'!O66 -> 706.51366 | K10: ='3-Statement Model'!P66 -> 729.64321 | L10: ='3-Statement Model'!Q66 -> 751.0445 | ... N10: ='3-Statement Model'!S66 -> 466.22568
B12: EBIT | E12: =E7-E10 -> 1573.9793 | F12: =F7-F10 -> 1777.3453 | G12: =G7-G10 -> 1984.1988 | H12: =H7-H10 -> 2176.5187 | I12: =I7-I10 -> 2368.5592 | J12: =J7-J10 -> 2473.9157 | K12: =K7-K10 -> 2591.7028 | L12: =L7-L10 -> 2699.4842 | ... N12: =N7-N10 -> 3199.9
B14: EBIT | E14: ='3-Statement Model'!J72 -> 1573.9793 | F14: ='3-Statement Model'!K72 -> 1777.3453 | G14: ='3-Statement Model'!L72 -> 1984.1988 | H14: ='3-Statement Model'!M72 -> 2176.5187 | I14: ='3-Statement Model'!N72 -> 2368.5592 | J14: ='3-Statement Model'!O72 -> 2473.9157 | K14: ='3-Statement Model'!P72 -> 2591.7028 | L14: ='3-Statement Model'!Q72 -> 2699.4842 | ... N14: ='3-Statement Model'!S72 -> 3199.9
B15: % of revenue | E15: ='3-Statement Model'!J73 -> 0.13910299 | F15: ='3-Statement Model'!K73 -> 0.14921281 | G15: ='3-Statement Model'!L73 -> 0.15615789 | H15: ='3-Statement Model'!M73 -> 0.16144776 | I15: ='3-Statement Model'!N73 -> 0.16651389 | J15: ='3-Statement Model'!O73 -> 0.1656833 | K15: ='3-Statement Model'!P73 -> 0.16620752 | L15: ='3-Statement Model'!Q73 -> 0.16663827 | ... N15: ='3-Statement Model'!S73 -> 0.18591253
B17: Taxes | E17: =E12*E18 -> 317.61552 | F17: =F12*F18 -> 358.65304 | G17: =G12*G18 -> 400.39431 | H17: =H12*H18 -> 439.2028 | I17: =I12*I18 -> 477.95493 | J17: =J12*J18 -> 499.21498 | K17: =K12*K18 -> 522.98341 | L17: =L12*L18 -> 544.73277 | ... N17: =N12*N18 -> 645.71239
B18: % tax rate | E18: =Assumptions!J50 -> 0.20179143 | F18: =Assumptions!K50 -> 0.20179143 | G18: =Assumptions!L50 -> 0.20179143 | H18: =Assumptions!M50 -> 0.20179143 | I18: =Assumptions!N50 -> 0.20179143 | J18: =Assumptions!O50 -> 0.20179143 | K18: =Assumptions!P50 -> 0.20179143 | L18: =Assumptions!Q50 -> 0.20179143 | ... N18: =Assumptions!S50 -> 0.20179143
B20: NOPAT | E20: =E12-E17 -> 1256.3637 | F20: =F12-F17 -> 1418.6923 | G20: =G12-G17 -> 1583.8045 | H20: =H12-H17 -> 1737.3158 | I20: =I12-I17 -> 1890.6042 | J20: =J12-J17 -> 1974.7007 | K20: =K12-K17 -> 2068.7194 | L20: =L12-L17 -> 2154.7514 | ... N20: =N12-N17 -> 2554.1876
B21: % of revenue | E21: =E20/E4 -> 0.1110332 | F21: =F20/F4 -> 0.11910294 | G21: =G20/G4 -> 0.12464656 | H21: =H20/H4 -> 0.12886898 | I21: =I20/I4 -> 0.13291281 | J21: =J20/J4 -> 0.13224983 | K21: =K20/K4 -> 0.13266827 | L21: =L20/L4 -> 0.1330121 | ... N21: =N20/N4 -> 0.14839698
B23: D&A | E23: ='3-Statement Model'!J158 -> 598.54062 | F23: ='3-Statement Model'!K158 -> 640.68503 | G23: ='3-Statement Model'!L158 -> 684.13744 | H23: ='3-Statement Model'!M158 -> 694.98905 | I23: ='3-Statement Model'!N158 -> 661.2368 | J23: ='3-Statement Model'!O158 -> 706.51366 | K23: ='3-Statement Model'!P158 -> 729.64321 | L23: ='3-Statement Model'!Q158 -> 751.0445 | ... N23: ='3-Statement Model'!S158 -> 466.22568
B24: Provisions | E24: ='3-Statement Model'!J159 -> -0.62103703 | F24: ='3-Statement Model'!K159 -> 2.2911886 | G24: ='3-Statement Model'!L159 -> 3.0543598 | H24: ='3-Statement Model'!M159 -> 2.9775482 | I24: ='3-Statement Model'!N159 -> 2.8555238 | J24: ='3-Statement Model'!O159 -> 2.7174296 | K24: ='3-Statement Model'!P159 -> 2.5421399 | L24: ='3-Statement Model'!Q159 -> 2.330458 | ... N24: ='3-Statement Model'!S159 -> 1.8053446
B25: Accounts receivable | E25: ='3-Statement Model'!J161 -> 35.960731 | F25: ='3-Statement Model'!K161 -> -47.451476 | G25: ='3-Statement Model'!L161 -> -73.371208 | H25: ='3-Statement Model'!M161 -> -137.817 | I25: ='3-Statement Model'!N161 -> -132.16905 | J25: ='3-Statement Model'!O161 -> -125.77731 | K25: ='3-Statement Model'!P161 -> -117.66396 | L25: ='3-Statement Model'!Q161 -> -107.86618 | ... N25: ='3-Statement Model'!S161 -> -83.561093
B26: Inventories | E26: ='3-Statement Model'!J162 -> -46.12561 | F26: ='3-Statement Model'!K162 -> -0.086021971 | G26: ='3-Statement Model'!L162 -> 10.531299 | H26: ='3-Statement Model'!M162 -> -84.438216 | I26: ='3-Statement Model'!N162 -> -80.97781 | J26: ='3-Statement Model'!O162 -> -77.061695 | K26: ='3-Statement Model'!P162 -> -72.090777 | L26: ='3-Statement Model'!Q162 -> -66.087837 | ... N26: ='3-Statement Model'!S162 -> -51.196511
B27: Prepaid expense and accrued income | E27: ='3-Statement Model'!J163 -> 24.698368 | F27: ='3-Statement Model'!K163 -> -13.110972 | G27: ='3-Statement Model'!L163 -> -17.478101 | H27: ='3-Statement Model'!M163 -> -17.038558 | I27: ='3-Statement Model'!N163 -> -16.340292 | J27: ='3-Statement Model'!O163 -> -15.55007 | K27: ='3-Statement Model'!P163 -> -14.547002 | L27: ='3-Statement Model'!Q163 -> -13.335685 | ... N27: ='3-Statement Model'!S163 -> -10.330805
B28: Other current assets | E28: ='3-Statement Model'!J164 -> 0 | F28: ='3-Statement Model'!K164 -> 0 | G28: ='3-Statement Model'!L164 -> 0 | H28: ='3-Statement Model'!M164 -> 0 | I28: ='3-Statement Model'!N164 -> 0 | J28: ='3-Statement Model'!O164 -> 0 | K28: ='3-Statement Model'!P164 -> 0 | L28: ='3-Statement Model'!Q164 -> 0 | ... N28: ='3-Statement Model'!S164 -> 0
B29: Accounts payable | E29: ='3-Statement Model'!J165 -> -96.279512 | F29: ='3-Statement Model'!K165 -> 47.064606 | G29: ='3-Statement Model'!L165 -> 77.615656 | H29: ='3-Statement Model'!M165 -> 75.663763 | I29: ='3-Statement Model'!N165 -> 72.562948 | J29: ='3-Statement Model'!O165 -> 69.053778 | K29: ='3-Statement Model'!P165 -> 64.599416 | L29: ='3-Statement Model'!Q165 -> 59.220276 | ... N29: ='3-Statement Model'!S165 -> 45.876391
B30: Accrued expenses and deferred income | E30: ='3-Statement Model'!J166 -> 2.3605938 | F30: ='3-Statement Model'!K166 -> 33.001734 | G30: ='3-Statement Model'!L166 -> 43.994269 | H30: ='3-Statement Model'!M166 -> 42.887893 | I30: ='3-Statement Model'!N166 -> 41.130282 | J30: ='3-Statement Model'!O166 -> 39.141207 | K30: ='3-Statement Model'!P166 -> 36.616376 | L30: ='3-Statement Model'!Q166 -> 33.567361 | ... N30: ='3-Statement Model'!S166 -> 26.003752
B31: Income tax liabilities | E31: ='3-Statement Model'!J167 -> 0 | F31: ='3-Statement Model'!K167 -> 0 | G31: ='3-Statement Model'!L167 -> 0 | H31: ='3-Statement Model'!M167 -> 0 | I31: ='3-Statement Model'!N167 -> 0 | J31: ='3-Statement Model'!O167 -> 0 | K31: ='3-Statement Model'!P167 -> 0 | L31: ='3-Statement Model'!Q167 -> 0 | ... N31: ='3-Statement Model'!S167 -> 0
B33: CapEx property, plant and equipment | E33: ='3-Statement Model'!J172 -> -498.20841 | F33: ='3-Statement Model'!K172 -> -522.68374 | G33: ='3-Statement Model'!L172 -> -555.31155 | H33: ='3-Statement Model'!M172 -> -587.11882 | I33: ='3-Statement Model'!N172 -> -576.64832 | J33: ='3-Statement Model'!O172 -> -597.7343 | K33: ='3-Statement Model'!P172 -> -565.62112 | L33: ='3-Statement Model'!Q172 -> -526.74439 | ... N33: ='3-Statement Model'!S172 -> -430.29644
B34: % of revenue | E34: =-E33/E4 -> 0.044029984 | F34: =-F33/F4 -> 0.043880674 | G34: =-G33/G4 -> 0.043703422 | H34: =-H33/H4 -> 0.043550748 | I34: =-I33/I4 -> 0.040539394 | J34: =-J33/J4 -> 0.040031515 | K34: =-K33/K4 -> 0.036273636 | L34: =-L33/L4 -> 0.032515757 | ... N34: =-N33/N4 -> 0.025
B36: CapEx intangibles | E36: ='3-Statement Model'!J173 -> -25.04757 | F36: ='3-Statement Model'!K173 -> -26.367489 | G36: ='3-Statement Model'!L173 -> -28.127059 | H36: ='3-Statement Model'!M173 -> -29.842379 | I36: ='3-Statement Model'!N173 -> -31.487403 | J36: ='3-Statement Model'!O173 -> -33.052873 | K36: ='3-Statement Model'!P173 -> -34.517361 | L36: ='3-Statement Model'!Q173 -> -35.859902 | ... N36: ='3-Statement Model'!S173 -> -38.100512
B37: % of revenue | E37: =-E36/E4 -> 0.00221362 | F37: =-F36/F4 -> 0.00221362 | G37: =-G36/G4 -> 0.00221362 | H37: =-H36/H4 -> 0.00221362 | I37: =-I36/I4 -> 0.00221362 | J37: =-J36/J4 -> 0.00221362 | K37: =-K36/K4 -> 0.00221362 | L37: =-L36/L4 -> 0.00221362 | ... N37: =-N36/N4 -> 0.00221362
B39: M&A investments | E39: ='3-Statement Model'!J174 -> -253.7802 | F39: ='3-Statement Model'!K174 -> -317.03763 | G39: ='3-Statement Model'!L174 -> -333.7444 | H39: ='3-Statement Model'!M174 -> -356.01602 | I39: ='3-Statement Model'!N174 -> -377.72755 | J39: ='3-Statement Model'!O174 -> -341.38546 | K39: ='3-Statement Model'!P174 -> -298.63187 | L39: ='3-Statement Model'!Q174 -> -218.30443 | ... N39: ='3-Statement Model'!S174 -> 0
B40: % of revenue | E40: =-E39/E4 -> 0.02242824 | F40: =-F39/F4 -> 0.026616142 | G40: =-G39/G4 -> 0.026265927 | H40: =-H39/H4 -> 0.026408222 | I40: =-I39/I4 -> 0.026554913 | J40: =-J39/J4 -> 0.022863298 | K40: =-K39/K4 -> 0.019151448 | L40: =-L39/L4 -> 0.013475861 | ... N40: =-N39/N4 -> 0
B42: FCFF | E42: =E20+SUM(E23:E31)+E33+E36+E39 -> 997.86171 | F42: =F20+SUM(F23:F31)+F33+F36+F39 -> 1214.9975 | G42: =G20+SUM(G23:G31)+G33+G36+G39 -> 1395.1052 | H42: =H20+SUM(H23:H31)+H33+H36+H39 -> 1341.5631 | I42: =I20+SUM(I23:I31)+I33+I36+I39 -> 1453.0394 | J42: =J20+SUM(J23:J31)+J33+J36+J39 -> 1601.5651 | K42: =K20+SUM(K23:K31)+K33+K36+K39 -> 1799.0485 | L42: =L20+SUM(L23:L31)+L33+L36+L39 -> 2032.7156 | ... N42: =N20+SUM(N23:N31)+N33+N36+N39 -> 2480.6134
B45: Last fiscal year end | D45: 45657
B46: End of the first fiscal year | D46: 46022
B47: Valuation date | D47: 45961
B48: Fraction of first year cash flows forecast => Stub period | D48: =YEARFRAC(D47,D46) -> 0.16666667
B49: FCF in the last year of explicit forecast 2034 | D49: =N59 -> 2480.6134
B50: EBITDA in last year of explicit forecast 2034 | D50: =N14+N23 -> 3666.1257
B51: WACC | D51: =WACC!D23 -> 0.080719126
B53: Fiscal year ended | D53: 45657 | E53: 46022 | F53: 46387 | G53: 46752 | H53: 47118 | I53: 47483 | J53: 47848 | K53: 48213 | L53: 48579 | M53: 48944 | N53: 49309
B55: FCFF | E55: =E42 -> 997.86171 | F55: =F42 -> 1214.9975 | G55: =G42 -> 1395.1052 | H55: =H42 -> 1341.5631 | I55: =I42 -> 1453.0394 | J55: =J42 -> 1601.5651 | K55: =K42 -> 1799.0485 | L55: =L42 -> 2032.7156 | ... N55: =N42 -> 2480.6134
D57: Val date | E57: 1 | F57: =E57+1 -> 2 | G57: =F57+1 -> 3 | H57: =G57+1 -> 4 | I57: =H57+1 -> 5 | J57: =I57+1 -> 6 | K57: =J57+1 -> 7 | L57: =K57+1 -> 8 | M57: =L57+1 -> 9 | N57: =M57+1 -> 10
B58: Date for disocunting cash flows - mid of the year | D58: 45982 | E58: =AVERAGE(D58,E53) -> 46002 | F58: =AVERAGE(E53,F53) -> 46204.5 | G58: =AVERAGE(F53,G53) -> 46569.5 | H58: =AVERAGE(G53,H53) -> 46935 | I58: =AVERAGE(H53,I53) -> 47300.5 | J58: =AVERAGE(I53,J53) -> 47665.5 | K58: =AVERAGE(J53,K53) -> 48030.5 | L58: =AVERAGE(K53,L53) -> 48396 | M58: =AVERAGE(L53,M53) -> 48761.5 | N58: =AVERAGE(M53,N53) -> 49126.5
B59: Unlevered FCF - adjusted for the stub perriod | E59: =((E58-D58)/366)*E55 -> 54.527962 | F59: =((F58-E58)/365)*F55 -> 674.07394 | G59: =((G58-F58)/365)*G55 -> 1395.1052 | H59: =((H58-G58)/365)*H55 -> 1343.4009 | I59: =((I58-H58)/365)*I55 -> 1455.0298 | J59: =((J58-I58)/365)*J55 -> 1601.5651 | K59: =((K58-J58)/365)*K55 -> 1799.0485 | L59: =((L58-K58)/365)*L55 -> 2035.5002 | M59: =((M58-L58)/365)*M55 -> 2298.4507 | N59: =((N58-M58)/365)*N55 -> 2480.6134
B60: Present value of unlevered free cash flows - mid of the year | E60: =E59/((1+$D$51)^((E58-$D$58)/365)) -> 54.296519 | F60: =F59/((1+$D$51)^((F58-$D$58)/365)) -> 642.91945 | G60: =G59/((1+$D$51)^((G58-$D$58)/365)) -> 1231.2412 | H60: =H59/((1+$D$51)^((H58-$D$58)/365)) -> 1096.9398 | I60: =I59/((1+$D$51)^((I58-$D$58)/365)) -> 1099.2337 | J60: =J59/((1+$D$51)^((J58-$D$58)/365)) -> 1119.5665 | K60: =K59/((1+$D$51)^((K58-$D$58)/365)) -> 1163.6847 | L60: =L59/((1+$D$51)^((L58-$D$58)/365)) -> 1218.1607 | ... N60: =N59/((1+$D$51)^((N58-$D$58)/365)) -> 1270.9272
B62: Mid of year assumption discounting year | E62: =(E58-$D$58)/365 -> 0.054794521 | F62: =(F58-$D$58)/365 -> 0.60958904 | G62: =(G58-$D$58)/365 -> 1.609589 | H62: =(H58-$D$58)/365 -> 2.6109589 | I62: =(I58-$D$58)/365 -> 3.6123288 | J62: =(J58-$D$58)/365 -> 4.6123288 | K62: =(K58-$D$58)/365 -> 5.6123288 | L62: =(L58-$D$58)/365 -> 6.6136986 | ... N62: =(N58-$D$58)/365 -> 8.6150685
B64: Terminal value - perpetuity growth
B65: Growth rate in perpetuity | C65: 0.028
B66: 2034 FCF x (1+g) | C66: =N59*(1+C65) -> 2550.0706
B67: Terminal value in 2034 | C67: =C66/(D51-C65) -> 48370.881
B68: Present value of terminal value | C68: =C67/(1+D51)^((N58-D58)/365) -> 24782.527
B69: Present value of FCF - Explicit forecast | C69: =SUM(E60:N60) -> 10169.622
B70: Enterpise Value (EV) | C70: =C68+C69 -> 34952.149
B72: Terminal value as of TEV | C72: =C68/C70 -> 0.70904159
B73: FCF as % of EV | C73: =C69/C70 -> 0.29095841
B74: Emplied TV exit EBITDA multiple | C74: =C67/D50 -> 13.194005
B76: Terminal value - EBITDA multiple approach
B77: Ebitda in last year of explicit forecast 2034 | C77: =D50 -> 3666.1257
B78: EBITDA multiple | C78: 13.1
B79: Terminal value in 2034 | C79: =C77*C78 -> 48026.247
B80: Present vlaue of terminal value | C80: =C79/(1+D51)^((N58-D58)/365) -> 24605.956
B81: Present value of FCF - explicit forecast | C81: =SUM(E60:N60) -> 10169.622
B82: Enterprise value (EV) | C82: =C80+C81 -> 34775.578
B84: Terminal value as % of TEV | C84: =C80/C82 -> 0.70756426
B85: FCF as % of TEV | C85: =C81/C82 -> 0.29243574
B86: Implied perpetuity growth rate | C86: =(C78*D51-D49/D50)/(C78+D49/D50) -> 0.02764027
B88: Enterprise value to equity value bridge
B90: Enterprise value | C90: =C70 -> 34952.149
B91: (+) Cash and cash equivalents | C91: 520.4
B92: (+) Securities | C92: =5.4+79.2 -> 84.6
B93: (+) Derivatives | C93: 30
B94: (+) Employee benefit assets | C94: 61.1
B95: (+) Deferred tax assets | C95: 136.8
B96: (+) Investments in associated companies | C96: 3.1
B97: (-) Derivatives | C97: 20.3
B98: (-) Bank loans | C98: 1073.8
B99: (-) Lease liabilities | C99: 434.2
B100: (-) Straight bonds | C100: 4680
B101: (-) Other financial liabilities | C101: 27.3
B102: (-) Non-controlling interest | C102: 11.1
B103: (-) Employee benefit obligations | C103: 345.9
B104: (-) Deferred tax liabilities | C104: 308.7
B105: (-) Provisions | C105: 171.5
B106: Implied equity value | C106: =C90+C91+C92+C93+C94+C95+C96-C97-C98-C99-C100-C101-C102-C103-C104-C105 -> 28715.349
B107: Basic shares outstanding (million) | C107: =160479293/1000000 -> 160.47929
B108: Treasury shares (million) | C108: =34778/1000000 -> 0.034778
B109: Diluted shares outstanding (million) | C109: =(C107-C108) -> 160.44452
B110: Implied share price | C110: =C106/C109 -> 178.9737
B113: Sensitivity analysis on per share value
F115: 2029 EBITDA Margin
C116: =C110 -> 178.9737 | D116: =E116-0.5% -> 0.203 | E116: =F116-0.5% -> 0.208 | F116: 0.213 | G116: =F116+0.5% -> 0.218 | H116: =G116+0.5% -> 0.223
C117: =C118-0.25% -> 0.023 | D117: 154.19148 | E117: 159.54927 | F117: 164.90705 | G117: 170.26484 | H117: 175.62263
B118: Terminal growht rate | C118: =C119-0.25% -> 0.0255 | D118: 160.53448 | E118: 166.07822 | F118: 171.62195 | G118: 177.16569 | H118: 182.70942
C119: 0.028 | D119: 167.47906 | E119: 173.22638 | F119: 178.9737 | G119: 184.72103 | H119: 190.46835
C120: =C119+0.25% -> 0.0305 | D120: 175.11507 | E120: 181.08625 | F120: 187.05742 | G120: 193.0286 | H120: 198.99978
C121: =C120+0.25% -> 0.033 | D121: 183.55118 | E121: 189.76967 | F121: 195.98816 | G121: 202.20664 | H121: 208.42513
F125: WACC
C126: =C110 -> 178.9737 | D126: =E126-0.25% -> 0.075719126 | E126: =F126-0.25% -> 0.078219126 | F126: 0.080719126 | G126: =F126+0.25% -> 0.083219126 | H126: =G126+0.25% -> 0.085719126
C127: =C128-0.25% -> 0.023 | D127: 185.94203 | E127: 174.94189 | F127: 164.90705 | G127: 155.71708 | H127: 147.27075
B128: Terminal growht rate | C128: =C129-0.25% -> 0.0255 | D128: 194.31632 | E128: 182.42445 | F128: 171.62195 | G128: 161.76705 | H128: 152.74152
C129: 0.028 | D129: 203.56805 | E129: 190.652 | F129: 178.9737 | G129: 168.36483 | H129: 158.6862
C130: =C129+0.25% -> 0.0305 | D130: 213.84278 | E130: 199.74163 | F130: 187.05742 | G130: 175.58836 | H130: 165.16917
C131: =C130+0.25% -> 0.033 | D131: 225.3201 | E131: 209.83633 | F131: 195.98816 | G131: 183.53108 | H131: 172.267
...

Sheet Assumptions
C2: Working Case | E2: Management
B5: x | C5: Assumptions | E5: 2020 | F5: =E5+1 -> 2021 | G5: =F5+1 -> 2022 | H5: =G5+1 -> 2023 | I5: =H5+1 -> 2024 | J5: =I5+1 -> 2025 | K5: =J5+1 -> 2026 | L5: =K5+1 -> 2027 | M5: =L5+1 -> 2028 | ... S5: =R5+1 -> 2034
B7: x | C7: Working Case | E7: 2020 | F7: 2021 | G7: 2022 | H7: 2023 | I7: 2024 | J7: 2025 | K7: 2026 | L7: 2027 | M7: 2028 | N7: 2029 | O7: 2029 | P7: 2029 | Q7: 2029 | R7: 2029 | S7: 2029
B9: x | C9: Revenue
C10: EMEA (% growth) | E10: =CHOOSE(MATCH($E$2,{"Management";"Conservative"},0),E119,#REF!) -> -- | F10: =CHOOSE(MATCH($E$2,{"Management";"Conservative"},0),F119,#REF!) -> 0.16478801 | G10: =CHOOSE(MATCH($E$2,{"Management";"Conservative"},0),G119,#REF!) -> 0.017708896 | H10: =CHOOSE(MATCH($E$2,{"Management";"Conservative"},0),H119,#REF!) -> 0.17767588 | I10: =CHOOSE(MATCH($E$2,{"Management";"Conservative"},0),I119,#REF!) -> 0.044162551 | J10: =CHOOSE(MATCH($E$2,{"Management";"Conservative"},0),J119,#REF!) -> -0.01204749 | K10: =CHOOSE(MATCH($E$2,{"Management";"Conservative"},0),K119,#REF!) -> 0.052486486 | L10: =CHOOSE(MATCH($E$2,{"Management";"Conservative"},0),L119,#REF!) -> 0.056324324 | ... S10: =CHOOSE(MATCH($E$2,{"Management";"Conservative"},0),S119,#REF!) -> 0.028
C11: Americas (% growth) | E11: =CHOOSE(MATCH($E$2,{"Management";"Conservative"},0),E120,#REF!) -> -- | F11: =CHOOSE(MATCH($E$2,{"Management";"Conservative"},0),F120,#REF!) -> 0.20634132 | G11: =CHOOSE(MATCH($E$2,{"Management";"Conservative"},0),G120,#REF!) -> 0.31560517 | H11: =CHOOSE(MATCH($E$2,{"Management";"Conservative"},0),H120,#REF!) -> 0.169845 | I11: =CHOOSE(MATCH($E$2,{"Management";"Conservative"},0),I120,#REF!) -> 0.096629995 | J11: =CHOOSE(MATCH($E$2,{"Management";"Conservative"},0),J120,#REF!) -> -0.041 | K11: =CHOOSE(MATCH($E$2,{"Management";"Conservative"},0),K120,#REF!) -> 0.045 | L11: =CHOOSE(MATCH($E$2,{"Management";"Conservative"},0),L120,#REF!) -> 0.08 | ... S11: =CHOOSE(MATCH($E$2,{"Management";"Conservative"},0),S120,#REF!) -> 0.0287
C12: Asia/Pacific (% growth) | E12: =CHOOSE(MATCH($E$2,{"Management";"Conservative"},0),E121,#REF!) -> -- | F12: =CHOOSE(MATCH($E$2,{"Management";"Conservative"},0),F121,#REF!) -> 0.20750885 | G12: =CHOOSE(MATCH($E$2,{"Management";"Conservative"},0),G121,#REF!) -> 0.12960738 | H12: =CHOOSE(MATCH($E$2,{"Management";"Conservative"},0),H121,#REF!) -> 0.11588531 | I12: =CHOOSE(MATCH($E$2,{"Management";"Conservative"},0),I121,#REF!) -> -0.019824628 | J12: =CHOOSE(MATCH($E$2,{"Management";"Conservative"},0),J121,#REF!) -> -0.085 | K12: =CHOOSE(MATCH($E$2,{"Management";"Conservative"},0),K121,#REF!) -> 0.066 | L12: =CHOOSE(MATCH($E$2,{"Management";"Conservative"},0),L121,#REF!) -> 0.067 | ... S12: =CHOOSE(MATCH($E$2,{"Management";"Conservative"},0),S121,#REF!) -> 0.0271
C13: Global Business (% growth) | E13: =CHOOSE(MATCH($E$2,{"Management";"Conservative"},0),E122,#REF!) -> -- | F13: =CHOOSE(MATCH($E$2,{"Management";"Conservative"},0),F122,#REF!) -> 0.040049482 | G13: =CHOOSE(MATCH($E$2,{"Management";"Conservative"},0),G122,#REF!) -> 0.19565864 | H13: =CHOOSE(MATCH($E$2,{"Management";"Conservative"},0),H122,#REF!) -> -1 | I13: =CHOOSE(MATCH($E$2,{"Management";"Conservative"},0),I122,#REF!) -> #DIV/0! | J13: =CHOOSE(MATCH($E$2,{"Management";"Conservative"},0),J122,#REF!) -> 0 | K13: =CHOOSE(MATCH($E$2,{"Management";"Conservative"},0),K122,#REF!) -> 0 | L13: =CHOOSE(MATCH($E$2,{"Management";"Conservative"},0),L122,#REF!) -> 0 | ... S13: =CHOOSE(MATCH($E$2,{"Management";"Conservative"},0),S122,#REF!) -> 0
B15: x | C15: COGS
C16: Cost of Goods Sold (% of revenue) | E16: =CHOOSE(MATCH($E$2,{"Management";"Conservative"},0),E125,#REF!) -> 0.45225703 | F16: =CHOOSE(MATCH($E$2,{"Management";"Conservative"},0),F125,#REF!) -> 0.48215038 | G16: =CHOOSE(MATCH($E$2,{"Management";"Conservative"},0),G125,#REF!) -> 0.50630016 | H16: =CHOOSE(MATCH($E$2,{"Management";"Conservative"},0),H125,#REF!) -> 0.46391899 | I16: =CHOOSE(MATCH($E$2,{"Management";"Conservative"},0),I125,#REF!) -> 0.45456555 | J16: =CHOOSE(MATCH($E$2,{"Management";"Conservative"},0),J125,#REF!) -> 0.45 | K16: =CHOOSE(MATCH($E$2,{"Management";"Conservative"},0),K125,#REF!) -> 0.45 | L16: =CHOOSE(MATCH($E$2,{"Management";"Conservative"},0),L125,#REF!) -> 0.45 | ... S16: =CHOOSE(MATCH($E$2,{"Management";"Conservative"},0),S125,#REF!) -> 0.45
B18: x | C18: OpEx
C19: Personnel Expenses (% of revenue) | E19: =CHOOSE(MATCH($E$2,{"Management";"Conservative"},0),E128,#REF!) -> 0.19370113 | F19: =CHOOSE(MATCH($E$2,{"Management";"Conservative"},0),F128,#REF!) -> 0.17674524 | G19: =CHOOSE(MATCH($E$2,{"Management";"Conservative"},0),G128,#REF!) -> 0.16303208 | H19: =CHOOSE(MATCH($E$2,{"Management";"Conservative"},0),H128,#REF!) -> 0.17856317 | I19: =CHOOSE(MATCH($E$2,{"Management";"Conservative"},0),I128,#REF!) -> 0.18223087 | J19: =CHOOSE(MATCH($E$2,{"Management";"Conservative"},0),J128,#REF!) -> 0.189 | K19: =CHOOSE(MATCH($E$2,{"Management";"Conservative"},0),K128,#REF!) -> 0.182 | L19: =CHOOSE(MATCH($E$2,{"Management";"Conservative"},0),L128,#REF!) -> 0.177 | ... S19: =CHOOSE(MATCH($E$2,{"Management";"Conservative"},0),S128,#REF!) -> 0.177
C20: Production and Operations (% of revenue) | E20: =CHOOSE(MATCH($E$2,{"Management";"Conservative"},0),E129,#REF!) -> 0.050713415 | F20: =CHOOSE(MATCH($E$2,{"Management";"Conservative"},0),F129,#REF!) -> 0.050419896 | G20: =CHOOSE(MATCH($E$2,{"Management";"Conservative"},0),G129,#REF!) -> 0.047513296 | H20: =CHOOSE(MATCH($E$2,{"Management";"Conservative"},0),H129,#REF!) -> 0.051029488 | I20: =CHOOSE(MATCH($E$2,{"Management";"Conservative"},0),I129,#REF!) -> 0.052843213 | J20: =CHOOSE(MATCH($E$2,{"Management";"Conservative"},0),J129,#REF!) -> 0.052 | K20: =CHOOSE(MATCH($E$2,{"Management";"Conservative"},0),K129,#REF!) -> 0.051 | L20: =CHOOSE(MATCH($E$2,{"Management";"Conservative"},0),L129,#REF!) -> 0.05 | ... S20: =CHOOSE(MATCH($E$2,{"Management";"Conservative"},0),S129,#REF!) -> 0.049
C21: Logistics and Distribution (% of revenue) | E21: =CHOOSE(MATCH($E$2,{"Management";"Conservative"},0),E130,#REF!) -> 0.050979994 | F21: =CHOOSE(MATCH($E$2,{"Management";"Conservative"},0),F130,#REF!) -> 0.051554749 | G21: =CHOOSE(MATCH($E$2,{"Management";"Conservative"},0),G130,#REF!) -> 0.049505328 | H21: =CHOOSE(MATCH($E$2,{"Management";"Conservative"},0),H130,#REF!) -> 0.050371043 | I21: =CHOOSE(MATCH($E$2,{"Management";"Conservative"},0),I130,#REF!) -> 0.051457524 | J21: =CHOOSE(MATCH($E$2,{"Management";"Conservative"},0),J130,#REF!) -> 0.05 | K21: =CHOOSE(MATCH($E$2,{"Management";"Conservative"},0),K130,#REF!) -> 0.049 | L21: =CHOOSE(MATCH($E$2,{"Management";"Conservative"},0),L130,#REF!) -> 0.049 | ... S21: =CHOOSE(MATCH($E$2,{"Management";"Conservative"},0),S130,#REF!) -> 0.048
C22: Sales, Marketing and Travel Costs (% of revenue) | E22: =CHOOSE(MATCH($E$2,{"Management";"Conservative"},0),E131,#REF!) -> 0.02691175 | F22: =CHOOSE(MATCH($E$2,{"Management";"Conservative"},0),F131,#REF!) -> 0.025409898 | G22: =CHOOSE(MATCH($E$2,{"Management";"Conservative"},0),G131,#REF!) -> 0.028927353 | H22: =CHOOSE(MATCH($E$2,{"Management";"Conservative"},0),H131,#REF!) -> 0.03296674 | I22: =CHOOSE(MATCH($E$2,{"Management";"Conservative"},0),I131,#REF!) -> 0.031530804 | J22: =CHOOSE(MATCH($E$2,{"Management";"Conservative"},0),J131,#REF!) -> 0.031 | K22: =CHOOSE(MATCH($E$2,{"Management";"Conservative"},0),K131,#REF!) -> 0.03 | L22: =CHOOSE(MATCH($E$2,{"Management";"Conservative"},0),L131,#REF!) -> 0.029 | ... S22: =CHOOSE(MATCH($E$2,{"Management";"Conservative"},0),S131,#REF!) -> 0.029
C23: Administration Costs (% of revenue) | E23: =CHOOSE(MATCH($E$2,{"Management";"Conservative"},0),E132,#REF!) -> 0.035315324 | F23: =CHOOSE(MATCH($E$2,{"Management";"Conservative"},0),F132,#REF!) -> 0.025874647 | G23: =CHOOSE(MATCH($E$2,{"Management";"Conservative"},0),G132,#REF!) -> 0.017508912 | H23: =CHOOSE(MATCH($E$2,{"Management";"Conservative"},0),H132,#REF!) -> 0.041215098 | I23: =CHOOSE(MATCH($E$2,{"Management";"Conservative"},0),I132,#REF!) -> 0.034438201 | J23: =CHOOSE(MATCH($E$2,{"Management";"Conservative"},0),J132,#REF!) -> 0.036 | K23: =CHOOSE(MATCH($E$2,{"Management";"Conservative"},0),K132,#REF!) -> 0.035 | L23: =CHOOSE(MATCH($E$2,{"Management";"Conservative"},0),L132,#REF!) -> 0.035 | ... S23: =CHOOSE(MATCH($E$2,{"Management";"Conservative"},0),S132,#REF!) -> 0.034
C25: CapEx
C26: Own property, plant and equipment | E26: =CHOOSE(MATCH($E$2,{"Management";"Conservative"},0),E135,#REF!) -> 120.1 | F26: =CHOOSE(MATCH($E$2,{"Management";"Conservative"},0),F135,#REF!) -> 157.3 | G26: =CHOOSE(MATCH($E$2,{"Management";"Conservative"},0),G135,#REF!) -> 238 | H26: =CHOOSE(MATCH($E$2,{"Management";"Conservative"},0),H135,#REF!) -> 256.8 | I26: =CHOOSE(MATCH($E$2,{"Management";"Conservative"},0),I135,#REF!) -> 331.1 | J26: =CHOOSE(MATCH($E$2,{"Management";"Conservative"},0),J135,#REF!) -> 373.20623 | K26: =CHOOSE(MATCH($E$2,{"Management";"Conservative"},0),K135,#REF!) -> 391.09438 | L26: =CHOOSE(MATCH($E$2,{"Management";"Conservative"},0),L135,#REF!) -> 414.94089 | ... S26: =CHOOSE(MATCH($E$2,{"Management";"Conservative"},0),S135,#REF!) -> 292.60158
C27: % of revenue | E27: =CHOOSE(MATCH($E$2,{"Management";"Conservative"},0),E136,#REF!) -> 0.01524576 | F27: =CHOOSE(MATCH($E$2,{"Management";"Conservative"},0),F136,#REF!) -> 0.017001178 | G27: =CHOOSE(MATCH($E$2,{"Management";"Conservative"},0),G136,#REF!) -> 0.022684382 | H27: =CHOOSE(MATCH($E$2,{"Management";"Conservative"},0),H136,#REF!) -> 0.022849821 | I27: =CHOOSE(MATCH($E$2,{"Management";"Conservative"},0),I136,#REF!) -> 0.028147342 | J27: =CHOOSE(MATCH($E$2,{"Management";"Conservative"},0),J136,#REF!) -> 0.03 | K27: =CHOOSE(MATCH($E$2,{"Management";"Conservative"},0),K136,#REF!) -> 0.03 | L27: =CHOOSE(MATCH($E$2,{"Management";"Conservative"},0),L136,#REF!) -> 0.03 | ... S27: =CHOOSE(MATCH($E$2,{"Management";"Conservative"},0),S136,#REF!) -> 0.017
C28: Right-of-use assets | E28: =CHOOSE(MATCH($E$2,{"Management";"Conservative"},0),E137,#REF!) -> 72.4 | F28: =CHOOSE(MATCH($E$2,{"Management";"Conservative"},0),F137,#REF!) -> 75.7 | G28: =CHOOSE(MATCH($E$2,{"Management";"Conservative"},0),G137,#REF!) -> 104.5 | H28: =CHOOSE(MATCH($E$2,{"Management";"Conservative"},0),H137,#REF!) -> 120 | I28: =CHOOSE(MATCH($E$2,{"Management";"Conservative"},0),I137,#REF!) -> 134.3 | J28: =CHOOSE(MATCH($E$2,{"Management";"Conservative"},0),J137,#REF!) -> 125.00218 | K28: =CHOOSE(MATCH($E$2,{"Management";"Conservative"},0),K137,#REF!) -> 131.58936 | L28: =CHOOSE(MATCH($E$2,{"Management";"Conservative"},0),L137,#REF!) -> 140.37065 | ... S28: =CHOOSE(MATCH($E$2,{"Management";"Conservative"},0),S137,#REF!) -> 137.69486
C29: % of revenu | E29: =CHOOSE(MATCH($E$2,{"Management";"Conservative"},0),E138,#REF!) -> 0.0091906164 | F29: =CHOOSE(MATCH($E$2,{"Management";"Conservative"},0),F138,#REF!) -> 0.0081817494 | G29: =CHOOSE(MATCH($E$2,{"Management";"Conservative"},0),G138,#REF!) -> 0.0099601594 | H29: =CHOOSE(MATCH($E$2,{"Management";"Conservative"},0),H138,#REF!) -> 0.010677487 | I29: =CHOOSE(MATCH($E$2,{"Management";"Conservative"},0),I138,#REF!) -> 0.011417058 | J29: =CHOOSE(MATCH($E$2,{"Management";"Conservative"},0),J138,#REF!) -> 0.011047272 | K29: =CHOOSE(MATCH($E$2,{"Management";"Conservative"},0),K138,#REF!) -> 0.011047272 | L29: =CHOOSE(MATCH($E$2,{"Management";"Conservative"},0),L138,#REF!) -> 0.011047272 | ... S29: =CHOOSE(MATCH($E$2,{"Management";"Conservative"},0),S138,#REF!) -> 0.008
C30: Intangible assets | E30: =CHOOSE(MATCH($E$2,{"Management";"Conservative"},0),E139,#REF!) -> 11.6 | F30: =CHOOSE(MATCH($E$2,{"Management";"Conservative"},0),F139,#REF!) -> 13.5 | G30: =CHOOSE(MATCH($E$2,{"Management";"Conservative"},0),G139,#REF!) -> 28 | H30: =CHOOSE(MATCH($E$2,{"Management";"Conservative"},0),H139,#REF!) -> 23.1 | I30: =CHOOSE(MATCH($E$2,{"Management";"Conservative"},0),I139,#REF!) -> 27.9 | J30: =CHOOSE(MATCH($E$2,{"Management";"Conservative"},0),J139,#REF!) -> 25.04757 | K30: =CHOOSE(MATCH($E$2,{"Management";"Conservative"},0),K139,#REF!) -> 26.367489 | L30: =CHOOSE(MATCH($E$2,{"Management";"Conservative"},0),L139,#REF!) -> 28.127059 | ... S30: =CHOOSE(MATCH($E$2,{"Management";"Conservative"},0),S139,#REF!) -> 38.100512
C31: % of revenue | E31: =CHOOSE(MATCH($E$2,{"Management";"Conservative"},0),E140,#REF!) -> 0.0014725297 | F31: =CHOOSE(MATCH($E$2,{"Management";"Conservative"},0),F140,#REF!) -> 0.0014590967 | G31: =CHOOSE(MATCH($E$2,{"Management";"Conservative"},0),G140,#REF!) -> 0.0026687508 | H31: =CHOOSE(MATCH($E$2,{"Management";"Conservative"},0),H140,#REF!) -> 0.0020554162 | I31: =CHOOSE(MATCH($E$2,{"Management";"Conservative"},0),I140,#REF!) -> 0.0023718238 | J31: =CHOOSE(MATCH($E$2,{"Management";"Conservative"},0),J140,#REF!) -> 0.00221362 | K31: =CHOOSE(MATCH($E$2,{"Management";"Conservative"},0),K140,#REF!) -> 0.00221362 | L31: =CHOOSE(MATCH($E$2,{"Management";"Conservative"},0),L140,#REF!) -> 0.00221362 | ... S31: =CHOOSE(MATCH($E$2,{"Management";"Conservative"},0),S140,#REF!) -> 0.00221362
C33: M&A Investments
C34: % revenue growth trough M&A | J34: =CHOOSE(MATCH($E$2,{"Management";"Conservative"},0),J143,#REF!) -> 0.010787131 | K34: =CHOOSE(MATCH($E$2,{"Management";"Conservative"},0),K143,#REF!) -> 0.01400936 | L34: =CHOOSE(MATCH($E$2,{"Management";"Conservative"},0),L143,#REF!) -> 0.01400936 | M34: =CHOOSE(MATCH($E$2,{"Management";"Conservative"},0),M143,#REF!) -> 0.01400936 | N34: =CHOOSE(MATCH($E$2,{"Management";"Conservative"},0),N143,#REF!) -> 0.01400936 | O34: =CHOOSE(MATCH($E$2,{"Management";"Conservative"},0),O143,#REF!) -> 0.012 | P34: =CHOOSE(MATCH($E$2,{"Management";"Conservative"},0),P143,#REF!) -> 0.01 | Q34: =CHOOSE(MATCH($E$2,{"Management";"Conservative"},0),Q143,#REF!) -> 0.007 | ... S34: =CHOOSE(MATCH($E$2,{"Management";"Conservative"},0),S143,#REF!) -> 0
C35: Revenue growth through M&A | J35: =CHOOSE(MATCH($E$2,{"Management";"Conservative"},0),J144,#REF!) -> 126.8901 | K35: =CHOOSE(MATCH($E$2,{"Management";"Conservative"},0),K144,#REF!) -> 158.51882 | L35: =CHOOSE(MATCH($E$2,{"Management";"Conservative"},0),L144,#REF!) -> 166.8722 | M35: =CHOOSE(MATCH($E$2,{"Management";"Conservative"},0),M144,#REF!) -> 178.00801 | N35: =CHOOSE(MATCH($E$2,{"Management";"Conservative"},0),N144,#REF!) -> 188.86378 | O35: =CHOOSE(MATCH($E$2,{"Management";"Conservative"},0),O144,#REF!) -> 170.69273 | P35: =CHOOSE(MATCH($E$2,{"Management";"Conservative"},0),P144,#REF!) -> 149.31593 | Q35: =CHOOSE(MATCH($E$2,{"Management";"Conservative"},0),Q144,#REF!) -> 109.15222 | ... S35: =CHOOSE(MATCH($E$2,{"Management";"Conservative"},0),S144,#REF!) -> 0
C36: Average EV/Revenue multiple M&A | J36: =CHOOSE(MATCH($E$2,{"Management";"Conservative"},0),J145,#REF!) -> 2 | K36: =CHOOSE(MATCH($E$2,{"Management";"Conservative"},0),K145,#REF!) -> 2 | L36: =CHOOSE(MATCH($E$2,{"Management";"Conservative"},0),L145,#REF!) -> 2 | M36: =CHOOSE(MATCH($E$2,{"Management";"Conservative"},0),M145,#REF!) -> 2 | N36: =CHOOSE(MATCH($E$2,{"Management";"Conservative"},0),N145,#REF!) -> 2 | O36: =CHOOSE(MATCH($E$2,{"Management";"Conservative"},0),O145,#REF!) -> 2 | P36: =CHOOSE(MATCH($E$2,{"Management";"Conservative"},0),P145,#REF!) -> 2 | Q36: =CHOOSE(MATCH($E$2,{"Management";"Conservative"},0),Q145,#REF!) -> 2 | ... S36: =CHOOSE(MATCH($E$2,{"Management";"Conservative"},0),S145,#REF!) -> 2
C37: M&A Investments | J37: =CHOOSE(MATCH($E$2,{"Management";"Conservative"},0),J146,#REF!) -> 253.7802 | K37: =CHOOSE(MATCH($E$2,{"Management";"Conservative"},0),K146,#REF!) -> 317.03763 | L37: =CHOOSE(MATCH($E$2,{"Management";"Conservative"},0),L146,#REF!) -> 333.7444 | M37: =CHOOSE(MATCH($E$2,{"Management";"Conservative"},0),M146,#REF!) -> 356.01602 | N37: =CHOOSE(MATCH($E$2,{"Management";"Conservative"},0),N146,#REF!) -> 377.72755 | O37: =CHOOSE(MATCH($E$2,{"Management";"Conservative"},0),O146,#REF!) -> 341.38546 | P37: =CHOOSE(MATCH($E$2,{"Management";"Conservative"},0),P146,#REF!) -> 298.63187 | Q37: =CHOOSE(MATCH($E$2,{"Management";"Conservative"},0),Q146,#REF!) -> 218.30443 | ... S37: =CHOOSE(MATCH($E$2,{"Management";"Conservative"},0),S146,#REF!) -> 0
B39: x | C39: Interest
C40: Interest Income | E40: =CHOOSE(MATCH($E$2,{"Management";"Conservative"},0),E149,#REF!) -> 5.5 | F40: =CHOOSE(MATCH($E$2,{"Management";"Conservative"},0),F149,#REF!) -> 11.5 | G40: =CHOOSE(MATCH($E$2,{"Management";"Conservative"},0),G149,#REF!) -> 19 | H40: =CHOOSE(MATCH($E$2,{"Management";"Conservative"},0),H149,#REF!) -> 30.9 | I40: =CHOOSE(MATCH($E$2,{"Management";"Conservative"},0),I149,#REF!) -> 26.6 | J40: =CHOOSE(MATCH($E$2,{"Management";"Conservative"},0),J149,#REF!) -> 14.626968 | K40: =CHOOSE(MATCH($E$2,{"Management";"Conservative"},0),K149,#REF!) -> 20.415726 | L40: =CHOOSE(MATCH($E$2,{"Management";"Conservative"},0),L149,#REF!) -> 27.410596 | ... S40: =CHOOSE(MATCH($E$2,{"Management";"Conservative"},0),S149,#REF!) -> 97.553834
C41: Implied Interest rate % | F41: =CHOOSE(MATCH($E$2,{"Management";"Conservative"},0),F150,#REF!) -> 0.0087207098 | G41: =CHOOSE(MATCH($E$2,{"Management";"Conservative"},0),G150,#REF!) -> 0.016170213 | H41: =CHOOSE(MATCH($E$2,{"Management";"Conservative"},0),H150,#REF!) -> 0.016494955 | I41: =CHOOSE(MATCH($E$2,{"Management";"Conservative"},0),I150,#REF!) -> 0.041310763 | J41: =CHOOSE(MATCH($E$2,{"Management";"Conservative"},0),J150,#REF!) -> 0.02067416 | K41: =CHOOSE(MATCH($E$2,{"Management";"Conservative"},0),K150,#REF!) -> 0.02067416 | L41: =CHOOSE(MATCH($E$2,{"Management";"Conservative"},0),L150,#REF!) -> 0.02067416 | M41: =CHOOSE(MATCH($E$2,{"Management";"Conservative"},0),M150,#REF!) -> 0.02067416 | ... S41: =CHOOSE(MATCH($E$2,{"Management";"Conservative"},0),S150,#REF!) -> 0.02067416
C43: Other Financial Income | E43: =CHOOSE(MATCH($E$2,{"Management";"Conservative"},0),E152,#REF!) -> 6 | F43: =CHOOSE(MATCH($E$2,{"Management";"Conservative"},0),F152,#REF!) -> 7 | G43: =CHOOSE(MATCH($E$2,{"Management";"Conservative"},0),G152,#REF!) -> 6.9 | H43: =CHOOSE(MATCH($E$2,{"Management";"Conservative"},0),H152,#REF!) -> 7.3 | I43: =CHOOSE(MATCH($E$2,{"Management";"Conservative"},0),I152,#REF!) -> 7.3 | J43: =CHOOSE(MATCH($E$2,{"Management";"Conservative"},0),J152,#REF!) -> 6.9 | K43: =CHOOSE(MATCH($E$2,{"Management";"Conservative"},0),K152,#REF!) -> 6.9 | L43: =CHOOSE(MATCH($E$2,{"Management";"Conservative"},0),L152,#REF!) -> 6.9 | ... S43: =CHOOSE(MATCH($E$2,{"Management";"Conservative"},0),S152,#REF!) -> 6.9
C44: Other Financial Expenses | E44: =CHOOSE(MATCH($E$2,{"Management";"Conservative"},0),E153,#REF!) -> 24.7 | F44: =CHOOSE(MATCH($E$2,{"Management";"Conservative"},0),F153,#REF!) -> 17.8 | G44: =CHOOSE(MATCH($E$2,{"Management";"Conservative"},0),G153,#REF!) -> 48.4 | H44: =CHOOSE(MATCH($E$2,{"Management";"Conservative"},0),H153,#REF!) -> 86.3 | I44: =CHOOSE(MATCH($E$2,{"Management";"Conservative"},0),I153,#REF!) -> 2.5 | J44: =CHOOSE(MATCH($E$2,{"Management";"Conservative"},0),J153,#REF!) -> 23.35 | K44: =CHOOSE(MATCH($E$2,{"Management";"Conservative"},0),K153,#REF!) -> 23.35 | L44: =CHOOSE(MATCH($E$2,{"Management";"Conservative"},0),L153,#REF!) -> 23.35 | ... S44: =CHOOSE(MATCH($E$2,{"Management";"Conservative"},0),S153,#REF!) -> 23.35
C46: Income from Associated Companies | E46: =CHOOSE(MATCH($E$2,{"Management";"Conservative"},0),E155,#REF!) -> 0.5 | F46: =CHOOSE(MATCH($E$2,{"Management";"Conservative"},0),F155,#REF!) -> 0.4 | G46: =CHOOSE(MATCH($E$2,{"Management";"Conservative"},0),G155,#REF!) -> 0.4 | H46: =CHOOSE(MATCH($E$2,{"Management";"Conservative"},0),H155,#REF!) -> 1.1 | I46: =CHOOSE(MATCH($E$2,{"Management";"Conservative"},0),I155,#REF!) -> 3.6 | J46: =CHOOSE(MATCH($E$2,{"Management";"Conservative"},0),J155,#REF!) -> 3.6 | K46: =CHOOSE(MATCH($E$2,{"Management";"Conservative"},0),K155,#REF!) -> 3.6 | L46: =CHOOSE(MATCH($E$2,{"Management";"Conservative"},0),L155,#REF!) -> 3.6 | ... S46: =CHOOSE(MATCH($E$2,{"Management";"Conservative"},0),S155,#REF!) -> 3.6
C47: % of investments in associated companies | E47: =CHOOSE(MATCH($E$2,{"Management";"Conservative"},0),E156,#REF!) -> 0.2 | F47: =CHOOSE(MATCH($E$2,{"Management";"Conservative"},0),F156,#REF!) -> 0.043478261 | G47: =CHOOSE(MATCH($E$2,{"Management";"Conservative"},0),G156,#REF!) -> 0.042105263 | H47: =CHOOSE(MATCH($E$2,{"Management";"Conservative"},0),H156,#REF!) -> 0.057591623 | I47: =CHOOSE(MATCH($E$2,{"Management";"Conservative"},0),I156,#REF!) -> 0.14937759 | J47: =CHOOSE(MATCH($E$2,{"Management";"Conservative"},0),J156,#REF!) -> 0.14937759 | K47: =CHOOSE(MATCH($E$2,{"Management";"Conservative"},0),K156,#REF!) -> 0.14937759 | L47: =CHOOSE(MATCH($E$2,{"Management";"Conservative"},0),L156,#REF!) -> 0.14937759 | ... S47: =CHOOSE(MATCH($E$2,{"Management";"Conservative"},0),S156,#REF!) -> 0.14937759
B49: x | C49: Taxes
C50: Tax rate (% of EBT) | E50: =CHOOSE(MATCH($E$2,{"Management";"Conservative"},0),E159,#REF!) -> 0.22187647 | F50: =CHOOSE(MATCH($E$2,{"Management";"Conservative"},0),F159,#REF!) -> 0.21822742 | G50: =CHOOSE(MATCH($E$2,{"Management";"Conservative"},0),G159,#REF!) -> 0.22406888 | H50: =CHOOSE(MATCH($E$2,{"Management";"Conservative"},0),H159,#REF!) -> 0.20487878 | I50: =CHOOSE(MATCH($E$2,{"Management";"Conservative"},0),I159,#REF!) -> 0.20179143 | J50: =CHOOSE(MATCH($E$2,{"Management";"Conservative"},0),J159,#REF!) -> 0.20179143 | K50: =CHOOSE(MATCH($E$2,{"Management";"Conservative"},0),K159,#REF!) -> 0.20179143 | L50: =CHOOSE(MATCH($E$2,{"Management";"Conservative"},0),L159,#REF!) -> 0.20179143 | ... S50: =CHOOSE(MATCH($E$2,{"Management";"Conservative"},0),S159,#REF!) -> 0.20179143
B52: x | C52: Impairment (% or revenue)
C53: Impairment (% or revenue) | E53: =CHOOSE(MATCH($E$2,{"Management";"Conservative"},0),E162,#REF!) -> 0 | F53: =CHOOSE(MATCH($E$2,{"Management";"Conservative"},0),F162,#REF!) -> 0 | G53: =CHOOSE(MATCH($E$2,{"Management";"Conservative"},0),G162,#REF!) -> 0 | H53: =CHOOSE(MATCH($E$2,{"Management";"Conservative"},0),H162,#REF!) -> 0.00091648426 | I53: =CHOOSE(MATCH($E$2,{"Management";"Conservative"},0),I162,#REF!) -> 0 | J53: =CHOOSE(MATCH($E$2,{"Management";"Conservative"},0),J162,#REF!) -> 0 | K53: =CHOOSE(MATCH($E$2,{"Management";"Conservative"},0),K162,#REF!) -> 0 | L53: =CHOOSE(MATCH($E$2,{"Management";"Conservative"},0),L162,#REF!) -> 0 | ... S53: =CHOOSE(MATCH($E$2,{"Management";"Conservative"},0),S162,#REF!) -> 0
C55: Net Income
C56: NCI net income | E56: =CHOOSE(MATCH($E$2,{"Management";"Conservative"},0),E165,#REF!) -> 0.6 | F56: =CHOOSE(MATCH($E$2,{"Management";"Conservative"},0),F165,#REF!) -> 0.6 | G56: =CHOOSE(MATCH($E$2,{"Management";"Conservative"},0),G165,#REF!) -> 0 | H56: =CHOOSE(MATCH($E$2,{"Management";"Conservative"},0),H165,#REF!) -> 0.6 | I56: =CHOOSE(MATCH($E$2,{"Management";"Conservative"},0),I165,#REF!) -> 2.1 | J56: =CHOOSE(MATCH($E$2,{"Management";"Conservative"},0),J165,#REF!) -> 2.0933134 | K56: =CHOOSE(MATCH($E$2,{"Management";"Conservative"},0),K165,#REF!) -> 2.2631811 | L56: =CHOOSE(MATCH($E$2,{"Management";"Conservative"},0),L165,#REF!) -> 2.4777408 | ... S56: =CHOOSE(MATCH($E$2,{"Management";"Conservative"},0),S165,#REF!) -> 3.9587273
C57: % of revenue | E57: =CHOOSE(MATCH($E$2,{"Management";"Conservative"},0),E166,#REF!) -> 7.616533e-05 | F57: =CHOOSE(MATCH($E$2,{"Management";"Conservative"},0),F166,#REF!) -> 6.484874e-05 | G57: =CHOOSE(MATCH($E$2,{"Management";"Conservative"},0),G166,#REF!) -> 0 | H57: =CHOOSE(MATCH($E$2,{"Management";"Conservative"},0),H166,#REF!) -> 5.3387433e-05 | I57: =CHOOSE(MATCH($E$2,{"Management";"Conservative"},0),I166,#REF!) -> 0.00017852437 | J57: =CHOOSE(MATCH($E$2,{"Management";"Conservative"},0),J166,#REF!) -> 0.000185 | K57: =CHOOSE(MATCH($E$2,{"Management";"Conservative"},0),K166,#REF!) -> 0.00019 | L57: =CHOOSE(MATCH($E$2,{"Management";"Conservative"},0),L166,#REF!) -> 0.000195 | ... S57: =CHOOSE(MATCH($E$2,{"Management";"Conservative"},0),S166,#REF!) -> 0.00023
C59: Working Captial
C61: Accounts receivable | E61: =CHOOSE(MATCH($E$2,{"Management";"Conservative"},0),E170,#REF!) -> 1361.8 | F61: =CHOOSE(MATCH($E$2,{"Management";"Conservative"},0),F170,#REF!) -> 1576.8 | G61: =CHOOSE(MATCH($E$2,{"Management";"Conservative"},0),G170,#REF!) -> 1719.6 | H61: =CHOOSE(MATCH($E$2,{"Management";"Conservative"},0),H170,#REF!) -> 2009.2 | I61: =CHOOSE(MATCH($E$2,{"Management";"Conservative"},0),I170,#REF!) -> 2175 | J61: =CHOOSE(MATCH($E$2,{"Management";"Conservative"},0),J170,#REF!) -> 2139.0393 | K61: =CHOOSE(MATCH($E$2,{"Management";"Conservative"},0),K170,#REF!) -> 2186.4907 | L61: =CHOOSE(MATCH($E$2,{"Management";"Conservative"},0),L170,#REF!) -> 2259.862 | ... S61: =CHOOSE(MATCH($E$2,{"Management";"Conservative"},0),S170,#REF!) -> 3061.1767
C62: Account receivable days | E62: =CHOOSE(MATCH($E$2,{"Management";"Conservative"},0),E171,#REF!) -> 0 | F62: =CHOOSE(MATCH($E$2,{"Management";"Conservative"},0),F171,#REF!) -> 57.963371 | G62: =CHOOSE(MATCH($E$2,{"Management";"Conservative"},0),G171,#REF!) -> 57.339351 | H62: =CHOOSE(MATCH($E$2,{"Management";"Conservative"},0),H171,#REF!) -> 60.55078 | I62: =CHOOSE(MATCH($E$2,{"Management";"Conservative"},0),I171,#REF!) -> 64.916264 | J62: =CHOOSE(MATCH($E$2,{"Management";"Conservative"},0),J171,#REF!) -> 69 | K62: =CHOOSE(MATCH($E$2,{"Management";"Conservative"},0),K171,#REF!) -> 67 | L62: =CHOOSE(MATCH($E$2,{"Management";"Conservative"},0),L171,#REF!) -> 64.916264 | ... S62: =CHOOSE(MATCH($E$2,{"Management";"Conservative"},0),S171,#REF!) -> 64.916264
C64: Inventories | E64: =CHOOSE(MATCH($E$2,{"Management";"Conservative"},0),E173,#REF!) -> 814 | F64: =CHOOSE(MATCH($E$2,{"Management";"Conservative"},0),F173,#REF!) -> 1158.3 | G64: =CHOOSE(MATCH($E$2,{"Management";"Conservative"},0),G173,#REF!) -> 1212.8 | H64: =CHOOSE(MATCH($E$2,{"Management";"Conservative"},0),H173,#REF!) -> 1240.7 | I64: =CHOOSE(MATCH($E$2,{"Management";"Conservative"},0),I173,#REF!) -> 1348.9 | J64: =CHOOSE(MATCH($E$2,{"Management";"Conservative"},0),J173,#REF!) -> 1395.0256 | K64: =CHOOSE(MATCH($E$2,{"Management";"Conservative"},0),K173,#REF!) -> 1395.1116 | L64: =CHOOSE(MATCH($E$2,{"Management";"Conservative"},0),L173,#REF!) -> 1384.5803 | ... S64: =CHOOSE(MATCH($E$2,{"Management";"Conservative"},0),S173,#REF!) -> 1875.5327
C65: Inventory days | E65: =CHOOSE(MATCH($E$2,{"Management";"Conservative"},0),E174,#REF!) -> 0 | F65: =CHOOSE(MATCH($E$2,{"Management";"Conservative"},0),F174,#REF!) -> 80.68701 | G65: =CHOOSE(MATCH($E$2,{"Management";"Conservative"},0),G174,#REF!) -> 81.461926 | H65: =CHOOSE(MATCH($E$2,{"Management";"Conservative"},0),H174,#REF!) -> 85.8805 | I65: =CHOOSE(MATCH($E$2,{"Management";"Conservative"},0),I174,#REF!) -> 88.384732 | J65: =CHOOSE(MATCH($E$2,{"Management";"Conservative"},0),J174,#REF!) -> 100 | K65: =CHOOSE(MATCH($E$2,{"Management";"Conservative"},0),K174,#REF!) -> 95 | L65: =CHOOSE(MATCH($E$2,{"Management";"Conservative"},0),L174,#REF!) -> 88.384732 | ... S65: =CHOOSE(MATCH($E$2,{"Management";"Conservative"},0),S174,#REF!) -> 88.384732
C67: Prepaid expense and accrued income | E67: =CHOOSE(MATCH($E$2,{"Management";"Conservative"},0),E176,#REF!) -> 120.7 | F67: =CHOOSE(MATCH($E$2,{"Management";"Conservative"},0),F176,#REF!) -> 190.4 | G67: =CHOOSE(MATCH($E$2,{"Management";"Conservative"},0),G176,#REF!) -> 190.1 | H67: =CHOOSE(MATCH($E$2,{"Management";"Conservative"},0),H176,#REF!) -> 243.8 | I67: =CHOOSE(MATCH($E$2,{"Management";"Conservative"},0),I176,#REF!) -> 273.5 | J67: =CHOOSE(MATCH($E$2,{"Management";"Conservative"},0),J176,#REF!) -> 248.80163 | K67: =CHOOSE(MATCH($E$2,{"Management";"Conservative"},0),K176,#REF!) -> 261.9126 | L67: =CHOOSE(MATCH($E$2,{"Management";"Conservative"},0),L176,#REF!) -> 279.39071 | ... S67: =CHOOSE(MATCH($E$2,{"Management";"Conservative"},0),S176,#REF!) -> 378.45866
C68: as % of revenue | E68: =CHOOSE(MATCH($E$2,{"Management";"Conservative"},0),E177,#REF!) -> 0 | F68: =CHOOSE(MATCH($E$2,{"Management";"Conservative"},0),F177,#REF!) -> 0.016812036 | G68: =CHOOSE(MATCH($E$2,{"Management";"Conservative"},0),G177,#REF!) -> 0.018133209 | H68: =CHOOSE(MATCH($E$2,{"Management";"Conservative"},0),H177,#REF!) -> 0.019304006 | I68: =CHOOSE(MATCH($E$2,{"Management";"Conservative"},0),I177,#REF!) -> 0.021988251 | J68: =CHOOSE(MATCH($E$2,{"Management";"Conservative"},0),J177,#REF!) -> 0.021988251 | K68: =CHOOSE(MATCH($E$2,{"Management";"Conservative"},0),K177,#REF!) -> 0.021988251 | L68: =CHOOSE(MATCH($E$2,{"Management";"Conservative"},0),L177,#REF!) -> 0.021988251 | ... S68: =CHOOSE(MATCH($E$2,{"Management";"Conservative"},0),S177,#REF!) -> 0.021988251
C70: Accounts payables | E70: =CHOOSE(MATCH($E$2,{"Management";"Conservative"},0),E179,#REF!) -> 846.3 | F70: =CHOOSE(MATCH($E$2,{"Management";"Conservative"},0),F179,#REF!) -> 1033.2 | G70: =CHOOSE(MATCH($E$2,{"Management";"Conservative"},0),G179,#REF!) -> 1016.6 | H70: =CHOOSE(MATCH($E$2,{"Management";"Conservative"},0),H179,#REF!) -> 1108.2 | I70: =CHOOSE(MATCH($E$2,{"Management";"Conservative"},0),I179,#REF!) -> 1212.3 | J70: =CHOOSE(MATCH($E$2,{"Management";"Conservative"},0),J179,#REF!) -> 1116.0205 | K70: =CHOOSE(MATCH($E$2,{"Management";"Conservative"},0),K179,#REF!) -> 1163.0851 | L70: =CHOOSE(MATCH($E$2,{"Management";"Conservative"},0),L179,#REF!) -> 1240.7008 | ... S70: =CHOOSE(MATCH($E$2,{"Management";"Conservative"},0),S179,#REF!) -> 1680.6355
C71: Account payable days | E71: =CHOOSE(MATCH($E$2,{"Management";"Conservative"},0),E180,#REF!) -> 0 | F71: =CHOOSE(MATCH($E$2,{"Management";"Conservative"},0),F180,#REF!) -> 76.890551 | G71: =CHOOSE(MATCH($E$2,{"Management";"Conservative"},0),G180,#REF!) -> 70.423287 | H71: =CHOOSE(MATCH($E$2,{"Management";"Conservative"},0),H180,#REF!) -> 74.374928 | I71: =CHOOSE(MATCH($E$2,{"Management";"Conservative"},0),I180,#REF!) -> 79.200174 | J71: =CHOOSE(MATCH($E$2,{"Management";"Conservative"},0),J180,#REF!) -> 80 | K71: =CHOOSE(MATCH($E$2,{"Management";"Conservative"},0),K180,#REF!) -> 79.200174 | L71: =CHOOSE(MATCH($E$2,{"Management";"Conservative"},0),L180,#REF!) -> 79.200174 | ... S71: =CHOOSE(MATCH($E$2,{"Management";"Conservative"},0),S180,#REF!) -> 79.200174
C73: Accrued expenses and deferred income | E73: =CHOOSE(MATCH($E$2,{"Management";"Conservative"},0),E182,E225) -> 454 | F73: =CHOOSE(MATCH($E$2,{"Management";"Conservative"},0),F182,F225) -> 519.9 | G73: =CHOOSE(MATCH($E$2,{"Management";"Conservative"},0),G182,G225) -> 489 | H73: =CHOOSE(MATCH($E$2,{"Management";"Conservative"},0),H182,H225) -> 678.2 | I73: =CHOOSE(MATCH($E$2,{"Management";"Conservative"},0),I182,I225) -> 623.9 | J73: =CHOOSE(MATCH($E$2,{"Management";"Conservative"},0),J182,J225) -> 626.26059 | K73: =CHOOSE(MATCH($E$2,{"Management";"Conservative"},0),K182,K225) -> 659.26233 | L73: =CHOOSE(MATCH($E$2,{"Management";"Conservative"},0),L182,L225) -> 703.2566 | ... S73: =CHOOSE(MATCH($E$2,{"Management";"Conservative"},0),S182,S225) -> 952.62133
C74: as % of revenue | E74: =CHOOSE(MATCH($E$2,{"Management";"Conservative"},0),E183,E226) -> 0 | F74: =CHOOSE(MATCH($E$2,{"Management";"Conservative"},0),F183,F226) -> 0.052630157 | G74: =CHOOSE(MATCH($E$2,{"Management";"Conservative"},0),G183,G226) -> 0.048080406 | H74: =CHOOSE(MATCH($E$2,{"Management";"Conservative"},0),H183,H226) -> 0.051928176 | I74: =CHOOSE(MATCH($E$2,{"Management";"Conservative"},0),I183,I226) -> 0.055346805 | J74: =CHOOSE(MATCH($E$2,{"Management";"Conservative"},0),J183,J226) -> 0.055346805 | K74: =CHOOSE(MATCH($E$2,{"Management";"Conservative"},0),K183,K226) -> 0.055346805 | L74: =CHOOSE(MATCH($E$2,{"Management";"Conservative"},0),L183,L226) -> 0.055346805 | ... S74: =CHOOSE(MATCH($E$2,{"Management";"Conservative"},0),S183,S226) -> 0.055346805
C76: Provisions | E76: =CHOOSE(MATCH($E$2,{"Management";"Conservative"},0),E185,E228) -> 26.8 | F76: =CHOOSE(MATCH($E$2,{"Management";"Conservative"},0),F185,F228) -> 26 | G76: =CHOOSE(MATCH($E$2,{"Management";"Conservative"},0),G185,G228) -> 26.9 | H76: =CHOOSE(MATCH($E$2,{"Management";"Conservative"},0),H185,H228) -> 46.3 | I76: =CHOOSE(MATCH($E$2,{"Management";"Conservative"},0),I185,I228) -> 44.1 | J76: =CHOOSE(MATCH($E$2,{"Management";"Conservative"},0),J185,J228) -> 43.478963 | K76: =CHOOSE(MATCH($E$2,{"Management";"Conservative"},0),K185,K228) -> 45.770152 | L76: =CHOOSE(MATCH($E$2,{"Management";"Conservative"},0),L185,L228) -> 48.824511 | ... S76: =CHOOSE(MATCH($E$2,{"Management";"Conservative"},0),S185,S228) -> 66.136985
C77: as % of revenue | E77: =CHOOSE(MATCH($E$2,{"Management";"Conservative"},0),E186,E229) -> 0 | F77: =CHOOSE(MATCH($E$2,{"Management";"Conservative"},0),F186,F229) -> 0.0028533446 | G77: =CHOOSE(MATCH($E$2,{"Management";"Conservative"},0),G186,G229) -> 0.0025210164 | H77: =CHOOSE(MATCH($E$2,{"Management";"Conservative"},0),H186,H229) -> 0.0032566334 | I77: =CHOOSE(MATCH($E$2,{"Management";"Conservative"},0),I186,I229) -> 0.0038425245 | J77: =CHOOSE(MATCH($E$2,{"Management";"Conservative"},0),J186,J229) -> 0.0038425245 | K77: =CHOOSE(MATCH($E$2,{"Management";"Conservative"},0),K186,K229) -> 0.0038425245 | L77: =CHOOSE(MATCH($E$2,{"Management";"Conservative"},0),L186,L229) -> 0.0038425245 | ... S77: =CHOOSE(MATCH($E$2,{"Management";"Conservative"},0),S186,S229) -> 0.0038425245
B79: x | C79: Dividends
C80: Common dividends | E80: =CHOOSE(MATCH($E$2,{"Management";"Conservative"},0),E189,#REF!) -> 326 | F80: =CHOOSE(MATCH($E$2,{"Management";"Conservative"},0),F189,#REF!) -> 354.5 | G80: =CHOOSE(MATCH($E$2,{"Management";"Conservative"},0),G189,#REF!) -> 445.8 | H80: =CHOOSE(MATCH($E$2,{"Management";"Conservative"},0),H189,#REF!) -> 492.3 | I80: =CHOOSE(MATCH($E$2,{"Management";"Conservative"},0),I189,#REF!) -> 264.7 | J80: =CHOOSE(MATCH($E$2,{"Management";"Conservative"},0),J189,#REF!) -> 524.71999 | K80: =CHOOSE(MATCH($E$2,{"Management";"Conservative"},0),K189,#REF!) -> 634.9868 | L80: =CHOOSE(MATCH($E$2,{"Management";"Conservative"},0),L189,#REF!) -> 756.19139 | ... S80: =CHOOSE(MATCH($E$2,{"Management";"Conservative"},0),S189,#REF!) -> 1721.4496
C81: % of net income | E81: =CHOOSE(MATCH($E$2,{"Management";"Conservative"},0),E190,#REF!) -> 0.39505574 | F81: =CHOOSE(MATCH($E$2,{"Management";"Conservative"},0),F190,#REF!) -> 0.34467671 | G81: =CHOOSE(MATCH($E$2,{"Management";"Conservative"},0),G190,#REF!) -> 0.38348387 | H81: =CHOOSE(MATCH($E$2,{"Management";"Conservative"},0),H190,#REF!) -> 0.46329757 | I81: =CHOOSE(MATCH($E$2,{"Management";"Conservative"},0),I190,#REF!) -> 0.21216736 | J81: =CHOOSE(MATCH($E$2,{"Management";"Conservative"},0),J190,#REF!) -> 0.46 | K81: =CHOOSE(MATCH($E$2,{"Management";"Conservative"},0),K190,#REF!) -> 0.485 | L81: =CHOOSE(MATCH($E$2,{"Management";"Conservative"},0),L190,#REF!) -> 0.51 | ... S81: =CHOOSE(MATCH($E$2,{"Management";"Conservative"},0),S190,#REF!) -> 0.685
C82: Dividends to NCI | E82: =CHOOSE(MATCH($E$2,{"Management";"Conservative"},0),E191,#REF!) -> 1 | F82: =CHOOSE(MATCH($E$2,{"Management";"Conservative"},0),F191,#REF!) -> 0.6 | G82: =CHOOSE(MATCH($E$2,{"Management";"Conservative"},0),G191,#REF!) -> 0.2 | H82: =CHOOSE(MATCH($E$2,{"Management";"Conservative"},0),H191,#REF!) -> 1 | I82: =CHOOSE(MATCH($E$2,{"Management";"Conservative"},0),I191,#REF!) -> 1.6 | J82: =CHOOSE(MATCH($E$2,{"Management";"Conservative"},0),J191,#REF!) -> 0.95608421 | K82: =CHOOSE(MATCH($E$2,{"Management";"Conservative"},0),K191,#REF!) -> 1.0973605 | L82: =CHOOSE(MATCH($E$2,{"Management";"Conservative"},0),L191,#REF!) -> 1.2427619 | ... S82: =CHOOSE(MATCH($E$2,{"Management";"Conservative"},0),S191,#REF!) -> 2.1063479
C83: % of net income | E83: =CHOOSE(MATCH($E$2,{"Management";"Conservative"},0),E192,#REF!) -> 0.0012118274 | F83: =CHOOSE(MATCH($E$2,{"Management";"Conservative"},0),F192,#REF!) -> 0.00058337385 | G83: =CHOOSE(MATCH($E$2,{"Management";"Conservative"},0),G192,#REF!) -> 0.00017204301 | H83: =CHOOSE(MATCH($E$2,{"Management";"Conservative"},0),H192,#REF!) -> 0.0009410879 | I83: =CHOOSE(MATCH($E$2,{"Management";"Conservative"},0),I192,#REF!) -> 0.0012824623 | J83: =CHOOSE(MATCH($E$2,{"Management";"Conservative"},0),J192,#REF!) -> 0.0008381589 | K83: =CHOOSE(MATCH($E$2,{"Management";"Conservative"},0),K192,#REF!) -> 0.0008381589 | L83: =CHOOSE(MATCH($E$2,{"Management";"Conservative"},0),L192,#REF!) -> 0.0008381589 | ... S83: =CHOOSE(MATCH($E$2,{"Management";"Conservative"},0),S192,#REF!) -> 0.0008381589
C85: FX rate effects
C86: FX rate effects | E86: =CHOOSE(MATCH($E$2,{"Management";"Conservative"},0),E195,#REF!) -> -300.1 | F86: =CHOOSE(MATCH($E$2,{"Management";"Conservative"},0),F195,#REF!) -> 52.5 | G86: =CHOOSE(MATCH($E$2,{"Management";"Conservative"},0),G195,#REF!) -> -237.2 | H86: =CHOOSE(MATCH($E$2,{"Management";"Conservative"},0),H195,#REF!) -> -806.7 | I86: =CHOOSE(MATCH($E$2,{"Management";"Conservative"},0),I195,#REF!) -> 320.6 | J86: =CHOOSE(MATCH($E$2,{"Management";"Conservative"},0),J195,#REF!) -> 0 | K86: =CHOOSE(MATCH($E$2,{"Management";"Conservative"},0),K195,#REF!) -> 0 | L86: =CHOOSE(MATCH($E$2,{"Management";"Conservative"},0),L195,#REF!) -> 0 | ... S86: =CHOOSE(MATCH($E$2,{"Management";"Conservative"},0),S195,#REF!) -> 0
C87: % of revenue | E87: =CHOOSE(MATCH($E$2,{"Management";"Conservative"},0),E196,#REF!) -> -0.038095359 | F87: =CHOOSE(MATCH($E$2,{"Management";"Conservative"},0),F196,#REF!) -> 0.0056742648 | G87: =CHOOSE(MATCH($E$2,{"Management";"Conservative"},0),G196,#REF!) -> -0.022608132 | H87: =CHOOSE(MATCH($E$2,{"Management";"Conservative"},0),H196,#REF!) -> -0.071779403 | I87: =CHOOSE(MATCH($E$2,{"Management";"Conservative"},0),I196,#REF!) -> 0.02725472 | J87: =CHOOSE(MATCH($E$2,{"Management";"Conservative"},0),J196,#REF!) -> 0 | K87: =CHOOSE(MATCH($E$2,{"Management";"Conservative"},0),K196,#REF!) -> 0 | L87: =CHOOSE(MATCH($E$2,{"Management";"Conservative"},0),L196,#REF!) -> 0 | ... S87: =CHOOSE(MATCH($E$2,{"Management";"Conservative"},0),S196,#REF!) -> 0
B89: x | C89: Other Balance Sheet Items
C90: Other current assets | E90: =CHOOSE(MATCH($E$2,{"Management";"Conservative"},0),E199,E227) -> 19.4 | F90: =CHOOSE(MATCH($E$2,{"Management";"Conservative"},0),F199,F227) -> 30.9 | G90: =CHOOSE(MATCH($E$2,{"Management";"Conservative"},0),G199,G227) -> 25.5 | H90: =CHOOSE(MATCH($E$2,{"Management";"Conservative"},0),H199,H227) -> 63.8 | I90: =CHOOSE(MATCH($E$2,{"Management";"Conservative"},0),I199,I227) -> 58.4 | J90: =CHOOSE(MATCH($E$2,{"Management";"Conservative"},0),J199,J227) -> 58.4 | K90: =CHOOSE(MATCH($E$2,{"Management";"Conservative"},0),K199,K227) -> 58.4 | L90: =CHOOSE(MATCH($E$2,{"Management";"Conservative"},0),L199,L227) -> 58.4 | ... S90: =CHOOSE(MATCH($E$2,{"Management";"Conservative"},0),S199,S227) -> 58.4
C91: Assets classified as held for sale | E91: =CHOOSE(MATCH($E$2,{"Management";"Conservative"},0),E200,E228) -> 0 | F91: =CHOOSE(MATCH($E$2,{"Management";"Conservative"},0),F200,F228) -> 33.7 | G91: =CHOOSE(MATCH($E$2,{"Management";"Conservative"},0),G200,G228) -> 0 | H91: =CHOOSE(MATCH($E$2,{"Management";"Conservative"},0),H200,H228) -> 0 | I91: =CHOOSE(MATCH($E$2,{"Management";"Conservative"},0),I200,I228) -> 0 | J91: =CHOOSE(MATCH($E$2,{"Management";"Conservative"},0),J200,J228) -> 0 | K91: =CHOOSE(MATCH($E$2,{"Management";"Conservative"},0),K200,K228) -> 0 | L91: =CHOOSE(MATCH($E$2,{"Management";"Conservative"},0),L200,L228) -> 0 | ... S91: =CHOOSE(MATCH($E$2,{"Management";"Conservative"},0),S200,S228) -> 0
C93: Investments in associated companies | E93: =CHOOSE(MATCH($E$2,{"Management";"Conservative"},0),E202,E230) -> 2.5 | F93: =CHOOSE(MATCH($E$2,{"Management";"Conservative"},0),F202,F230) -> 9.2 | G93: =CHOOSE(MATCH($E$2,{"Management";"Conservative"},0),G202,G230) -> 9.5 | H93: =CHOOSE(MATCH($E$2,{"Management";"Conservative"},0),H202,H230) -> 19.1 | I93: =CHOOSE(MATCH($E$2,{"Management";"Conservative"},0),I202,I230) -> 24.1 | J93: =CHOOSE(MATCH($E$2,{"Management";"Conservative"},0),J202,J230) -> 24.1 | K93: =CHOOSE(MATCH($E$2,{"Management";"Conservative"},0),K202,K230) -> 24.1 | L93: =CHOOSE(MATCH($E$2,{"Management";"Conservative"},0),L202,L230) -> 24.1 | ... S93: =CHOOSE(MATCH($E$2,{"Management";"Conservative"},0),S202,S230) -> 24.1
C94: Deferred tax assets | E94: =CHOOSE(MATCH($E$2,{"Management";"Conservative"},0),E203,E231) -> 194.7 | F94: =CHOOSE(MATCH($E$2,{"Management";"Conservative"},0),F203,F231) -> 142.5 | G94: =CHOOSE(MATCH($E$2,{"Management";"Conservative"},0),G203,G231) -> 144.8 | H94: =CHOOSE(MATCH($E$2,{"Management";"Conservative"},0),H203,H231) -> 188.6 | I94: =CHOOSE(MATCH($E$2,{"Management";"Conservative"},0),I203,I231) -> 150.7 | J94: =CHOOSE(MATCH($E$2,{"Management";"Conservative"},0),J203,J231) -> 150.7 | K94: =CHOOSE(MATCH($E$2,{"Management";"Conservative"},0),K203,K231) -> 150.7 | L94: =CHOOSE(MATCH($E$2,{"Management";"Conservative"},0),L203,L231) -> 150.7 | ... S94: =CHOOSE(MATCH($E$2,{"Management";"Conservative"},0),S203,S231) -> 150.7
C95: Other non-current assets | E95: =CHOOSE(MATCH($E$2,{"Management";"Conservative"},0),E204,E232) -> 87.3 | F95: =CHOOSE(MATCH($E$2,{"Management";"Conservative"},0),F204,F232) -> 233.5 | G95: =CHOOSE(MATCH($E$2,{"Management";"Conservative"},0),G204,G232) -> 92.2 | H95: =CHOOSE(MATCH($E$2,{"Management";"Conservative"},0),H204,H232) -> 160.8 | I95: =CHOOSE(MATCH($E$2,{"Management";"Conservative"},0),I204,I232) -> 164.5 | J95: =CHOOSE(MATCH($E$2,{"Management";"Conservative"},0),J204,J232) -> 164.5 | K95: =CHOOSE(MATCH($E$2,{"Management";"Conservative"},0),K204,K232) -> 164.5 | L95: =CHOOSE(MATCH($E$2,{"Management";"Conservative"},0),L204,L232) -> 164.5 | ... S95: =CHOOSE(MATCH($E$2,{"Management";"Conservative"},0),S204,S232) -> 164.5
C97: Financial liabilities | E97: =CHOOSE(MATCH($E$2,{"Management";"Conservative"},0),E206,E235) -> 334.7 | F97: =CHOOSE(MATCH($E$2,{"Management";"Conservative"},0),F206,F235) -> 334.9 | G97: =CHOOSE(MATCH($E$2,{"Management";"Conservative"},0),G206,G235) -> 303 | H97: =CHOOSE(MATCH($E$2,{"Management";"Conservative"},0),H206,H235) -> 1217.9 | I97: =CHOOSE(MATCH($E$2,{"Management";"Conservative"},0),I206,I235) -> 337.4 | J97: =CHOOSE(MATCH($E$2,{"Management";"Conservative"},0),J206,J235) -> 337.4 | K97: =CHOOSE(MATCH($E$2,{"Management";"Conservative"},0),K206,K235) -> 337.4 | L97: =CHOOSE(MATCH($E$2,{"Management";"Conservative"},0),L206,L235) -> 337.4 | ... S97: =CHOOSE(MATCH($E$2,{"Management";"Conservative"},0),S206,S235) -> 337.4
C98: Income tax liabilities | E98: =CHOOSE(MATCH($E$2,{"Management";"Conservative"},0),E207,E236) -> 163.3 | F98: =CHOOSE(MATCH($E$2,{"Management";"Conservative"},0),F207,F236) -> 170.3 | G98: =CHOOSE(MATCH($E$2,{"Management";"Conservative"},0),G207,G236) -> 205.9 | H98: =CHOOSE(MATCH($E$2,{"Management";"Conservative"},0),H207,H236) -> 365.4 | I98: =CHOOSE(MATCH($E$2,{"Management";"Conservative"},0),I207,I236) -> 367.7 | J98: =CHOOSE(MATCH($E$2,{"Management";"Conservative"},0),J207,J236) -> 367.7 | K98: =CHOOSE(MATCH($E$2,{"Management";"Conservative"},0),K207,K236) -> 367.7 | L98: =CHOOSE(MATCH($E$2,{"Management";"Conservative"},0),L207,L236) -> 367.7 | ... S98: =CHOOSE(MATCH($E$2,{"Management";"Conservative"},0),S207,S236) -> 367.7
C99: Liabilities classified as held for sale | E99: =CHOOSE(MATCH($E$2,{"Management";"Conservative"},0),E208,E238) -> 0 | F99: =CHOOSE(MATCH($E$2,{"Management";"Conservative"},0),F208,F238) -> 3.7 | G99: =CHOOSE(MATCH($E$2,{"Management";"Conservative"},0),G208,G238) -> 0 | H99: =CHOOSE(MATCH($E$2,{"Management";"Conservative"},0),H208,H238) -> 0 | I99: =CHOOSE(MATCH($E$2,{"Management";"Conservative"},0),I208,I238) -> 0 | J99: =CHOOSE(MATCH($E$2,{"Management";"Conservative"},0),J208,J238) -> 0 | K99: =CHOOSE(MATCH($E$2,{"Management";"Conservative"},0),K208,K238) -> 0 | L99: =CHOOSE(MATCH($E$2,{"Management";"Conservative"},0),L208,L238) -> 0 | ... S99: =CHOOSE(MATCH($E$2,{"Management";"Conservative"},0),S208,S238) -> 0
C100: Employee benefit obligation | E100: =CHOOSE(MATCH($E$2,{"Management";"Conservative"},0),E209,E239) -> 319.5 | F100: =CHOOSE(MATCH($E$2,{"Management";"Conservative"},0),F209,F239) -> 322.9 | G100: =CHOOSE(MATCH($E$2,{"Management";"Conservative"},0),G209,G239) -> 239.9 | H100: =CHOOSE(MATCH($E$2,{"Management";"Conservative"},0),H209,H239) -> 328.6 | I100: =CHOOSE(MATCH($E$2,{"Management";"Conservative"},0),I209,I239) -> 357.2 | J100: =CHOOSE(MATCH($E$2,{"Management";"Conservative"},0),J209,J239) -> 357.2 | K100: =CHOOSE(MATCH($E$2,{"Management";"Conservative"},0),K209,K239) -> 357.2 | L100: =CHOOSE(MATCH($E$2,{"Management";"Conservative"},0),L209,L239) -> 357.2 | ... S100: =CHOOSE(MATCH($E$2,{"Management";"Conservative"},0),S209,S239) -> 357.2
C101: Provisions | E101: =CHOOSE(MATCH($E$2,{"Management";"Conservative"},0),E210,E241) -> 98.3 | F101: =CHOOSE(MATCH($E$2,{"Management";"Conservative"},0),F210,F241) -> 95.6 | G101: =CHOOSE(MATCH($E$2,{"Management";"Conservative"},0),G210,G241) -> 78 | H101: =CHOOSE(MATCH($E$2,{"Management";"Conservative"},0),H210,H241) -> 200.5 | I101: =CHOOSE(MATCH($E$2,{"Management";"Conservative"},0),I210,I241) -> 183.1 | J101: =CHOOSE(MATCH($E$2,{"Management";"Conservative"},0),J210,J241) -> 183.1 | K101: =CHOOSE(MATCH($E$2,{"Management";"Conservative"},0),K210,K241) -> 183.1 | L101: =CHOOSE(MATCH($E$2,{"Management";"Conservative"},0),L210,L241) -> 183.1 | ... S101: =CHOOSE(MATCH($E$2,{"Management";"Conservative"},0),S210,S241) -> 183.1
C102: Deferred tax liabilities | E102: =CHOOSE(MATCH($E$2,{"Management";"Conservative"},0),E211,E242) -> 379.9 | F102: =CHOOSE(MATCH($E$2,{"Management";"Conservative"},0),F211,F242) -> 367.2 | G102: =CHOOSE(MATCH($E$2,{"Management";"Conservative"},0),G211,G242) -> 322.5 | H102: =CHOOSE(MATCH($E$2,{"Management";"Conservative"},0),H211,H242) -> 404.7 | I102: =CHOOSE(MATCH($E$2,{"Management";"Conservative"},0),I211,I242) -> 338.9 | J102: =CHOOSE(MATCH($E$2,{"Management";"Conservative"},0),J211,J242) -> 338.9 | K102: =CHOOSE(MATCH($E$2,{"Management";"Conservative"},0),K211,K242) -> 338.9 | L102: =CHOOSE(MATCH($E$2,{"Management";"Conservative"},0),L211,L242) -> 338.9 | ... S102: =CHOOSE(MATCH($E$2,{"Management";"Conservative"},0),S211,S242) -> 338.9
C104: Other liabilities | E104: =CHOOSE(MATCH($E$2,{"Management";"Conservative"},0),E213,E244) -> 31.3 | F104: =CHOOSE(MATCH($E$2,{"Management";"Conservative"},0),F213,F244) -> 36.4 | G104: =CHOOSE(MATCH($E$2,{"Management";"Conservative"},0),G213,G244) -> 36.1 | H104: =CHOOSE(MATCH($E$2,{"Management";"Conservative"},0),H213,H244) -> 35.7 | I104: =CHOOSE(MATCH($E$2,{"Management";"Conservative"},0),I213,I244) -> 41 | J104: =CHOOSE(MATCH($E$2,{"Management";"Conservative"},0),J213,J244) -> 41 | K104: =CHOOSE(MATCH($E$2,{"Management";"Conservative"},0),K213,K244) -> 41 | L104: =CHOOSE(MATCH($E$2,{"Management";"Conservative"},0),L213,L244) -> 41 | ... S104: =CHOOSE(MATCH($E$2,{"Management";"Conservative"},0),S213,S244) -> 41
C106: Cash distribution
C107: Minimum cash (as % of revenue) | J107: =CHOOSE(MATCH($E$2,{"Management";"Conservative"},0),J216,J246) -> 0.05 | K107: =CHOOSE(MATCH($E$2,{"Management";"Conservative"},0),K216,K246) -> 0.05 | L107: =CHOOSE(MATCH($E$2,{"Management";"Conservative"},0),L216,L246) -> 0.05 | M107: =CHOOSE(MATCH($E$2,{"Management";"Conservative"},0),M216,M246) -> 0.05 | N107: =CHOOSE(MATCH($E$2,{"Management";"Conservative"},0),N216,N246) -> 0.05 | O107: =CHOOSE(MATCH($E$2,{"Management";"Conservative"},0),O216,O246) -> 0.05 | P107: =CHOOSE(MATCH($E$2,{"Management";"Conservative"},0),P216,P246) -> 0.05 | Q107: =CHOOSE(MATCH($E$2,{"Management";"Conservative"},0),Q216,Q246) -> 0.05 | ... S107: =CHOOSE(MATCH($E$2,{"Management";"Conservative"},0),S216,S246) -> 0.05
C109: % of Stock repurchases | J109: =CHOOSE(MATCH($E$2,{"Management";"Conservative"},0),J218,J248) -> 0 | K109: =CHOOSE(MATCH($E$2,{"Management";"Conservative"},0),K218,K248) -> 0 | L109: =CHOOSE(MATCH($E$2,{"Management";"Conservative"},0),L218,L248) -> 0 | M109: =CHOOSE(MATCH($E$2,{"Management";"Conservative"},0),M218,M248) -> 0 | N109: =CHOOSE(MATCH($E$2,{"Management";"Conservative"},0),N218,N248) -> 0 | O109: =CHOOSE(MATCH($E$2,{"Management";"Conservative"},0),O218,O248) -> 0 | P109: =CHOOSE(MATCH($E$2,{"Management";"Conservative"},0),P218,P248) -> 0 | Q109: =CHOOSE(MATCH($E$2,{"Management";"Conservative"},0),Q218,Q248) -> 0 | ... S109: =CHOOSE(MATCH($E$2,{"Management";"Conservative"},0),S218,S248) -> 0
C110: % of Debt repayment | J110: =CHOOSE(MATCH($E$2,{"Management";"Conservative"},0),J219,J249) -> 0.15 | K110: =CHOOSE(MATCH($E$2,{"Management";"Conservative"},0),K219,K249) -> 0.15 | L110: =CHOOSE(MATCH($E$2,{"Management";"Conservative"},0),L219,L249) -> 0.15 | M110: =CHOOSE(MATCH($E$2,{"Management";"Conservative"},0),M219,M249) -> 0 | N110: =CHOOSE(MATCH($E$2,{"Management";"Conservative"},0),N219,N249) -> 0 | O110: =CHOOSE(MATCH($E$2,{"Management";"Conservative"},0),O219,O249) -> 0 | P110: =CHOOSE(MATCH($E$2,{"Management";"Conservative"},0),P219,P249) -> 0 | Q110: =CHOOSE(MATCH($E$2,{"Management";"Conservative"},0),Q219,Q249) -> 0 | ... S110: =CHOOSE(MATCH($E$2,{"Management";"Conservative"},0),S219,S249) -> 0
C112: Interest rate (%) | J112: =CHOOSE(MATCH($E$2,{"Management";"Conservative"},0),J221,J251) -> 0.02704 | K112: =CHOOSE(MATCH($E$2,{"Management";"Conservative"},0),K221,K251) -> 0.02704 | L112: =CHOOSE(MATCH($E$2,{"Management";"Conservative"},0),L221,L251) -> 0.02704 | M112: =CHOOSE(MATCH($E$2,{"Management";"Conservative"},0),M221,M251) -> 0.02704 | N112: =CHOOSE(MATCH($E$2,{"Management";"Conservative"},0),N221,N251) -> 0.02704 | O112: =CHOOSE(MATCH($E$2,{"Management";"Conservative"},0),O221,O251) -> 0.02704 | P112: =CHOOSE(MATCH($E$2,{"Management";"Conservative"},0),P221,P251) -> 0.02704 | Q112: =CHOOSE(MATCH($E$2,{"Management";"Conservative"},0),Q221,Q251) -> 0.02704 | ... S112: =CHOOSE(MATCH($E$2,{"Management";"Conservative"},0),S221,S251) -> 0.02704
C114: Capital stock | E114: =CHOOSE(MATCH($E$2,{"Management";"Conservative"},0),E223,E246) -> 1.4 | F114: =CHOOSE(MATCH($E$2,{"Management";"Conservative"},0),F223,F246) -> 1.4 | G114: =CHOOSE(MATCH($E$2,{"Management";"Conservative"},0),G223,G246) -> 1.5 | H114: =CHOOSE(MATCH($E$2,{"Management";"Conservative"},0),H223,H246) -> 1.6 | I114: =CHOOSE(MATCH($E$2,{"Management";"Conservative"},0),I223,I246) -> 1.6 | J114: =CHOOSE(MATCH($E$2,{"Management";"Conservative"},0),J223,J246) -> 1.6 | K114: =CHOOSE(MATCH($E$2,{"Management";"Conservative"},0),K223,K246) -> 1.6 | L114: =CHOOSE(MATCH($E$2,{"Management";"Conservative"},0),L223,L246) -> 1.6 | ... S114: =CHOOSE(MATCH($E$2,{"Management";"Conservative"},0),S223,S246) -> 1.6
B116: x | C116: Management | E116: 2020 | F116: =E116+1 -> 2021 | G116: =F116+1 -> 2022 | H116: =G116+1 -> 2023 | I116: =H116+1 -> 2024 | J116: =I116+1 -> 2025 | K116: =J116+1 -> 2026 | L116: =K116+1 -> 2027 | M116: =L116+1 -> 2028 | ... S116: =R116+1 -> 2034
B118: x | C118: Revenue
C119: EMEA (% growth) | E119: -- | F119: 0.16478801 | G119: 0.017708896 | H119: 0.17767588 | I119: 0.044162551 | J119: -0.01204749 | K119: 0.052486486 | L119: 0.056324324 | M119: 0.054162162 | N119: 0.053498069 | O119: =N119-($N$119-$S$119)/($S$116-$N$116) -> 0.048398456 | P119: =O119-($N$119-$S$119)/($S$116-$N$116) -> 0.043298842 | Q119: =P119-($N$119-$S$119)/($S$116-$N$116) -> 0.038199228 | R119: =Q119-($N$119-$S$119)/($S$116-$N$116) -> 0.033099614 | S119: 0.028
C120: Americas (% growth) | E120: -- | F120: 0.20634132 | G120: 0.31560517 | H120: 0.169845 | I120: 0.096629995 | J120: -0.041 | K120: 0.045 | L120: 0.08 | M120: 0.072 | N120: 0.059 | O120: =N120-($N$120-$S$120)/($S$116-$N$116) -> 0.05294 | P120: =O120-($N$120-$S$120)/($S$116-$N$116) -> 0.04688 | Q120: =P120-($N$120-$S$120)/($S$116-$N$116) -> 0.04082 | R120: =Q120-($N$120-$S$120)/($S$116-$N$116) -> 0.03476 | S120: 0.0287
C121: Asia/Pacific (% growth) | E121: -- | F121: 0.20750885 | G121: 0.12960738 | H121: 0.11588531 | I121: -0.019824628 | J121: -0.085 | K121: 0.066 | L121: 0.067 | M121: 0.057 | N121: 0.052 | O121: =N121-($N$121-$S$121)/($S$116-$N$116) -> 0.04702 | P121: =O121-($N$121-$S$121)/($S$116-$N$116) -> 0.04204 | Q121: =P121-($N$121-$S$121)/($S$116-$N$116) -> 0.03706 | R121: =Q121-($N$121-$S$121)/($S$116-$N$116) -> 0.03208 | S121: 0.0271
C122: Global Business (% growth) | E122: -- | F122: 0.040049482 | G122: 0.19565864 | H122: -1 | I122: #DIV/0! | J122: 0 | K122: 0 | L122: 0 | M122: 0 | N122: 0 | O122: 0 | P122: 0 | Q122: 0 | R122: 0 | S122: 0
B124: x | C124: COGS
C125: Cost of Goods Sold (% of revenue) | E125: 0.45225703 | F125: 0.48215038 | G125: 0.50630016 | H125: 0.46391899 | I125: 0.45456555 | J125: 0.45 | K125: 0.45 | L125: 0.45 | M125: 0.45 | N125: 0.45 | O125: 0.45 | P125: 0.45 | Q125: 0.45 | R125: 0.45 | S125: 0.45
B127: x | C127: OpEx
C128: Personnel Expenses (% of revenue) | E128: 0.19370113 | F128: 0.17674524 | G128: 0.16303208 | H128: 0.17856317 | I128: 0.18223087 | J128: 0.189 | K128: 0.182 | L128: 0.177 | M128: 0.177 | N128: 0.177 | O128: =N128 -> 0.177 | P128: =O128 -> 0.177 | Q128: =P128 -> 0.177 | R128: =Q128 -> 0.177 | S128: =R128 -> 0.177
C129: Production and Operations (% of revenue) | E129: 0.050713415 | F129: 0.050419896 | G129: 0.047513296 | H129: 0.051029488 | I129: 0.052843213 | J129: 0.052 | K129: 0.051 | L129: 0.05 | M129: 0.049 | N129: 0.049 | O129: =N129 -> 0.049 | P129: =O129 -> 0.049 | Q129: =P129 -> 0.049 | R129: =Q129 -> 0.049 | S129: =R129 -> 0.049
C130: Logistics and Distribution (% of revenue) | E130: 0.050979994 | F130: 0.051554749 | G130: 0.049505328 | H130: 0.050371043 | I130: 0.051457524 | J130: 0.05 | K130: 0.049 | L130: 0.049 | M130: 0.048 | N130: 0.048 | O130: =N130 -> 0.048 | P130: =O130 -> 0.048 | Q130: =P130 -> 0.048 | R130: =Q130 -> 0.048 | S130: =R130 -> 0.048
C131: Sales, Marketing and Travel Costs (% of revenue) | E131: 0.02691175 | F131: 0.025409898 | G131: 0.028927353 | H131: 0.03296674 | I131: 0.031530804 | J131: 0.031 | K131: 0.03 | L131: 0.029 | M131: 0.029 | N131: 0.029 | O131: =N131 -> 0.029 | P131: =O131 -> 0.029 | Q131: =P131 -> 0.029 | R131: =Q131 -> 0.029 | S131: =R131 -> 0.029
C132: Administration Costs (% of revenue) | E132: 0.035315324 | F132: 0.025874647 | G132: 0.017508912 | H132: 0.041215098 | I132: 0.034438201 | J132: 0.036 | K132: 0.035 | L132: 0.035 | M132: 0.034 | N132: 0.034 | O132: =N132 -> 0.034 | P132: =O132 -> 0.034 | Q132: =P132 -> 0.034 | R132: =Q132 -> 0.034 | S132: =R132 -> 0.034
B134: x | C134: CapEx
C135: Own property, plant and equipment opening | E135: 120.1 | F135: 157.3 | G135: 238 | H135: 256.8 | I135: 331.1 | J135: =J136*'3-Statement Model'!J24+33.75 -> 373.20623 | K135: =K136*'3-Statement Model'!K24+33.75 -> 391.09438 | L135: =L136*'3-Statement Model'!L24+33.75 -> 414.94089 | M135: =M136*'3-Statement Model'!M24+33.75 -> 438.1877 | N135: =N136*'3-Statement Model'!N24 -> 426.73183 | O135: =O136*'3-Statement Model'!O24 -> 447.9478 | P135: =P136*'3-Statement Model'!P24 -> 417.1174 | Q135: =Q136*'3-Statement Model'!Q24 -> 380.69213 | R135: =R136*'3-Statement Model'!R24 -> 339.026 | S135: =S136*'3-Statement Model'!S24 -> 292.60158
C136: % of revenue | E136: =E135/'3-Statement Model'!E24 -> 0.01524576 | F136: =F135/'3-Statement Model'!F24 -> 0.017001178 | G136: =G135/'3-Statement Model'!G24 -> 0.022684382 | H136: =H135/'3-Statement Model'!H24 -> 0.022849821 | I136: =I135/'3-Statement Model'!I24 -> 0.028147342 | J136: 0.03 | K136: 0.03 | L136: 0.03 | M136: 0.03 | N136: 0.03 | O136: 0.03 | P136: =O136-($O$136-$S$136)/($S$116-$O$116) -> 0.02675 | Q136: =P136-($O$136-$S$136)/($S$116-$O$116) -> 0.0235 | R136: =Q136-($O$136-$S$136)/($S$116-$O$116) -> 0.02025 | S136: 0.017
C137: Right-of-use assets opening | E137: 72.4 | F137: 75.7 | G137: 104.5 | H137: 120 | I137: 134.3 | J137: =J138*'3-Statement Model'!J24 -> 125.00218 | K137: =K138*'3-Statement Model'!K24 -> 131.58936 | L137: =L138*'3-Statement Model'!L24 -> 140.37065 | M137: =M138*'3-Statement Model'!M24 -> 148.93112 | N137: =N138*'3-Statement Model'!N24 -> 149.91649 | O137: =O138*'3-Statement Model'!O24 -> 149.7865 | P137: =P138*'3-Statement Model'!P24 -> 148.50372 | Q137: =Q138*'3-Statement Model'!Q24 -> 146.05225 | ... S137: =S138*'3-Statement Model'!S24 -> 137.69486
...

Sheet WACC
B3: CHF | C3: Low | D3: Mid | E3: High | F3: Comments
B4: Risk free rate | C4: =D4 -> 0.00204 | D4: =E4 -> 0.00204 | E4: 0.00204 | F4: 10/30y gov bond of ch
B5: Equity market risk premium | C5: 0.07 | D5: =AVERAGE(E5,C5) -> 0.075 | E5: 0.08 | F5: Damodaran adj for country exposure
B6: Asset Beta | C6: 0.95 | D6: =AVERAGE(E6,C6) -> 1.025 | E6: 1.1 | F6: Avg and median beta of peer companies
B7: Gearing | C7: =C22/C21 -> 1 | D7: =D22/D21 -> 0.81818182 | E7: =E22/E21 -> 0.66666667 | F7: D/E ratio
B8: Re-levered beta | C8: =C6*(1+(1-C18)*C7) -> 1.7081 | D8: =D6*(1+(1-D18)*D7) -> 1.6942318 | E8: =E6*(1+(1-E18)*E7) -> 1.6852 | F8: TBD if Harris pringle or Hamada
B9: Cost of Equity | C9: =C4+C5*C8 -> 0.121607 | D9: =D4+D5*D8 -> 0.12910739 | E9: =E4+E5*E8 -> 0.136856
B11: Country risk premium | C11: 0 | D11: 0 | E11: 0
B12: Adjusted Cost of Equity | C12: =C9+C11 -> 0.121607 | D12: =D9+D11 -> 0.12910739 | E12: =E9+E11 -> 0.136856
B14: Risk free rate | C14: =C4 -> 0.00204 | D14: =D4 -> 0.00204 | E14: =E4 -> 0.00204 | F14: =F4 -> 10/30y gov bond of ch
B15: Credit spread | C15: 0.025 | D15: 0.025 | E15: 0.025 | F15: Credit spread for A- rated companies
B16: Pre-tax Cost of Debt | C16: =C14+C15 -> 0.02704 | D16: =D14+D15 -> 0.02704 | E16: =E14+E15 -> 0.02704
B18: Tax rate | C18: =D18 -> 0.202 | D18: =E18 -> 0.202 | E18: 0.202 | F18: Historical data
B19: After-tax Cost of Debt | C19: =C16*(1-C18) -> 0.02157792 | D19: =D16*(1-D18) -> 0.02157792 | E19: =E16*(1-E18) -> 0.02157792
B21: Equity-to-capital ratio | C21: 0.5 | D21: =AVERAGE(E21,C21) -> 0.55 | E21: 0.6 | F21: From peers
B22: Debt-to-capital ratio | C22: =1-C21 -> 0.5 | D22: =1-D21 -> 0.45 | E22: =1-E21 -> 0.4 | F22: From peers
B23: WACC | C23: =C12*C21+C19*C22 -> 0.07159246 | D23: =D12*D21+D19*D22 -> 0.080719126 | E23: =E12*E21+E19*E22 -> 0.090744768

Sheet Terminal Growth Rate
B3: Region | C3: Average Real GDP Growth | D3: 2034E Weight
B5: EMEA | C5: 0.013 | D5: 0.433 | E5: =C5+D9*D10 -> 0.028
B6: Americas | C6: 0.0137 | D6: 0.335 | E6: =C6+D9*D10 -> 0.0287
B7: APAC | C7: 0.0121 | D7: 0.232 | E7: =C7+D9*D10 -> 0.0271
B8: Weighted Average Real GDP Growth | D8: =C5*D5+C6*D6+C7*D7 -> 0.0130257
B9: LT inflation | D9: 0.02
B10: Inflation pass through | D10: 0.75
B11: Long Term Growth Rate | D11: =D8+D9*D10 -> 0.0280257
B13: Source: OECD

Sheet Asset Life
B3: Own property, plant and equipment | D3: 2020 | E3: =D3+1 -> 2021 | F3: =E3+1 -> 2022 | G3: =F3+1 -> 2023 | H3: =G3+1 -> 2024
B5: Acquisition cost | D5: 3267.4 | E5: 3442 | F5: 3549.1 | G5: 3973.3 | H5: 4394
B6: Depreciation expense | D6: 169.3 | E6: 165.8 | F6: 174.5 | G6: 200 | H6: 220.7
B7: Accumulated depreciation | D7: 1880.1 | E7: 1986.6 | F7: 2060.4 | G7: 2108 | H7: 2349.2
B8: Useful life | D8: =D5/D6 -> 19.299468 | E8: =E5/E6 -> 20.759952 | F8: =F5/F6 -> 20.338682 | G8: =G5/G6 -> 19.8665 | H8: =H5/H6 -> 19.909379
B9: Average age | D9: =D7/D6 -> 11.105139 | E9: =E7/E6 -> 11.981906 | F9: =F7/F6 -> 11.80745 | G9: =G7/G6 -> 10.54 | H9: =H7/H6 -> 10.644314
B11: Useful life | C11: =AVERAGE(D8:H8) -> 20.034796
B12: Average age | C12: =AVERAGE(D9:H9) -> 11.215762
B15: Right-of-use assets | D15: 2020 | E15: =D15+1 -> 2021 | F15: =E15+1 -> 2022 | G15: =F15+1 -> 2023 | H15: =G15+1 -> 2024
B17: Acquisition cost | D17: 446.4 | E17: 504.8 | F17: 552.6 | G17: 649.7 | H17: 751.5
B18: Depreciation expense | D18: 85.5 | E18: 84.5 | F18: 86.1 | G18: 106 | H18: 120.8
B19: Accumulated depreciation | D19: 131.1 | E19: 183.6 | F19: 219 | G19: 257.7 | H19: 337.8
B20: Useful life | D20: =D17/D18 -> 5.2210526 | E20: =E17/E18 -> 5.9739645 | F20: =F17/F18 -> 6.4181185 | G20: =G17/G18 -> 6.1292453 | H20: =H17/H18 -> 6.2210265
B21: Average life | D21: =D19/D18 -> 1.5333333 | E21: =E19/E18 -> 2.1727811 | F21: =F19/F18 -> 2.543554 | G21: =G19/G18 -> 2.4311321 | H21: =H19/H18 -> 2.7963576
B23: Useful life | C23: =AVERAGE(D20:H20) -> 5.9926815
B24: Average age | C24: =AVERAGE(D21:H21) -> 2.2954316
B27: Intangible assets | D27: 2020 | E27: =D27+1 -> 2021 | F27: =E27+1 -> 2022 | G27: =F27+1 -> 2023 | H27: =G27+1 -> 2024
B29: Acquisition cost | D29: 1644.2 | E29: 1752.5 | F29: 1774.5 | G29: 2886.2 | H29: 3123.1
B30: Amortization expense | D30: 112.3 | E30: 116.3 | F30: 123.9 | G30: 179.3 | H30: 214.1
B31: Accumulated amortization | D31: 560.7 | E31: 669.2 | F31: 771.1 | G31: 863 | H31: 1076.4
B32: Useful life | D32: =D29/D30 -> 14.64114 | E32: =E29/E30 -> 15.068788 | F32: =F29/F30 -> 14.322034 | G32: =G29/G30 -> 16.097044 | H32: =H29/H30 -> 14.587109
B33: Average life | D33: =D31/D30 -> 4.9928762 | E33: =E31/E30 -> 5.7540843 | F33: =F31/F30 -> 6.2235674 | G33: =G31/G30 -> 4.8131623 | H33: =H31/H30 -> 5.0275572
B35: Useful life | C35: =AVERAGE(D32:H32) -> 14.943223
B36: Average age | C36: =AVERAGE(D33:H33) -> 5.3622495

Sheet Tables
B3: Ratio Forecast
B5: Profitability | C5: =2023 -> 2023 | D5: =C5+1 -> 2024 | E5: =D5+1 -> 2025 | F5: =E5+1 -> 2026 | G5: =F5+1 -> 2027 | H5: =G5+1 -> 2028 | I5: =H5+1 -> 2029 | J5: =I5+1 -> 2030 | K5: =J5+1 -> 2031 | ... N5: =M5+1 -> 2034
B6: Gross Margin | C6: ='3-Statement Model'!H33 -> 0.53608101 | D6: ='3-Statement Model'!I33 -> 0.54543445 | E6: ='3-Statement Model'!J33 -> 0.55 | F6: ='3-Statement Model'!K33 -> 0.55 | G6: ='3-Statement Model'!L33 -> 0.55 | H6: ='3-Statement Model'!M33 -> 0.55 | I6: ='3-Statement Model'!N33 -> 0.55 | J6: ='3-Statement Model'!O33 -> 0.55 | ... N6: ='3-Statement Model'!S33 -> 0.55
B7: EBITDA Margin | C7: ='3-Statement Model'!H56 -> 0.18193547 | D7: ='3-Statement Model'!I56 -> 0.19293384 | E7: ='3-Statement Model'!J56 -> 0.192 | F7: ='3-Statement Model'!K56 -> 0.203 | G7: ='3-Statement Model'!L56 -> 0.21 | H7: ='3-Statement Model'!M56 -> 0.213 | I7: ='3-Statement Model'!N56 -> 0.213 | J7: ='3-Statement Model'!O56 -> 0.213 | ... N7: ='3-Statement Model'!S56 -> 0.213
B8: EBIT Margin | C8: ='3-Statement Model'!H73 -> 0.13783745 | D8: ='3-Statement Model'!I73 -> 0.14570139 | E8: ='3-Statement Model'!J73 -> 0.13910299 | F8: ='3-Statement Model'!K73 -> 0.14921281 | G8: ='3-Statement Model'!L73 -> 0.15615789 | H8: ='3-Statement Model'!M73 -> 0.16144776 | I8: ='3-Statement Model'!N73 -> 0.16651389 | J8: ='3-Statement Model'!O73 -> 0.1656833 | ... N8: ='3-Statement Model'!S73 -> 0.18591253
B9: EBT Margin | C9: ='3-Statement Model'!H93 -> 0.11891161 | D9: ='3-Statement Model'!I93 -> 0.13287314 | E9: ='3-Statement Model'!J93 -> 0.12629637 | F9: ='3-Statement Model'!K93 -> 0.1377022 | G9: ='3-Statement Model'!L93 -> 0.1461921 | H9: ='3-Statement Model'!M93 -> 0.15296063 | I9: ='3-Statement Model'!N93 -> 0.15900147 | J9: ='3-Statement Model'!O93 -> 0.15901454 | ... N9: ='3-Statement Model'!S93 -> 0.18291933
B10: Net Margin | C10: ='3-Statement Model'!H99 -> 0.094549143 | D10: ='3-Statement Model'!I99 -> 0.10606048 | E10: ='3-Statement Model'!J99 -> 0.10081084 | F10: ='3-Statement Model'!K99 -> 0.10991507 | G10: ='3-Statement Model'!L99 -> 0.11669179 | H10: ='3-Statement Model'!M99 -> 0.12209449 | I10: ='3-Statement Model'!N99 -> 0.12691634 | J10: ='3-Statement Model'!O99 -> 0.12692677 | ... N10: ='3-Statement Model'!S99 -> 0.14600778
B11: ROE | C11: ='3-Statement Model'!H98/(('3-Statement Model'!H148+'3-Statement Model'!G148)/2) -> 0.19496711 | D11: ='3-Statement Model'!I98/(('3-Statement Model'!I148+'3-Statement Model'!H148)/2) -> 0.19223421 | E11: ='3-Statement Model'!J98/(('3-Statement Model'!J148+'3-Statement Model'!I148)/2) -> 0.15512781 | F11: ='3-Statement Model'!K98/(('3-Statement Model'!K148+'3-Statement Model'!J148)/2) -> 0.16375509 | G11: ='3-Statement Model'!L98/(('3-Statement Model'!L148+'3-Statement Model'!K148)/2) -> 0.17058464 | H11: ='3-Statement Model'!M98/(('3-Statement Model'!M148+'3-Statement Model'!L148)/2) -> 0.17447208 | I11: ='3-Statement Model'!N98/(('3-Statement Model'!N148+'3-Statement Model'!M148)/2) -> 0.17682269 | J11: ='3-Statement Model'!O98/(('3-Statement Model'!O148+'3-Statement Model'!N148)/2) -> 0.17236225 | ... N11: ='3-Statement Model'!S98/(('3-Statement Model'!S148+'3-Statement Model'!R148)/2) -> 0.17878416
B12: ROA | C12: ='3-Statement Model'!H98/(('3-Statement Model'!H126+'3-Statement Model'!G126)/2) -> 0.079283716 | D12: ='3-Statement Model'!I98/(('3-Statement Model'!I126+'3-Statement Model'!H126)/2) -> 0.080417687 | E12: ='3-Statement Model'!J98/(('3-Statement Model'!J126+'3-Statement Model'!I126)/2) -> 0.070416872 | F12: ='3-Statement Model'!K98/(('3-Statement Model'!K126+'3-Statement Model'!J126)/2) -> 0.078241988 | G12: ='3-Statement Model'!L98/(('3-Statement Model'!L126+'3-Statement Model'!K126)/2) -> 0.085324867 | H12: ='3-Statement Model'!M98/(('3-Statement Model'!M126+'3-Statement Model'!L126)/2) -> 0.090684216 | I12: ='3-Statement Model'!N98/(('3-Statement Model'!N126+'3-Statement Model'!M126)/2) -> 0.0947897 | J12: ='3-Statement Model'!O98/(('3-Statement Model'!O126+'3-Statement Model'!N126)/2) -> 0.095022342 | ... N12: ='3-Statement Model'!S98/(('3-Statement Model'!S126+'3-Statement Model'!R126)/2) -> 0.10747825
B13: ROEC | C13: ='3-Statement Model'!H72/(('3-Statement Model'!G126-'3-Statement Model'!G134+'3-Statement Model'!G141+'3-Statement Model'!G148+'3-Statement Model'!H148+'3-Statement Model'!H141-'3-Statement Model'!H134+'3-Statement Model'!H126)/2) -> 0.073312652 | D13: ='3-Statement Model'!I72/(('3-Statement Model'!H126-'3-Statement Model'!H134+'3-Statement Model'!H141+'3-Statement Model'!H148+'3-Statement Model'!I148+'3-Statement Model'!I141-'3-Statement Model'!I134+'3-Statement Model'!I126)/2) -> 0.068483271 | E13: ='3-Statement Model'!J72/(('3-Statement Model'!I126-'3-Statement Model'!I134+'3-Statement Model'!I141+'3-Statement Model'!I148+'3-Statement Model'!J148+'3-Statement Model'!J141-'3-Statement Model'!J134+'3-Statement Model'!J126)/2) -> 0.057608279 | F13: ='3-Statement Model'!K72/(('3-Statement Model'!J126-'3-Statement Model'!J134+'3-Statement Model'!J141+'3-Statement Model'!J148+'3-Statement Model'!K148+'3-Statement Model'!K141-'3-Statement Model'!K134+'3-Statement Model'!K126)/2) -> 0.062576771 | G13: ='3-Statement Model'!L72/(('3-Statement Model'!K126-'3-Statement Model'!K134+'3-Statement Model'!K141+'3-Statement Model'!K148+'3-Statement Model'!L148+'3-Statement Model'!L141-'3-Statement Model'!L134+'3-Statement Model'!L126)/2) -> 0.067297953 | H13: ='3-Statement Model'!M72/(('3-Statement Model'!L126-'3-Statement Model'!L134+'3-Statement Model'!L141+'3-Statement Model'!L148+'3-Statement Model'!M148+'3-Statement Model'!M141-'3-Statement Model'!M134+'3-Statement Model'!M126)/2) -> 0.070702413 | I13: ='3-Statement Model'!N72/(('3-Statement Model'!M126-'3-Statement Model'!M134+'3-Statement Model'!M141+'3-Statement Model'!M148+'3-Statement Model'!N148+'3-Statement Model'!N141-'3-Statement Model'!N134+'3-Statement Model'!N126)/2) -> 0.073249647 | J13: ='3-Statement Model'!O72/(('3-Statement Model'!N126-'3-Statement Model'!N134+'3-Statement Model'!N141+'3-Statement Model'!N148+'3-Statement Model'!O148+'3-Statement Model'!O141-'3-Statement Model'!O134+'3-Statement Model'!O126)/2) -> 0.072961513 | ... N13: ='3-Statement Model'!S72/(('3-Statement Model'!R126-'3-Statement Model'!R134+'3-Statement Model'!R141+'3-Statement Model'!R148+'3-Statement Model'!S148+'3-Statement Model'!S141-'3-Statement Model'!S134+'3-Statement Model'!S126)/2) -> 0.07993983
B14: EPS (in CHF) | C14: ='3-Statement Model'!H104/(DCF!$C$107) -> 6.6176762 | D14: ='3-Statement Model'!I104/(DCF!$C$107) -> 7.7611259 | E14: ='3-Statement Model'!J104/(DCF!$C$107) -> 7.0950109 | F14: ='3-Statement Model'!K104/(DCF!$C$107) -> 8.1442779 | G14: ='3-Statement Model'!L104/(DCF!$C$107) -> 9.2239344 | H14: ='3-Statement Model'!M104/(DCF!$C$107) -> 10.239894 | I14: ='3-Statement Model'!N104/(DCF!$C$107) -> 11.231306 | J14: ='3-Statement Model'!O104/(DCF!$C$107) -> 11.790202 | ... N14: ='3-Statement Model'!S104/(DCF!$C$107) -> 15.635079
B16: Liquidity | C16: =C5 -> 2023 | D16: =D5 -> 2024 | E16: =E5 -> 2025 | F16: =F5 -> 2026 | G16: =G5 -> 2027 | H16: =H5 -> 2028 | I16: =I5 -> 2029 | J16: =J5 -> 2030 | ... N16: =N5 -> 2034
B17: Current Ratio | C17: ='3-Statement Model'!H117/'3-Statement Model'!H134 -> 1.229918 | D17: ='3-Statement Model'!I117/'3-Statement Model'!I134 -> 1.7650267 | E17: ='3-Statement Model'!J117/'3-Statement Model'!J134 -> 1.9385939 | F17: ='3-Statement Model'!K117/'3-Statement Model'!K134 -> 2.0316018 | G17: ='3-Statement Model'!L117/'3-Statement Model'!L134 -> 2.0973835 | H17: ='3-Statement Model'!M117/'3-Statement Model'!M134 -> 2.2215072 | I17: ='3-Statement Model'!N117/'3-Statement Model'!N134 -> 2.3314933 | J17: ='3-Statement Model'!O117/'3-Statement Model'!O134 -> 2.4524218 | ... N17: ='3-Statement Model'!S117/'3-Statement Model'!S134 -> 3.1735056
B18: Quick Ratio | C18: =('3-Statement Model'!H117-'3-Statement Model'!H113-'3-Statement Model'!H114)/'3-Statement Model'!H134 -> 0.79534543 | D18: =('3-Statement Model'!I117-'3-Statement Model'!I113-'3-Statement Model'!I114)/'3-Statement Model'!I134 -> 1.1375029 | E18: =('3-Statement Model'!J117-'3-Statement Model'!J113-'3-Statement Model'!J114)/'3-Statement Model'!J134 -> 1.2786503 | F18: =('3-Statement Model'!K117-'3-Statement Model'!K113-'3-Statement Model'!K114)/'3-Statement Model'!K134 -> 1.3876515 | G18: =('3-Statement Model'!L117-'3-Statement Model'!L113-'3-Statement Model'!L114)/'3-Statement Model'!L134 -> 1.4806141 | H18: =('3-Statement Model'!M117-'3-Statement Model'!M113-'3-Statement Model'!M114)/'3-Statement Model'!M134 -> 1.5953311 | I18: =('3-Statement Model'!N117-'3-Statement Model'!N113-'3-Statement Model'!N114)/'3-Statement Model'!N134 -> 1.6970276 | J18: =('3-Statement Model'!O117-'3-Statement Model'!O113-'3-Statement Model'!O114)/'3-Statement Model'!O134 -> 1.8106562 | ... N18: =('3-Statement Model'!S117-'3-Statement Model'!S113-'3-Statement Model'!S114)/'3-Statement Model'!S134 -> 2.511442
B20: Working Capital | C20: =C5 -> 2023 | D20: =D5 -> 2024 | E20: =E5 -> 2025 | F20: =F5 -> 2026 | G20: =G5 -> 2027 | H20: =H5 -> 2028 | I20: =I5 -> 2029 | J20: =J5 -> 2030 | ... N20: =N5 -> 2034
B21: DSO | C21: =(('3-Statement Model'!G112+'3-Statement Model'!H112)/2)/'3-Statement Model'!H24*'3-Statement Model'!H107 -> 60.55078 | D21: =(('3-Statement Model'!H112+'3-Statement Model'!I112)/2)/'3-Statement Model'!I24*'3-Statement Model'!I107 -> 64.916264 | E21: =(('3-Statement Model'!I112+'3-Statement Model'!J112)/2)/'3-Statement Model'!J24*'3-Statement Model'!J107 -> 69.580001 | F21: =(('3-Statement Model'!J112+'3-Statement Model'!K112)/2)/'3-Statement Model'!K24*'3-Statement Model'!K107 -> 66.272979 | G21: =(('3-Statement Model'!K112+'3-Statement Model'!L112)/2)/'3-Statement Model'!L24*'3-Statement Model'!L107 -> 63.862442 | H21: =(('3-Statement Model'!L112+'3-Statement Model'!M112)/2)/'3-Statement Model'!M24*'3-Statement Model'!M107 -> 63.050592 | I21: =(('3-Statement Model'!M112+'3-Statement Model'!N112)/2)/'3-Statement Model'!N24*'3-Statement Model'!N107 -> 63.220525 | J21: =(('3-Statement Model'!N112+'3-Statement Model'!O112)/2)/'3-Statement Model'!O24*'3-Statement Model'!O107 -> 63.378962 | ... N21: =(('3-Statement Model'!R112+'3-Statement Model'!S112)/2)/'3-Statement Model'!S24*'3-Statement Model'!S107 -> 64.030252
B22: DIO | C22: =(('3-Statement Model'!H113+'3-Statement Model'!G113)/2)/'3-Statement Model'!H29*'3-Statement Model'!H107 -> 85.8805 | D22: =(('3-Statement Model'!I113+'3-Statement Model'!H113)/2)/'3-Statement Model'!I29*'3-Statement Model'!I107 -> 88.384732 | E22: =(('3-Statement Model'!J113+'3-Statement Model'!I113)/2)/'3-Statement Model'!J29*'3-Statement Model'!J107 -> 98.346783 | F22: =(('3-Statement Model'!K113+'3-Statement Model'!J113)/2)/'3-Statement Model'!K29*'3-Statement Model'!K107 -> 94.997071 | G22: =(('3-Statement Model'!L113+'3-Statement Model'!K113)/2)/'3-Statement Model'!L29*'3-Statement Model'!L107 -> 88.720865 | H22: =(('3-Statement Model'!M113+'3-Statement Model'!L113)/2)/'3-Statement Model'!M29*'3-Statement Model'!M107 -> 85.844584 | I22: =(('3-Statement Model'!N113+'3-Statement Model'!M113)/2)/'3-Statement Model'!N29*'3-Statement Model'!N107 -> 86.075952 | J22: =(('3-Statement Model'!O113+'3-Statement Model'!N113)/2)/'3-Statement Model'!O29*'3-Statement Model'!O107 -> 86.291667 | ... N22: =(('3-Statement Model'!S113+'3-Statement Model'!R113)/2)/'3-Statement Model'!S29*'3-Statement Model'!S107 -> 87.178411
B23: DPO | C23: =(('3-Statement Model'!H128+'3-Statement Model'!G128)/2)/'3-Statement Model'!H29*'3-Statement Model'!H107 -> 74.374928 | D23: =(('3-Statement Model'!I128+'3-Statement Model'!H128)/2)/'3-Statement Model'!I29*'3-Statement Model'!I107 -> 79.200174 | E23: =(('3-Statement Model'!J128+'3-Statement Model'!I128)/2)/'3-Statement Model'!J29*'3-Statement Model'!J107 -> 83.450815 | F23: =(('3-Statement Model'!K128+'3-Statement Model'!J128)/2)/'3-Statement Model'!K29*'3-Statement Model'!K107 -> 77.597744 | G23: =(('3-Statement Model'!L128+'3-Statement Model'!K128)/2)/'3-Statement Model'!L29*'3-Statement Model'!L107 -> 76.722875 | H23: =(('3-Statement Model'!M128+'3-Statement Model'!L128)/2)/'3-Statement Model'!M29*'3-Statement Model'!M107 -> 76.923987 | I23: =(('3-Statement Model'!N128+'3-Statement Model'!M128)/2)/'3-Statement Model'!N29*'3-Statement Model'!N107 -> 77.131312 | J23: =(('3-Statement Model'!O128+'3-Statement Model'!N128)/2)/'3-Statement Model'!O29*'3-Statement Model'!O107 -> 77.324611 | ... N23: =(('3-Statement Model'!S128+'3-Statement Model'!R128)/2)/'3-Statement Model'!S29*'3-Statement Model'!S107 -> 78.119208
B24: Cash Conversion Cycle | C24: =C21+C22-C23 -> 72.056352 | D24: =D21+D22-D23 -> 74.100822 | E24: =E21+E22-E23 -> 84.475969 | F24: =F21+F22-F23 -> 83.672306 | G24: =G21+G22-G23 -> 75.860431 | H24: =H21+H22-H23 -> 71.971188 | I24: =I21+I22-I23 -> 72.165165 | J24: =J21+J22-J23 -> 72.346018 | ... N24: =N21+N22-N23 -> 73.089455
B25: Asset Turnover | C25: ='3-Statement Model'!H24/(('3-Statement Model'!H126+'3-Statement Model'!G126)/2) -> 0.83854505 | D25: ='3-Statement Model'!I24/(('3-Statement Model'!I126+'3-Statement Model'!H126)/2) -> 0.75822483 | E25: ='3-Statement Model'!J24/(('3-Statement Model'!J126+'3-Statement Model'!I126)/2) -> 0.69850493 | F25: ='3-Statement Model'!K24/(('3-Statement Model'!K126+'3-Statement Model'!J126)/2) -> 0.71184038 | G25: ='3-Statement Model'!L24/(('3-Statement Model'!L126+'3-Statement Model'!K126)/2) -> 0.73119856 | H25: ='3-Statement Model'!M24/(('3-Statement Model'!M126+'3-Statement Model'!L126)/2) -> 0.74273801 | I25: ='3-Statement Model'!N24/(('3-Statement Model'!N126+'3-Statement Model'!M126)/2) -> 0.7468676 | J25: ='3-Statement Model'!O24/(('3-Statement Model'!O126+'3-Statement Model'!N126)/2) -> 0.74863908 | ... N25: ='3-Statement Model'!S24/(('3-Statement Model'!S126+'3-Statement Model'!R126)/2) -> 0.73611321
B26: Inventory Turnover | C26: ='3-Statement Model'!H29/(('3-Statement Model'!H113+'3-Statement Model'!G113)/2) -> 4.2500917 | D26: ='3-Statement Model'!I29/(('3-Statement Model'!I113+'3-Statement Model'!H113)/2) -> 4.1296725 | E26: ='3-Statement Model'!J29/(('3-Statement Model'!J113+'3-Statement Model'!I113)/2) -> 3.7113568 | F26: ='3-Statement Model'!K29/(('3-Statement Model'!K113+'3-Statement Model'!J113)/2) -> 3.8422237 | G26: ='3-Statement Model'!L29/(('3-Statement Model'!L113+'3-Statement Model'!K113)/2) -> 4.1140266 | H26: ='3-Statement Model'!M29/(('3-Statement Model'!M113+'3-Statement Model'!L113)/2) -> 4.2518699 | I26: ='3-Statement Model'!N29/(('3-Statement Model'!N113+'3-Statement Model'!M113)/2) -> 4.2404411 | J26: ='3-Statement Model'!O29/(('3-Statement Model'!O113+'3-Statement Model'!N113)/2) -> 4.2298407 | ... N26: ='3-Statement Model'!S29/(('3-Statement Model'!S113+'3-Statement Model'!R113)/2) -> 4.1868164
B27: Fixed Asset Turnover | C27: ='3-Statement Model'!H24/(('3-Statement Model'!H117+'3-Statement Model'!G117)/2) -> 2.4371605 | D27: ='3-Statement Model'!I24/(('3-Statement Model'!I117+'3-Statement Model'!H117)/2) -> 2.6841991 | E27: ='3-Statement Model'!J24/(('3-Statement Model'!J117+'3-Statement Model'!I117)/2) -> 2.4095247 | F27: ='3-Statement Model'!K24/(('3-Statement Model'!K117+'3-Statement Model'!J117)/2) -> 2.3689069 | G27: ='3-Statement Model'!L24/(('3-Statement Model'!L117+'3-Statement Model'!K117)/2) -> 2.3343883 | H27: ='3-Statement Model'!M24/(('3-Statement Model'!M117+'3-Statement Model'!L117)/2) -> 2.2616077 | I27: ='3-Statement Model'!N24/(('3-Statement Model'!N117+'3-Statement Model'!M117)/2) -> 2.1702529 | J27: ='3-Statement Model'!O24/(('3-Statement Model'!O117+'3-Statement Model'!N117)/2) -> 2.0857987 | ... N27: ='3-Statement Model'!S24/(('3-Statement Model'!S117+'3-Statement Model'!R117)/2) -> 1.6588707
B28: Receivables Turnover | C28: ='3-Statement Model'!H24/(('3-Statement Model'!H112+'3-Statement Model'!G112)/2) -> 6.0279983 | D28: ='3-Statement Model'!I24/(('3-Statement Model'!I112+'3-Statement Model'!H112)/2) -> 5.622628 | E28: ='3-Statement Model'!J24/(('3-Statement Model'!J112+'3-Statement Model'!I112)/2) -> 5.2457602 | F28: ='3-Statement Model'!K24/(('3-Statement Model'!K112+'3-Statement Model'!J112)/2) -> 5.5075237 | G28: ='3-Statement Model'!L24/(('3-Statement Model'!L112+'3-Statement Model'!K112)/2) -> 5.7154094 | H28: ='3-Statement Model'!M24/(('3-Statement Model'!M112+'3-Statement Model'!L112)/2) -> 5.789002 | I28: ='3-Statement Model'!N24/(('3-Statement Model'!N112+'3-Statement Model'!M112)/2) -> 5.7734414 | J28: ='3-Statement Model'!O24/(('3-Statement Model'!O112+'3-Statement Model'!N112)/2) -> 5.7590088 | ... N28: ='3-Statement Model'!S24/(('3-Statement Model'!S112+'3-Statement Model'!R112)/2) -> 5.7004304
B30: Solvency | C30: =2023 -> 2023 | D30: =C30+1 -> 2024 | E30: =D30+1 -> 2025 | F30: =E30+1 -> 2026 | G30: =F30+1 -> 2027 | H30: =G30+1 -> 2028 | I30: =H30+1 -> 2029 | J30: =I30+1 -> 2030 | K30: =J30+1 -> 2031 | ... N30: =M30+1 -> 2034
B31: Debt/Equity | C31: =('3-Statement Model'!H134+'3-Statement Model'!H141)/'3-Statement Model'!H148 -> 1.5366918 | D31: =('3-Statement Model'!I134+'3-Statement Model'!I141)/'3-Statement Model'!I148 -> 1.2672986 | E31: =('3-Statement Model'!J134+'3-Statement Model'!J141)/'3-Statement Model'!J148 -> 1.1438314 | F31: =('3-Statement Model'!K134+'3-Statement Model'!K141)/'3-Statement Model'!K148 -> 1.0461301 | G31: =('3-Statement Model'!L134+'3-Statement Model'!L141)/'3-Statement Model'!L148 -> 0.95608801 | H31: =('3-Statement Model'!M134+'3-Statement Model'!M141)/'3-Statement Model'!M148 -> 0.89430873 | I31: =('3-Statement Model'!N134+'3-Statement Model'!N141)/'3-Statement Model'!N148 -> 0.83868494 | J31: =('3-Statement Model'!O134+'3-Statement Model'!O141)/'3-Statement Model'!O148 -> 0.79084172 | ... N31: =('3-Statement Model'!S134+'3-Statement Model'!S141)/'3-Statement Model'!S148 -> 0.64796025
B32: Debt/Assets | C32: =('3-Statement Model'!H134+'3-Statement Model'!H141)/'3-Statement Model'!H126 -> 0.60578175 | D32: =('3-Statement Model'!I134+'3-Statement Model'!I141)/'3-Statement Model'!I126 -> 0.5589465 | E32: =('3-Statement Model'!J134+'3-Statement Model'!J141)/'3-Statement Model'!J126 -> 0.53354541 | F32: =('3-Statement Model'!K134+'3-Statement Model'!K141)/'3-Statement Model'!K126 -> 0.51127252 | G32: =('3-Statement Model'!L134+'3-Statement Model'!L141)/'3-Statement Model'!L126 -> 0.48877556 | H32: =('3-Statement Model'!M134+'3-Statement Model'!M141)/'3-Statement Model'!M126 -> 0.47210295 | I32: =('3-Statement Model'!N134+'3-Statement Model'!N141)/'3-Statement Model'!N126 -> 0.45613303 | J32: =('3-Statement Model'!O134+'3-Statement Model'!O141)/'3-Statement Model'!O126 -> 0.44160336 | ... N32: =('3-Statement Model'!S134+'3-Statement Model'!S141)/'3-Statement Model'!S126 -> 0.39318925
B33: Net Debt/EBITDA | C33: 2.8 | D33: 2.4 | E33: 2.3 | F33: 1.9 | G33: 1.5 | H33: 1.3 | I33: 1.1 | J33: 0.9 | K33: 0.7 | L33: 0.5 | M33: 0.3 | N33: 0.1
B34: Interest Coverage Ratio | C34: ='3-Statement Model'!H72/'3-Statement Model'!H77 -> 9.3488232 | D34: ='3-Statement Model'!I72/'3-Statement Model'!I77 -> 9.2194728 | E34: ='3-Statement Model'!J72/'3-Statement Model'!J77 -> 10.730219 | F34: ='3-Statement Model'!K72/'3-Statement Model'!K77 -> 12.285161 | G34: ='3-Statement Model'!L72/'3-Statement Model'!L77 -> 14.053444 | H34: ='3-Statement Model'!M72/'3-Statement Model'!M77 -> 15.977689 | I34: ='3-Statement Model'!N72/'3-Statement Model'!N77 -> 17.387446 | J34: ='3-Statement Model'!O72/'3-Statement Model'!O77 -> 18.160862 | ... N34: ='3-Statement Model'!S72/'3-Statement Model'!S77 -> 23.490268
B35: D/(D+E) | C35: =('3-Statement Model'!H134+'3-Statement Model'!H141)/'3-Statement Model'!H150 -> 0.60578578 | D35: =('3-Statement Model'!I134+'3-Statement Model'!I141)/'3-Statement Model'!I150 -> 0.5589465 | E35: =('3-Statement Model'!J134+'3-Statement Model'!J141)/'3-Statement Model'!J150 -> 0.53354541 | F35: =('3-Statement Model'!K134+'3-Statement Model'!K141)/'3-Statement Model'!K150 -> 0.51127252 | G35: =('3-Statement Model'!L134+'3-Statement Model'!L141)/'3-Statement Model'!L150 -> 0.48877556 | H35: =('3-Statement Model'!M134+'3-Statement Model'!M141)/'3-Statement Model'!M150 -> 0.47210295 | I35: =('3-Statement Model'!N134+'3-Statement Model'!N141)/'3-Statement Model'!N150 -> 0.45613303 | J35: =('3-Statement Model'!O134+'3-Statement Model'!O141)/'3-Statement Model'!O150 -> 0.44160336 | ... N35: =('3-Statement Model'!S134+'3-Statement Model'!S141)/'3-Statement Model'!S150 -> 0.39318925
B37: Dupont Analysis | C37: =2023 -> 2023 | D37: =C37+1 -> 2024 | E37: =D37+1 -> 2025 | F37: =E37+1 -> 2026 | G37: =F37+1 -> 2027 | H37: =G37+1 -> 2028 | I37: =H37+1 -> 2029 | J37: =I37+1 -> 2030 | K37: =J37+1 -> 2031 | ... N37: =M37+1 -> 2034
B38: Net Margin | C38: ='3-Statement Model'!H98/'3-Statement Model'!H24 -> 0.094549143 | D38: ='3-Statement Model'!I98/'3-Statement Model'!I24 -> 0.10606048 | E38: ='3-Statement Model'!J98/'3-Statement Model'!J24 -> 0.10081084 | F38: ='3-Statement Model'!K98/'3-Statement Model'!K24 -> 0.10991507 | G38: ='3-Statement Model'!L98/'3-Statement Model'!L24 -> 0.11669179 | H38: ='3-Statement Model'!M98/'3-Statement Model'!M24 -> 0.12209449 | I38: ='3-Statement Model'!N98/'3-Statement Model'!N24 -> 0.12691634 | J38: ='3-Statement Model'!O98/'3-Statement Model'!O24 -> 0.12692677 | ... N38: ='3-Statement Model'!S98/'3-Statement Model'!S24 -> 0.14600778
B39: Efficiency | C39: ='3-Statement Model'!H24/(('3-Statement Model'!H126+'3-Statement Model'!G126)/2) -> 0.83854505 | D39: ='3-Statement Model'!I24/(('3-Statement Model'!I126+'3-Statement Model'!H126)/2) -> 0.75822483 | E39: ='3-Statement Model'!J24/(('3-Statement Model'!J126+'3-Statement Model'!I126)/2) -> 0.69850493 | F39: ='3-Statement Model'!K24/(('3-Statement Model'!K126+'3-Statement Model'!J126)/2) -> 0.71184038 | G39: ='3-Statement Model'!L24/(('3-Statement Model'!L126+'3-Statement Model'!K126)/2) -> 0.73119856 | H39: ='3-Statement Model'!M24/(('3-Statement Model'!M126+'3-Statement Model'!L126)/2) -> 0.74273801 | I39: ='3-Statement Model'!N24/(('3-Statement Model'!N126+'3-Statement Model'!M126)/2) -> 0.7468676 | J39: ='3-Statement Model'!O24/(('3-Statement Model'!O126+'3-Statement Model'!N126)/2) -> 0.74863908 | ... N39: ='3-Statement Model'!S24/(('3-Statement Model'!S126+'3-Statement Model'!R126)/2) -> 0.73611321
B40: Leverage | C40: =(('3-Statement Model'!H126+'3-Statement Model'!G126)/2)/(('3-Statement Model'!H148+'3-Statement Model'!G148)/2) -> 2.4591066 | D40: =(('3-Statement Model'!I126+'3-Statement Model'!H126)/2)/(('3-Statement Model'!I148+'3-Statement Model'!H148)/2) -> 2.3904468 | E40: =(('3-Statement Model'!J126+'3-Statement Model'!I126)/2)/(('3-Statement Model'!J148+'3-Statement Model'!I148)/2) -> 2.2029921 | F40: =(('3-Statement Model'!K126+'3-Statement Model'!J126)/2)/(('3-Statement Model'!K148+'3-Statement Model'!J148)/2) -> 2.0929311 | G40: =(('3-Statement Model'!L126+'3-Statement Model'!K126)/2)/(('3-Statement Model'!L148+'3-Statement Model'!K148)/2) -> 1.9992371 | H40: =(('3-Statement Model'!M126+'3-Statement Model'!L126)/2)/(('3-Statement Model'!M148+'3-Statement Model'!L148)/2) -> 1.923952 | I40: =(('3-Statement Model'!N126+'3-Statement Model'!M126)/2)/(('3-Statement Model'!N148+'3-Statement Model'!M148)/2) -> 1.865421 | J40: =(('3-Statement Model'!O126+'3-Statement Model'!N126)/2)/(('3-Statement Model'!O148+'3-Statement Model'!N148)/2) -> 1.8139129 | ... N40: =(('3-Statement Model'!S126+'3-Statement Model'!R126)/2)/(('3-Statement Model'!S148+'3-Statement Model'!R148)/2) -> 1.663445
B41: ROE | C41: =C38*C39*C40 -> 0.19496711 | D41: =D38*D39*D40 -> 0.19223421 | E41: =E38*E39*E40 -> 0.15512781 | F41: =F38*F39*F40 -> 0.16375509 | G41: =G38*G39*G40 -> 0.17058464 | H41: =H38*H39*H40 -> 0.17447208 | I41: =I38*I39*I40 -> 0.17682269 | J41: =J38*J39*J40 -> 0.17236225 | ... N41: =N38*N39*N40 -> 0.17878416
B43: Projected Income Statement
B45: (CHF mm) | C45: =2023 -> 2023 | D45: =C45+1 -> 2024 | E45: =D45+1 -> 2025 | F45: =E45+1 -> 2026 | G45: =F45+1 -> 2027 | H45: =G45+1 -> 2028 | I45: =H45+1 -> 2029 | J45: =I45+1 -> 2030 | K45: =J45+1 -> 2031 | ... N45: =M45+1 -> 2034
B46: Revenue | C46: ='3-Statement Model'!H24 -> 11238.6 | D46: ='3-Statement Model'!I24 -> 11763.1 | E46: ='3-Statement Model'!J24 -> 11315.208 | F46: ='3-Statement Model'!K24 -> 11911.479 | G46: ='3-Statement Model'!L24 -> 12706.363 | H46: ='3-Statement Model'!M24 -> 13481.257 | I46: ='3-Statement Model'!N24 -> 14224.394 | J46: ='3-Statement Model'!O24 -> 14931.593 | ... N46: ='3-Statement Model'!S24 -> 17211.858
B47: COGS | C47: ='3-Statement Model'!H29 -> 5213.8 | D47: ='3-Statement Model'!I29 -> 5347.1 | E47: ='3-Statement Model'!J29 -> 5091.8435 | F47: ='3-Statement Model'!K29 -> 5360.1657 | G47: ='3-Statement Model'!L29 -> 5717.8634 | H47: ='3-Statement Model'!M29 -> 6066.5656 | I47: ='3-Statement Model'!N29 -> 6400.9774 | J47: ='3-Statement Model'!O29 -> 6719.217 | ... N47: ='3-Statement Model'!S29 -> 7745.336
B48: Gross Profit | C48: ='3-Statement Model'!H32 -> 6024.8 | D48: ='3-Statement Model'!I32 -> 6416 | E48: ='3-Statement Model'!J32 -> 6223.3642 | F48: ='3-Statement Model'!K32 -> 6551.3137 | G48: ='3-Statement Model'!L32 -> 6988.4997 | H48: ='3-Statement Model'!M32 -> 7414.6912 | I48: ='3-Statement Model'!N32 -> 7823.4168 | J48: ='3-Statement Model'!O32 -> 8212.3763 | ... N48: ='3-Statement Model'!S32 -> 9466.5218
B49: Opex | C49: ='3-Statement Model'!H52 -> 3980.1 | D49: ='3-Statement Model'!I52 -> 4146.5 | E49: ='3-Statement Model'!J52 -> 4050.8444 | F49: ='3-Statement Model'!K52 -> 4133.2834 | G49: ='3-Statement Model'!L52 -> 4320.1634 | H49: ='3-Statement Model'!M52 -> 4543.1835 | I49: ='3-Statement Model'!N52 -> 4793.6209 | J49: ='3-Statement Model'!O52 -> 5031.9469 | ... N49: ='3-Statement Model'!S52 -> 5800.3961
B50: EBITDA | C50: ='3-Statement Model'!H55 -> 2044.7 | D50: ='3-Statement Model'!I55 -> 2269.5 | E50: ='3-Statement Model'!J55 -> 2172.5199 | F50: ='3-Statement Model'!K55 -> 2418.0303 | G50: ='3-Statement Model'!L55 -> 2668.3362 | H50: ='3-Statement Model'!M55 -> 2871.5077 | I50: ='3-Statement Model'!N55 -> 3029.796 | J50: ='3-Statement Model'!O55 -> 3180.4294 | ... N50: ='3-Statement Model'!S55 -> 3666.1257
B51: Depreciation | C51: ='3-Statement Model'!H60 -> 306 | D51: ='3-Statement Model'!I60 -> 341.5 | E51: ='3-Statement Model'!J60 -> 383.24313 | F51: ='3-Statement Model'!K60 -> 423.62303 | G51: ='3-Statement Model'!L60 -> 465.19318 | H51: ='3-Statement Model'!M60 -> 474.04774 | I51: ='3-Statement Model'!N60 -> 438.18835 | J51: ='3-Statement Model'!O60 -> 481.25332 | ... N51: ='3-Statement Model'!S60 -> 320.73894
B52: Amortization | C52: ='3-Statement Model'!H63 -> 179.3 | D52: ='3-Statement Model'!I63 -> 214.1 | E52: ='3-Statement Model'!J63 -> 215.29748 | F52: ='3-Statement Model'!K63 -> 217.062 | G52: ='3-Statement Model'!L63 -> 218.94426 | H52: ='3-Statement Model'!M63 -> 220.94131 | I52: ='3-Statement Model'!N63 -> 223.04844 | J52: ='3-Statement Model'!O63 -> 225.26034 | ... N52: ='3-Statement Model'!S63 -> 145.48674
B53: EBIT | C53: ='3-Statement Model'!H72 -> 1549.1 | D53: ='3-Statement Model'!I72 -> 1713.9 | E53: ='3-Statement Model'!J72 -> 1573.9793 | F53: ='3-Statement Model'!K72 -> 1777.3453 | G53: ='3-Statement Model'!L72 -> 1984.1988 | H53: ='3-Statement Model'!M72 -> 2176.5187 | I53: ='3-Statement Model'!N72 -> 2368.5592 | J53: ='3-Statement Model'!O72 -> 2473.9157 | ... N53: ='3-Statement Model'!S72 -> 3199.9
B54: Net Finance Expense | C54: ='3-Statement Model'!H77-'3-Statement Model'!H80-'3-Statement Model'!H83+'3-Statement Model'!H86-'3-Statement Model'!H89 -> 212.7 | D54: ='3-Statement Model'!I77-'3-Statement Model'!I80-'3-Statement Model'!I83+'3-Statement Model'!I86-'3-Statement Model'!I89 -> 150.9 | E54: ='3-Statement Model'!J77-'3-Statement Model'!J80-'3-Statement Model'!J83+'3-Statement Model'!J86-'3-Statement Model'!J89 -> 144.90962 | F54: ='3-Statement Model'!K77-'3-Statement Model'!K80-'3-Statement Model'!K83+'3-Statement Model'!K86-'3-Statement Model'!K89 -> 137.10843 | G54: ='3-Statement Model'!L77-'3-Statement Model'!L80-'3-Statement Model'!L83+'3-Statement Model'!L86-'3-Statement Model'!L89 -> 126.6289 | H54: ='3-Statement Model'!M77-'3-Statement Model'!M80-'3-Statement Model'!M83+'3-Statement Model'!M86-'3-Statement Model'!M89 -> 114.41711 | I54: ='3-Statement Model'!N77-'3-Statement Model'!N80-'3-Statement Model'!N83+'3-Statement Model'!N86-'3-Statement Model'!N89 -> 106.85956 | J54: ='3-Statement Model'!O77-'3-Statement Model'!O80-'3-Statement Model'!O83+'3-Statement Model'!O86-'3-Statement Model'!O89 -> 99.575191 | ... N54: ='3-Statement Model'!S77-'3-Statement Model'!S80-'3-Statement Model'!S83+'3-Statement Model'!S86-'3-Statement Model'!S89 -> 51.518539
B55: EBT | C55: ='3-Statement Model'!H92 -> 1336.4 | D55: ='3-Statement Model'!I92 -> 1563 | E55: ='3-Statement Model'!J92 -> 1429.0696 | F55: ='3-Statement Model'!K92 -> 1640.2369 | G55: ='3-Statement Model'!L92 -> 1857.5699 | H55: ='3-Statement Model'!M92 -> 2062.1015 | I55: ='3-Statement Model'!N92 -> 2261.6996 | J55: ='3-Statement Model'!O92 -> 2374.3405 | ... N55: ='3-Statement Model'!S92 -> 3148.3815
B56: Income Tax | C56: ='3-Statement Model'!H95 -> 273.8 | D56: ='3-Statement Model'!I95 -> 315.4 | E56: ='3-Statement Model'!J95 -> 288.374 | F56: ='3-Statement Model'!K95 -> 330.98574 | G56: ='3-Statement Model'!L95 -> 374.84168 | H56: ='3-Statement Model'!M95 -> 416.11441 | I56: ='3-Statement Model'!N95 -> 456.39159 | J56: ='3-Statement Model'!O95 -> 479.12156 | ... N56: ='3-Statement Model'!S95 -> 635.31639
B57: Net Income | C57: ='3-Statement Model'!H98 -> 1062.6 | D57: ='3-Statement Model'!I98 -> 1247.6 | E57: ='3-Statement Model'!J98 -> 1140.6956 | F57: ='3-Statement Model'!K98 -> 1309.2511 | G57: ='3-Statement Model'!L98 -> 1482.7282 | H57: ='3-Statement Model'!M98 -> 1645.9871 | I57: ='3-Statement Model'!N98 -> 1805.308 | J57: ='3-Statement Model'!O98 -> 1895.2189 | ... N57: ='3-Statement Model'!S98 -> 2513.0651
B59: Projected Balance Sheet
B61: (CHF mm) | C61: =2023 -> 2023 | D61: =C61+1 -> 2024 | E61: =D61+1 -> 2025 | F61: =E61+1 -> 2026 | G61: =F61+1 -> 2027 | H61: =G61+1 -> 2028 | I61: =H61+1 -> 2029 | J61: =I61+1 -> 2030 | K61: =J61+1 -> 2031 | ... N61: =M61+1 -> 2034
B62: Cash and cash equivalents | C62: ='3-Statement Model'!H111 -> 643.9 | D62: ='3-Statement Model'!I111 -> 707.5 | E62: ='3-Statement Model'!J111 -> 987.49964 | F62: ='3-Statement Model'!K111 -> 1325.8385 | G62: ='3-Statement Model'!L111 -> 1676.2599 | H62: ='3-Statement Model'!M111 -> 2041.8153 | I62: ='3-Statement Model'!N111 -> 2394.1568 | J62: ='3-Statement Model'!O111 -> 2802.8129 | ... N62: ='3-Statement Model'!S111 -> 5430.6121
B63: Accounts receivables | C63: ='3-Statement Model'!H112 -> 2009.2 | D63: ='3-Statement Model'!I112 -> 2175 | E63: ='3-Statement Model'!J112 -> 2139.0393 | F63: ='3-Statement Model'!K112 -> 2186.4907 | G63: ='3-Statement Model'!L112 -> 2259.862 | H63: ='3-Statement Model'!M112 -> 2397.679 | I63: ='3-Statement Model'!N112 -> 2529.848 | J63: ='3-Statement Model'!O112 -> 2655.6253 | ... N63: ='3-Statement Model'!S112 -> 3061.1767
B64: Inventories | C64: ='3-Statement Model'!H113 -> 1240.7 | D64: ='3-Statement Model'!I113 -> 1348.9 | E64: ='3-Statement Model'!J113 -> 1395.0256 | F64: ='3-Statement Model'!K113 -> 1395.1116 | G64: ='3-Statement Model'!L113 -> 1384.5803 | H64: ='3-Statement Model'!M113 -> 1469.0185 | I64: ='3-Statement Model'!N113 -> 1549.9964 | J64: ='3-Statement Model'!O113 -> 1627.0581 | ... N64: ='3-Statement Model'!S113 -> 1875.5327
B65: Other current assets | C65: ='3-Statement Model'!H114+'3-Statement Model'!H115+'3-Statement Model'!H116 -> 307.6 | D65: ='3-Statement Model'!I114+'3-Statement Model'!I115+'3-Statement Model'!I116 -> 331.9 | E65: ='3-Statement Model'!J114+'3-Statement Model'!J115+'3-Statement Model'!J116 -> 307.20163 | F65: ='3-Statement Model'!K114+'3-Statement Model'!K115+'3-Statement Model'!K116 -> 320.3126 | G65: ='3-Statement Model'!L114+'3-Statement Model'!L115+'3-Statement Model'!L116 -> 337.79071 | H65: ='3-Statement Model'!M114+'3-Statement Model'!M115+'3-Statement Model'!M116 -> 354.82926 | I65: ='3-Statement Model'!N114+'3-Statement Model'!N115+'3-Statement Model'!N116 -> 371.16956 | J65: ='3-Statement Model'!O114+'3-Statement Model'!O115+'3-Statement Model'!O116 -> 386.71963 | ... N65: ='3-Statement Model'!S114+'3-Statement Model'!S115+'3-Statement Model'!S116 -> 436.85866
B66: Total current assets | C66: ='3-Statement Model'!H117 -> 4201.4 | D66: ='3-Statement Model'!I117 -> 4563.3 | E66: ='3-Statement Model'!J117 -> 4828.7662 | F66: ='3-Statement Model'!K117 -> 5227.7534 | G66: ='3-Statement Model'!L117 -> 5658.4929 | H66: ='3-Statement Model'!M117 -> 6263.3421 | I66: ='3-Statement Model'!N117 -> 6845.1707 | J66: ='3-Statement Model'!O117 -> 7472.2159 | ... N66: ='3-Statement Model'!S117 -> 10804.18
B67: Property, plant and equipment | C67: ='3-Statement Model'!H119 -> 2257.3 | D67: ='3-Statement Model'!I119 -> 2458.5 | E67: ='3-Statement Model'!J119 -> 2573.4653 | F67: ='3-Statement Model'!K119 -> 2672.526 | G67: ='3-Statement Model'!L119 -> 2762.6444 | H67: ='3-Statement Model'!M119 -> 2875.7154 | I67: ='3-Statement Model'!N119 -> 3014.1754 | J67: ='3-Statement Model'!O119 -> 3130.6564 | ... N67: ='3-Statement Model'!S119 -> 3294.8597
B68: Intangible assets | C68: ='3-Statement Model'!H120 -> 8223.6 | D68: ='3-Statement Model'!I120 -> 8616.1 | E68: ='3-Statement Model'!J120 -> 8679.6303 | F68: ='3-Statement Model'!K120 -> 8805.9734 | G68: ='3-Statement Model'!L120 -> 8948.9006 | H68: ='3-Statement Model'!M120 -> 9113.8177 | I68: ='3-Statement Model'!N120 -> 9299.9842 | J68: ='3-Statement Model'!O120 -> 9449.1622 | ... N68: ='3-Statement Model'!S120 -> 9373.3577
B69: Investments in associated companies | C69: ='3-Statement Model'!H121 -> 19.1 | D69: ='3-Statement Model'!I121 -> 24.1 | E69: ='3-Statement Model'!J121 -> 24.1 | F69: ='3-Statement Model'!K121 -> 24.1 | G69: ='3-Statement Model'!L121 -> 24.1 | H69: ='3-Statement Model'!M121 -> 24.1 | I69: ='3-Statement Model'!N121 -> 24.1 | J69: ='3-Statement Model'!O121 -> 24.1 | ... N69: ='3-Statement Model'!S121 -> 24.1
B70: Other non-current assets | C70: ='3-Statement Model'!H122+'3-Statement Model'!H123 -> 349.4 | D70: ='3-Statement Model'!I122+'3-Statement Model'!I123 -> 315.2 | E70: ='3-Statement Model'!J122+'3-Statement Model'!J123 -> 315.2 | F70: ='3-Statement Model'!K122+'3-Statement Model'!K123 -> 315.2 | G70: ='3-Statement Model'!L122+'3-Statement Model'!L123 -> 315.2 | H70: ='3-Statement Model'!M122+'3-Statement Model'!M123 -> 315.2 | I70: ='3-Statement Model'!N122+'3-Statement Model'!N123 -> 315.2 | J70: ='3-Statement Model'!O122+'3-Statement Model'!O123 -> 315.2 | ... N70: ='3-Statement Model'!S122+'3-Statement Model'!S123 -> 315.2
B71: Total non-current assets | C71: ='3-Statement Model'!H124 -> 10849.4 | D71: ='3-Statement Model'!I124 -> 11413.9 | E71: ='3-Statement Model'!J124 -> 11592.396 | F71: ='3-Statement Model'!K124 -> 11817.799 | G71: ='3-Statement Model'!L124 -> 12050.845 | H71: ='3-Statement Model'!M124 -> 12328.833 | I71: ='3-Statement Model'!N124 -> 12653.46 | J71: ='3-Statement Model'!O124 -> 12919.119 | ... N71: ='3-Statement Model'!S124 -> 13007.517
B72: Total assets | C72: ='3-Statement Model'!H126 -> 15050.8 | D72: ='3-Statement Model'!I126 -> 15977.2 | E72: ='3-Statement Model'!J126 -> 16421.162 | F72: ='3-Statement Model'!K126 -> 17045.553 | G72: ='3-Statement Model'!L126 -> 17709.338 | H72: ='3-Statement Model'!M126 -> 18592.175 | I72: ='3-Statement Model'!N126 -> 19498.63 | J72: ='3-Statement Model'!O126 -> 20391.335 | ... N72: ='3-Statement Model'!S126 -> 23811.698
B73: Accounts payables | C73: ='3-Statement Model'!H128 -> 1108.2 | D73: ='3-Statement Model'!I128 -> 1212.3 | E73: ='3-Statement Model'!J128 -> 1116.0205 | F73: ='3-Statement Model'!K128 -> 1163.0851 | G73: ='3-Statement Model'!L128 -> 1240.7008 | H73: ='3-Statement Model'!M128 -> 1316.3645 | I73: ='3-Statement Model'!N128 -> 1388.9275 | J73: ='3-Statement Model'!O128 -> 1457.9812 | ... N73: ='3-Statement Model'!S128 -> 1680.6355
B74: Other current liabilites | C74: ='3-Statement Model'!H129+'3-Statement Model'!H131+'3-Statement Model'!H132 -> 1089.9 | D74: ='3-Statement Model'!I129+'3-Statement Model'!I131+'3-Statement Model'!I132 -> 1035.7 | E74: ='3-Statement Model'!J129+'3-Statement Model'!J131+'3-Statement Model'!J132 -> 1037.4396 | F74: ='3-Statement Model'!K129+'3-Statement Model'!K131+'3-Statement Model'!K132 -> 1072.7325 | G74: ='3-Statement Model'!L129+'3-Statement Model'!L131+'3-Statement Model'!L132 -> 1119.7811 | H74: ='3-Statement Model'!M129+'3-Statement Model'!M131+'3-Statement Model'!M132 -> 1165.6465 | I74: ='3-Statement Model'!N129+'3-Statement Model'!N131+'3-Statement Model'!N132 -> 1209.6324 | J74: ='3-Statement Model'!O129+'3-Statement Model'!O131+'3-Statement Model'!O132 -> 1251.491 | ... N74: ='3-Statement Model'!S129+'3-Statement Model'!S131+'3-Statement Model'!S132 -> 1386.4583
B75: Financial liabilities | C75: ='3-Statement Model'!H130 -> 1217.9 | D75: ='3-Statement Model'!I130 -> 337.4 | E75: ='3-Statement Model'!J130 -> 337.4 | F75: ='3-Statement Model'!K130 -> 337.4 | G75: ='3-Statement Model'!L130 -> 337.4 | H75: ='3-Statement Model'!M130 -> 337.4 | I75: ='3-Statement Model'!N130 -> 337.4 | J75: ='3-Statement Model'!O130 -> 337.4 | ... N75: ='3-Statement Model'!S130 -> 337.4
B76: Liabilites classified as held for sale | C76: ='3-Statement Model'!H133 -> 0 | D76: ='3-Statement Model'!I133 -> 0 | E76: ='3-Statement Model'!J133 -> 0 | F76: ='3-Statement Model'!K133 -> 0 | G76: ='3-Statement Model'!L133 -> 0 | H76: ='3-Statement Model'!M133 -> 0 | I76: ='3-Statement Model'!N133 -> 0 | J76: ='3-Statement Model'!O133 -> 0 | ... N76: ='3-Statement Model'!S133 -> 0
B77: Total current liabilities | C77: ='3-Statement Model'!H134 -> 3416 | D77: ='3-Statement Model'!I134 -> 2585.4 | E77: ='3-Statement Model'!J134 -> 2490.86 | F77: ='3-Statement Model'!K134 -> 2573.2176 | G77: ='3-Statement Model'!L134 -> 2697.8819 | H77: ='3-Statement Model'!M134 -> 2819.4111 | I77: ='3-Statement Model'!N134 -> 2935.9598 | J77: ='3-Statement Model'!O134 -> 3046.8722 | ... N77: ='3-Statement Model'!S134 -> 3404.4938
B78: Financial liabilities | C78: ='3-Statement Model'!H136 -> 4732 | D78: ='3-Statement Model'!I136 -> 5424.8 | E78: ='3-Statement Model'!J136 -> 5350.3754 | F78: ='3-Statement Model'!K136 -> 5221.5052 | G78: ='3-Statement Model'!L136 -> 5037.8096 | H78: ='3-Statement Model'!M136 -> 5037.8096 | I78: ='3-Statement Model'!N136 -> 5037.8096 | J78: ='3-Statement Model'!O136 -> 5037.8096 | ... N78: ='3-Statement Model'!S136 -> 5037.8096
B79: Employee benefit obligations | C79: ='3-Statement Model'!H139 -> 328.6 | D79: ='3-Statement Model'!I139 -> 357.2 | E79: ='3-Statement Model'!J139 -> 357.2 | F79: ='3-Statement Model'!K139 -> 357.2 | G79: ='3-Statement Model'!L139 -> 357.2 | H79: ='3-Statement Model'!M139 -> 357.2 | I79: ='3-Statement Model'!N139 -> 357.2 | J79: ='3-Statement Model'!O139 -> 357.2 | ... N79: ='3-Statement Model'!S139 -> 357.2
B80: Other liabilities | C80: ='3-Statement Model'!H137+'3-Statement Model'!H138+'3-Statement Model'!H140 -> 640.9 | D80: ='3-Statement Model'!I137+'3-Statement Model'!I138+'3-Statement Model'!I140 -> 563 | E80: ='3-Statement Model'!J137+'3-Statement Model'!J138+'3-Statement Model'!J140 -> 563 | F80: ='3-Statement Model'!K137+'3-Statement Model'!K138+'3-Statement Model'!K140 -> 563 | G80: ='3-Statement Model'!L137+'3-Statement Model'!L138+'3-Statement Model'!L140 -> 563 | H80: ='3-Statement Model'!M137+'3-Statement Model'!M138+'3-Statement Model'!M140 -> 563 | I80: ='3-Statement Model'!N137+'3-Statement Model'!N138+'3-Statement Model'!N140 -> 563 | J80: ='3-Statement Model'!O137+'3-Statement Model'!O138+'3-Statement Model'!O140 -> 563 | ... N80: ='3-Statement Model'!S137+'3-Statement Model'!S138+'3-Statement Model'!S140 -> 563
B81: Total non-current liabilities | C81: ='3-Statement Model'!H141 -> 5701.5 | D81: ='3-Statement Model'!I141 -> 6345 | E81: ='3-Statement Model'!J141 -> 6270.5754 | F81: ='3-Statement Model'!K141 -> 6141.7052 | G81: ='3-Statement Model'!L141 -> 5958.0096 | H81: ='3-Statement Model'!M141 -> 5958.0096 | I81: ='3-Statement Model'!N141 -> 5958.0096 | J81: ='3-Statement Model'!O141 -> 5958.0096 | ... N81: ='3-Statement Model'!S141 -> 5958.0096
B82: Capital stock | C82: ='3-Statement Model'!H143 -> 1.6 | D82: ='3-Statement Model'!I143 -> 1.6 | E82: ='3-Statement Model'!J143 -> 1.6 | F82: ='3-Statement Model'!K143 -> 1.6 | G82: ='3-Statement Model'!L143 -> 1.6 | H82: ='3-Statement Model'!M143 -> 1.6 | I82: ='3-Statement Model'!N143 -> 1.6 | J82: ='3-Statement Model'!O143 -> 1.6 | ... N82: ='3-Statement Model'!S143 -> 1.6
B83: Treasury shares | C83: ='3-Statement Model'!H144 -> -11.9 | D83: ='3-Statement Model'!I144 -> -8.8 | E83: ='3-Statement Model'!J144 -> -8.8 | F83: ='3-Statement Model'!K144 -> -8.8 | G83: ='3-Statement Model'!L144 -> -8.8 | H83: ='3-Statement Model'!M144 -> -8.8 | I83: ='3-Statement Model'!N144 -> -8.8 | J83: ='3-Statement Model'!O144 -> -8.8 | ... N83: ='3-Statement Model'!S144 -> -8.8
B84: Reserves | C84: ='3-Statement Model'!H145 -> 5930.7 | D84: ='3-Statement Model'!I145 -> 7040 | E84: ='3-Statement Model'!J145 -> 7655.9756 | F84: ='3-Statement Model'!K145 -> 8330.24 | G84: ='3-Statement Model'!L145 -> 9056.7768 | H84: ='3-Statement Model'!M145 -> 9822.1608 | I84: ='3-Statement Model'!N145 -> 10616.496 | J84: ='3-Statement Model'!O145 -> 11403.012 | ... N84: ='3-Statement Model'!S145 -> 14487.78
B85: Non-controlling interest | C85: ='3-Statement Model'!H147 -> 12.8 | D85: ='3-Statement Model'!I147 -> 14 | E85: ='3-Statement Model'!J147 -> 10.950602 | F85: ='3-Statement Model'!K147 -> 7.5900608 | G85: ='3-Statement Model'!L147 -> 3.8695581 | H85: ='3-Statement Model'!M147 -> -0.206292 | I85: ='3-Statement Model'!N147 -> -4.6354278 | J85: ='3-Statement Model'!O147 -> -9.359557 | ... N85: ='3-Statement Model'!S147 -> -31.386218
B86: Total equity | C86: ='3-Statement Model'!H148 -> 5933.2 | D86: ='3-Statement Model'!I148 -> 7046.8 | E86: ='3-Statement Model'!J148 -> 7659.7262 | F86: ='3-Statement Model'!K148 -> 8330.63 | G86: ='3-Statement Model'!L148 -> 9053.4464 | H86: ='3-Statement Model'!M148 -> 9814.7545 | I86: ='3-Statement Model'!N148 -> 10604.661 | J86: ='3-Statement Model'!O148 -> 11386.453 | ... N86: ='3-Statement Model'!S148 -> 14449.194
B87: Total liabilities and equity | C87: ='3-Statement Model'!H150 -> 15050.7 | D87: ='3-Statement Model'!I150 -> 15977.2 | E87: ='3-Statement Model'!J150 -> 16421.162 | F87: ='3-Statement Model'!K150 -> 17045.553 | G87: ='3-Statement Model'!L150 -> 17709.338 | H87: ='3-Statement Model'!M150 -> 18592.175 | I87: ='3-Statement Model'!N150 -> 19498.63 | J87: ='3-Statement Model'!O150 -> 20391.335 | ... N87: ='3-Statement Model'!S150 -> 23811.698
B89: Projected Cash Flow Statement
B91: (CHF mm) | E91: =2025 -> 2025 | F91: =E91+1 -> 2026 | G91: =F91+1 -> 2027 | H91: =G91+1 -> 2028 | I91: =H91+1 -> 2029 | J91: =I91+1 -> 2030 | K91: =J91+1 -> 2031 | L91: =K91+1 -> 2032 | M91: =L91+1 -> 2033 | N91: =M91+1 -> 2034
B92: Net Income | E92: ='3-Statement Model'!J156 -> 1140.6956 | F92: ='3-Statement Model'!K156 -> 1309.2511 | G92: ='3-Statement Model'!L156 -> 1482.7282 | H92: ='3-Statement Model'!M156 -> 1645.9871 | I92: ='3-Statement Model'!N156 -> 1805.308 | J92: ='3-Statement Model'!O156 -> 1895.2189 | K92: ='3-Statement Model'!P156 -> 1995.9814 | L92: ='3-Statement Model'!Q156 -> 2090.3262 | ... N92: ='3-Statement Model'!S156 -> 2513.0651
B93: Reversal of NCI net income | E93: ='3-Statement Model'!J157 -> -2.0933134 | F93: ='3-Statement Model'!K157 -> -2.2631811 | G93: ='3-Statement Model'!L157 -> -2.4777408 | H93: ='3-Statement Model'!M157 -> -2.6962514 | I93: ='3-Statement Model'!N157 -> -2.9160008 | J93: ='3-Statement Model'!O157 -> -3.1356346 | K93: ='3-Statement Model'!P157 -> -3.3525324 | L93: ='3-Statement Model'!Q157 -> -3.5639264 | ... N93: ='3-Statement Model'!S157 -> -3.9587273
B94: Depreciation & Amortization | E94: ='3-Statement Model'!J158 -> 598.54062 | F94: ='3-Statement Model'!K158 -> 640.68503 | G94: ='3-Statement Model'!L158 -> 684.13744 | H94: ='3-Statement Model'!M158 -> 694.98905 | I94: ='3-Statement Model'!N158 -> 661.2368 | J94: ='3-Statement Model'!O158 -> 706.51366 | K94: ='3-Statement Model'!P158 -> 729.64321 | L94: ='3-Statement Model'!Q158 -> 751.0445 | ... N94: ='3-Statement Model'!S158 -> 466.22568
B95: Provisions | E95: ='3-Statement Model'!J159 -> -0.62103703 | F95: ='3-Statement Model'!K159 -> 2.2911886 | G95: ='3-Statement Model'!L159 -> 3.0543598 | H95: ='3-Statement Model'!M159 -> 2.9775482 | I95: ='3-Statement Model'!N159 -> 2.8555238 | J95: ='3-Statement Model'!O159 -> 2.7174296 | K95: ='3-Statement Model'!P159 -> 2.5421399 | L95: ='3-Statement Model'!Q159 -> 2.330458 | ... N95: ='3-Statement Model'!S159 -> 1.8053446
B96: Interest Income | E96: ='3-Statement Model'!J160 -> -14.626968 | F96: ='3-Statement Model'!K160 -> -20.415726 | G96: ='3-Statement Model'!L160 -> -27.410596 | H96: ='3-Statement Model'!M160 -> -34.655265 | I96: ='3-Statement Model'!N160 -> -42.212816 | J96: ='3-Statement Model'!O160 -> -49.497181 | K96: ='3-Statement Model'!P160 -> -57.945803 | L96: ='3-Statement Model'!Q160 -> -68.360129 | ... N96: ='3-Statement Model'!S160 -> -97.553834
B97: Accounts receivable | E97: ='3-Statement Model'!J161 -> 35.960731 | F97: ='3-Statement Model'!K161 -> -47.451476 | G97: ='3-Statement Model'!L161 -> -73.371208 | H97: ='3-Statement Model'!M161 -> -137.817 | I97: ='3-Statement Model'!N161 -> -132.16905 | J97: ='3-Statement Model'!O161 -> -125.77731 | K97: ='3-Statement Model'!P161 -> -117.66396 | L97: ='3-Statement Model'!Q161 -> -107.86618 | ... N97: ='3-Statement Model'!S161 -> -83.561093
B98: Inventories | E98: ='3-Statement Model'!J162 -> -46.12561 | F98: ='3-Statement Model'!K162 -> -0.086021971 | G98: ='3-Statement Model'!L162 -> 10.531299 | H98: ='3-Statement Model'!M162 -> -84.438216 | I98: ='3-Statement Model'!N162 -> -80.97781 | J98: ='3-Statement Model'!O162 -> -77.061695 | K98: ='3-Statement Model'!P162 -> -72.090777 | L98: ='3-Statement Model'!Q162 -> -66.087837 | ... N98: ='3-Statement Model'!S162 -> -51.196511
B99: Prepaid expense and accrued income | E99: ='3-Statement Model'!J163 -> 24.698368 | F99: ='3-Statement Model'!K163 -> -13.110972 | G99: ='3-Statement Model'!L163 -> -17.478101 | H99: ='3-Statement Model'!M163 -> -17.038558 | I99: ='3-Statement Model'!N163 -> -16.340292 | J99: ='3-Statement Model'!O163 -> -15.55007 | K99: ='3-Statement Model'!P163 -> -14.547002 | L99: ='3-Statement Model'!Q163 -> -13.335685 | ... N99: ='3-Statement Model'!S163 -> -10.330805
B100: Other current assets | E100: ='3-Statement Model'!J164 -> 0 | F100: ='3-Statement Model'!K164 -> 0 | G100: ='3-Statement Model'!L164 -> 0 | H100: ='3-Statement Model'!M164 -> 0 | I100: ='3-Statement Model'!N164 -> 0 | J100: ='3-Statement Model'!O164 -> 0 | K100: ='3-Statement Model'!P164 -> 0 | L100: ='3-Statement Model'!Q164 -> 0 | ... N100: ='3-Statement Model'!S164 -> 0
B101: Accounts payable | E101: ='3-Statement Model'!J165 -> -96.279512 | F101: ='3-Statement Model'!K165 -> 47.064606 | G101: ='3-Statement Model'!L165 -> 77.615656 | H101: ='3-Statement Model'!M165 -> 75.663763 | I101: ='3-Statement Model'!N165 -> 72.562948 | J101: ='3-Statement Model'!O165 -> 69.053778 | K101: ='3-Statement Model'!P165 -> 64.599416 | L101: ='3-Statement Model'!Q165 -> 59.220276 | ... N101: ='3-Statement Model'!S165 -> 45.876391
B102: Accrued expenses and deferred income | E102: ='3-Statement Model'!J166 -> 2.3605938 | F102: ='3-Statement Model'!K166 -> 33.001734 | G102: ='3-Statement Model'!L166 -> 43.994269 | H102: ='3-Statement Model'!M166 -> 42.887893 | I102: ='3-Statement Model'!N166 -> 41.130282 | J102: ='3-Statement Model'!O166 -> 39.141207 | K102: ='3-Statement Model'!P166 -> 36.616376 | L102: ='3-Statement Model'!Q166 -> 33.567361 | ... N102: ='3-Statement Model'!S166 -> 26.003752
B103: Income tax liabilities | E103: ='3-Statement Model'!J167 -> 0 | F103: ='3-Statement Model'!K167 -> 0 | G103: ='3-Statement Model'!L167 -> 0 | H103: ='3-Statement Model'!M167 -> 0 | I103: ='3-Statement Model'!N167 -> 0 | J103: ='3-Statement Model'!O167 -> 0 | K103: ='3-Statement Model'!P167 -> 0 | L103: ='3-Statement Model'!Q167 -> 0 | ... N103: ='3-Statement Model'!S167 -> 0
B104: Cash flow from operations | E104: ='3-Statement Model'!J168 -> 1642.5095 | F104: ='3-Statement Model'!K168 -> 1948.9663 | G104: ='3-Statement Model'!L168 -> 2181.3236 | H104: ='3-Statement Model'!M168 -> 2185.8601 | I104: ='3-Statement Model'!N168 -> 2308.4776 | J104: ='3-Statement Model'!O168 -> 2441.6231 | K104: ='3-Statement Model'!P168 -> 2563.7825 | L104: ='3-Statement Model'!Q168 -> 2677.2751 | ... N104: ='3-Statement Model'!S168 -> 2806.3753
B105: Capex property, plant and equipment | E105: ='3-Statement Model'!J172 -> -498.20841 | F105: ='3-Statement Model'!K172 -> -522.68374 | G105: ='3-Statement Model'!L172 -> -555.31155 | H105: ='3-Statement Model'!M172 -> -587.11882 | I105: ='3-Statement Model'!N172 -> -576.64832 | J105: ='3-Statement Model'!O172 -> -597.7343 | K105: ='3-Statement Model'!P172 -> -565.62112 | L105: ='3-Statement Model'!Q172 -> -526.74439 | ... N105: ='3-Statement Model'!S172 -> -430.29644
B106: New Intangibles | E106: ='3-Statement Model'!J173 -> -25.04757 | F106: ='3-Statement Model'!K173 -> -26.367489 | G106: ='3-Statement Model'!L173 -> -28.127059 | H106: ='3-Statement Model'!M173 -> -29.842379 | I106: ='3-Statement Model'!N173 -> -31.487403 | J106: ='3-Statement Model'!O173 -> -33.052873 | K106: ='3-Statement Model'!P173 -> -34.517361 | L106: ='3-Statement Model'!Q173 -> -35.859902 | ... N106: ='3-Statement Model'!S173 -> -38.100512
B107: M&A investment | E107: ='3-Statement Model'!J174 -> -253.7802 | F107: ='3-Statement Model'!K174 -> -317.03763 | G107: ='3-Statement Model'!L174 -> -333.7444 | H107: ='3-Statement Model'!M174 -> -356.01602 | I107: ='3-Statement Model'!N174 -> -377.72755 | J107: ='3-Statement Model'!O174 -> -341.38546 | K107: ='3-Statement Model'!P174 -> -298.63187 | L107: ='3-Statement Model'!Q174 -> -218.30443 | ... N107: ='3-Statement Model'!S174 -> 0
B108: Interest received | E108: ='3-Statement Model'!J175 -> 14.626968 | F108: ='3-Statement Model'!K175 -> 20.415726 | G108: ='3-Statement Model'!L175 -> 27.410596 | H108: ='3-Statement Model'!M175 -> 34.655265 | I108: ='3-Statement Model'!N175 -> 42.212816 | J108: ='3-Statement Model'!O175 -> 49.497181 | K108: ='3-Statement Model'!P175 -> 57.945803 | L108: ='3-Statement Model'!Q175 -> 68.360129 | ... N108: ='3-Statement Model'!S175 -> 97.553834
B109: Cash from investing activities | E109: ='3-Statement Model'!J176 -> -762.40922 | F109: ='3-Statement Model'!K176 -> -845.67314 | G109: ='3-Statement Model'!L176 -> -889.77241 | H109: ='3-Statement Model'!M176 -> -938.32196 | I109: ='3-Statement Model'!N176 -> -943.65046 | J109: ='3-Statement Model'!O176 -> -922.67545 | K109: ='3-Statement Model'!P176 -> -840.82454 | L109: ='3-Statement Model'!Q176 -> -712.5486 | ... N109: ='3-Statement Model'!S176 -> -370.84312
B110: Financial liabilities | E110: ='3-Statement Model'!J180 -> -74.424574 | F110: ='3-Statement Model'!K180 -> -128.8702 | G110: ='3-Statement Model'!L180 -> -183.6956 | H110: ='3-Statement Model'!M180 -> 0 | I110: ='3-Statement Model'!N180 -> 0 | J110: ='3-Statement Model'!O180 -> 0 | K110: ='3-Statement Model'!P180 -> 0 | L110: ='3-Statement Model'!Q180 -> 0 | ... N110: ='3-Statement Model'!S180 -> 0
B111: Provisions | E111: ='3-Statement Model'!J181 -> 0 | F111: ='3-Statement Model'!K181 -> 0 | G111: ='3-Statement Model'!L181 -> 0 | H111: ='3-Statement Model'!M181 -> 0 | I111: ='3-Statement Model'!N181 -> 0 | J111: ='3-Statement Model'!O181 -> 0 | K111: ='3-Statement Model'!P181 -> 0 | L111: ='3-Statement Model'!Q181 -> 0 | ... N111: ='3-Statement Model'!S181 -> 0
B112: Other liabilities | E112: ='3-Statement Model'!J182 -> 0 | F112: ='3-Statement Model'!K182 -> 0 | G112: ='3-Statement Model'!L182 -> 0 | H112: ='3-Statement Model'!M182 -> 0 | I112: ='3-Statement Model'!N182 -> 0 | J112: ='3-Statement Model'!O182 -> 0 | K112: ='3-Statement Model'!P182 -> 0 | L112: ='3-Statement Model'!Q182 -> 0 | ... N112: ='3-Statement Model'!S182 -> 0
B113: Common dividends | E113: ='3-Statement Model'!J183 -> -524.71999 | F113: ='3-Statement Model'!K183 -> -634.9868 | G113: ='3-Statement Model'!L183 -> -756.19139 | H113: ='3-Statement Model'!M183 -> -880.60312 | I113: ='3-Statement Model'!N183 -> -1010.9725 | J113: ='3-Statement Model'!O183 -> -1108.7031 | K113: ='3-Statement Model'!P183 -> -1217.5487 | L113: ='3-Statement Model'!Q183 -> -1327.3572 | ... N113: ='3-Statement Model'!S183 -> -1721.4496
...

Sheet Supporting Analyses
A2: x | B2: (CHF mm) | C2: =2015 -> 2015 | D2: =C2+1 -> 2016 | E2: =D2+1 -> 2017 | F2: =E2+1 -> 2018 | G2: =F2+1 -> 2019 | H2: =G2+1 -> 2020 | I2: =H2+1 -> 2021 | J2: =I2+1 -> 2022 | K2: =J2+1 -> 2023 | ... V2: =U2+1 -> 2034
B3: Net sales | C3: 5489.2 | D3: 5747.7 | E3: 6248.3 | F3: 7085.4 | G3: 8109.2 | H3: 7877.5 | I3: 9252.3 | J3: 10491.8 | K3: 11238.6 | L3: 11763.1 | M3: ='3-Statement Model'!J24 -> 11315.208 | N3: ='3-Statement Model'!K24 -> 11911.479 | O3: ='3-Statement Model'!L24 -> 12706.363 | P3: ='3-Statement Model'!M24 -> 13481.257 | Q3: ='3-Statement Model'!N24 -> 14224.394 | R3: ='3-Statement Model'!O24 -> 14931.593 | S3: ='3-Statement Model'!P24 -> 15593.174 | T3: ='3-Statement Model'!Q24 -> 16199.665 | ... V3: ='3-Statement Model'!S24 -> 17211.858
B4: % growth | C4: =(C3-5571.3)/5571.3 -> -0.014736238 | D4: =(D3-C3)/C3 -> 0.047092472 | E4: =(E3-D3)/D3 -> 0.087095708 | F4: =(F3-E3)/E3 -> 0.13397244 | G4: =(G3-F3)/F3 -> 0.14449431 | H4: =(H3-G3)/G3 -> -0.028572486 | I4: =(I3-H3)/H3 -> 0.17452237 | J4: =(J3-I3)/I3 -> 0.13396669 | K4: =(K3-J3)/J3 -> 0.071179397 | L4: =(L3-K3)/K3 -> 0.046669514 | M4: ='3-Statement Model'!J25 -> -0.038076041 | N4: ='3-Statement Model'!K25 -> 0.052696488 | O4: ='3-Statement Model'!L25 -> 0.066732569 | P4: ='3-Statement Model'!M25 -> 0.0609847 | Q4: ='3-Statement Model'!N25 -> 0.055123749 | R4: ='3-Statement Model'!O25 -> 0.04971734 | S4: ='3-Statement Model'!P25 -> 0.04430744 | T4: ='3-Statement Model'!Q25 -> 0.038894673 | ... V4: ='3-Statement Model'!S25 -> 0.02806309
B5: % growth in LC | C5: 0.062 | D5: 0.055 | E5: 0.09 | F5: 0.136 | G5: 0.163 | H5: 0.034 | I5: 0.171 | J5: 0.158 | K5: 0.145 | L5: 0.074
B7: Gross result | C7: 2970.8 | D7: 3181.1 | E7: 3399.1 | F7: 3751.7 | G7: 4334 | H7: 4314.8 | I7: 4791.3 | J7: 5179.8 | K7: 6024.8 | L7: 6416 | M7: ='3-Statement Model'!J32 -> 6223.3642 | N7: ='3-Statement Model'!K32 -> 6551.3137 | O7: ='3-Statement Model'!L32 -> 6988.4997 | P7: ='3-Statement Model'!M32 -> 7414.6912 | Q7: ='3-Statement Model'!N32 -> 7823.4168 | R7: ='3-Statement Model'!O32 -> 8212.3763 | S7: ='3-Statement Model'!P32 -> 8576.2457 | T7: ='3-Statement Model'!Q32 -> 8909.8159 | ... V7: ='3-Statement Model'!S32 -> 9466.5218
B8: Gross margin (%) | C8: =C7/C3 -> 0.54120819 | D8: =D7/D3 -> 0.55345617 | E8: =E7/E3 -> 0.54400397 | F8: =F7/F3 -> 0.52949728 | G8: =G7/G3 -> 0.53445469 | H8: =H7/H3 -> 0.54773723 | I8: =I7/I3 -> 0.51784962 | J8: =J7/J3 -> 0.49369984 | ... V8: =V7/V3 -> 0.55
B10: EBITDA | C10: 837.3 | D10: 965.7 | E10: 1068.5 | F10: 1149.9 | G10: 1387.6 | H10: 1497.6 | I10: 1758 | J10: 1964.2 | K10: 2044.7 | L10: 2269.5 | M10: ='3-Statement Model'!J55 -> 2172.5199 | N10: ='3-Statement Model'!K55 -> 2418.0303 | O10: ='3-Statement Model'!L55 -> 2668.3362 | P10: ='3-Statement Model'!M55 -> 2871.5077 | Q10: ='3-Statement Model'!N55 -> 3029.796 | R10: ='3-Statement Model'!O55 -> 3180.4294 | S10: ='3-Statement Model'!P55 -> 3321.346 | T10: ='3-Statement Model'!Q55 -> 3450.5287 | ... V10: ='3-Statement Model'!S55 -> 3666.1257
B11: EBITDA margin (%) | C11: =C10/C3 -> 0.15253589 | D11: =D10/D3 -> 0.16801503 | E11: =E10/E3 -> 0.17100651 | F11: =F10/F3 -> 0.16229147 | G11: =G10/G3 -> 0.17111429 | H11: =H10/H3 -> 0.19011108 | I11: =I10/I3 -> 0.19000681 | J11: =J10/J3 -> 0.18721287 | ... V11: =V10/V3 -> 0.213
B13: EBIT | C13: 673.3 | D13: 795.3 | E13: 896.3 | F13: 945.9 | G13: 1055.1 | H13: 1130.5 | I13: 1391.4 | J13: 1579.7 | K13: 1549.1 | L13: 1713.9
B14: EBIT margin (%) | C14: =C13/C3 -> 0.12265904 | D14: =D13/D3 -> 0.13836839 | E14: =E13/E3 -> 0.14344702 | F14: =F13/F3 -> 0.13349987 | G14: =G13/G3 -> 0.13011148 | H14: =H13/H3 -> 0.14351 | I14: =I13/I3 -> 0.15038423 | J14: =J13/J3 -> 0.1505652 | ... L14: =L13/L3 -> 0.14570139
B16: CapEx | C16: =135.6+7 -> 142.6 | D16: =149.5+5.4 -> 154.9 | E16: =158.5+4.9 -> 163.4 | F16: =233.4+5.2 -> 238.6 | G16: =179.7+12.6 -> 192.3 | H16: =120.1+11.6 -> 131.7 | I16: =157.3+13.5 -> 170.8 | J16: =238+28 -> 266 | K16: =256.8+23.1 -> 279.9 | L16: =331.1+27.9 -> 359 | M16: ='3-Statement Model'!J198+'3-Statement Model'!J203+'3-Statement Model'!J208 -> 523.25598 | N16: ='3-Statement Model'!K198+'3-Statement Model'!K203+'3-Statement Model'!K208 -> 549.05123 | O16: ='3-Statement Model'!L198+'3-Statement Model'!L203+'3-Statement Model'!L208 -> 583.43861 | P16: ='3-Statement Model'!M198+'3-Statement Model'!M203+'3-Statement Model'!M208 -> 616.9612 | Q16: ='3-Statement Model'!N198+'3-Statement Model'!N203+'3-Statement Model'!N208 -> 608.13572 | R16: ='3-Statement Model'!O198+'3-Statement Model'!O203+'3-Statement Model'!O208 -> 630.78717 | S16: ='3-Statement Model'!P198+'3-Statement Model'!P203+'3-Statement Model'!P208 -> 600.13848 | T16: ='3-Statement Model'!Q198+'3-Statement Model'!Q203+'3-Statement Model'!Q208 -> 562.60429 | ... V16: ='3-Statement Model'!S198+'3-Statement Model'!S203+'3-Statement Model'!S208 -> 468.39696
B17: CapEx as % of sales | C17: =C16/C3 -> 0.025978285 | D17: =D16/D3 -> 0.02694991 | E17: =E16/E3 -> 0.026151113 | F17: =F16/F3 -> 0.033674881 | G17: =G16/G3 -> 0.023713807 | H17: =H16/H3 -> 0.016718502 | I17: =I16/I3 -> 0.018460275 | J17: =J16/J3 -> 0.025353133 | ... L17: =L16/L3 -> 0.030519166 | M17: =M16/'3-Statement Model'!J24 -> 0.046243604 | N17: =N16/'3-Statement Model'!K24 -> 0.046094294 | O17: =O16/'3-Statement Model'!L24 -> 0.045917042 | P17: =P16/'3-Statement Model'!M24 -> 0.045764368 | Q17: =Q16/'3-Statement Model'!N24 -> 0.042753014 | R17: =R16/'3-Statement Model'!O24 -> 0.042245135 | S17: =S16/'3-Statement Model'!P24 -> 0.038487256 | T17: =T16/'3-Statement Model'!Q24 -> 0.034729377 | ... V17: =V16/'3-Statement Model'!S24 -> 0.02721362
B19: R&D | C19: 160.6 | D19: 161.4 | E19: 180.8 | F19: 189.5 | G19: 200.2 | H19: 193.6 | I19: 214.3 | J19: 232 | K19: 270.5 | L19: 278.1
B20: R&D as % of sales | C20: =C19/C3 -> 0.029257451 | D20: =D19/D3 -> 0.028080798 | E20: =E19/E3 -> 0.028935871 | F20: =F19/F3 -> 0.026745138 | G20: =G19/G3 -> 0.024688009 | H20: =H19/H3 -> 0.024576325 | I20: =I19/I3 -> 0.023161808 | J20: =J19/J3 -> 0.022112507 | ... L20: =L19/L3 -> 0.023641727
B21: New patents | C21: 70 | D21: 72 | E21: 74 | F21: 85 | G21: 93 | H21: 83 | I21: 99 | J21: 104 | K21: 108 | L21: 125
B22: R&D employees | C22: 872 | D22: 896 | E22: 900 | F22: 900 | G22: 1100 | H22: 1085 | I22: 1240 | J22: 1334 | K22: 1780 | L22: 1840
L23: =L19/L22 -> 0.1511413
B24: DIO | I24: =(('3-Statement Model'!E113+'3-Statement Model'!F113)/2)/('3-Statement Model'!F29/'3-Statement Model'!F107) -> 80.68701 | J24: =(('3-Statement Model'!F113+'3-Statement Model'!G113)/2)/('3-Statement Model'!G29/'3-Statement Model'!G107) -> 81.461926 | K24: =(('3-Statement Model'!G113+'3-Statement Model'!H113)/2)/('3-Statement Model'!H29/'3-Statement Model'!H107) -> 85.8805 | L24: =(('3-Statement Model'!H113+'3-Statement Model'!I113)/2)/('3-Statement Model'!I29/'3-Statement Model'!I107) -> 88.384732 | M24: =(('3-Statement Model'!J113+'3-Statement Model'!I113)/2)/'3-Statement Model'!J29*'3-Statement Model'!J107 -> 98.346783 | N24: =(('3-Statement Model'!K113+'3-Statement Model'!J113)/2)/'3-Statement Model'!K29*'3-Statement Model'!K107 -> 94.997071 | O24: =(('3-Statement Model'!L113+'3-Statement Model'!K113)/2)/'3-Statement Model'!L29*'3-Statement Model'!L107 -> 88.720865 | P24: =(('3-Statement Model'!M113+'3-Statement Model'!L113)/2)/'3-Statement Model'!M29*'3-Statement Model'!M107 -> 85.844584 | Q24: =(('3-Statement Model'!N113+'3-Statement Model'!M113)/2)/'3-Statement Model'!N29*'3-Statement Model'!N107 -> 86.075952 | R24: =(('3-Statement Model'!O113+'3-Statement Model'!N113)/2)/'3-Statement Model'!O29*'3-Statement Model'!O107 -> 86.291667 | S24: =(('3-Statement Model'!P113+'3-Statement Model'!O113)/2)/'3-Statement Model'!P29*'3-Statement Model'!P107 -> 86.509757 | T24: =(('3-Statement Model'!Q113+'3-Statement Model'!P113)/2)/'3-Statement Model'!Q29*'3-Statement Model'!Q107 -> 86.730235 | ... V24: =(('3-Statement Model'!S113+'3-Statement Model'!R113)/2)/'3-Statement Model'!S29*'3-Statement Model'!S107 -> 87.178411
B25: DSO | I25: =(('3-Statement Model'!E112+'3-Statement Model'!F112)/2)/(('3-Statement Model'!F24/'3-Statement Model'!F107)) -> 57.963371 | J25: =(('3-Statement Model'!F112+'3-Statement Model'!G112)/2)/(('3-Statement Model'!G24/'3-Statement Model'!G107)) -> 57.339351 | K25: =(('3-Statement Model'!G112+'3-Statement Model'!H112)/2)/(('3-Statement Model'!H24/'3-Statement Model'!H107)) -> 60.55078 | L25: =(('3-Statement Model'!H112+'3-Statement Model'!I112)/2)/(('3-Statement Model'!I24/'3-Statement Model'!I107)) -> 64.916264 | M25: =(('3-Statement Model'!I112+'3-Statement Model'!J112)/2)/(('3-Statement Model'!J24/'3-Statement Model'!J107)) -> 69.580001 | N25: =(('3-Statement Model'!J112+'3-Statement Model'!K112)/2)/(('3-Statement Model'!K24/'3-Statement Model'!K107)) -> 66.272979 | O25: =(('3-Statement Model'!K112+'3-Statement Model'!L112)/2)/(('3-Statement Model'!L24/'3-Statement Model'!L107)) -> 63.862442 | P25: =(('3-Statement Model'!L112+'3-Statement Model'!M112)/2)/(('3-Statement Model'!M24/'3-Statement Model'!M107)) -> 63.050592 | ... V25: =(('3-Statement Model'!R112+'3-Statement Model'!S112)/2)/(('3-Statement Model'!S24/'3-Statement Model'!S107)) -> 64.030252
B26: DPO | I26: =(('3-Statement Model'!E128+'3-Statement Model'!F128)/2)/(('3-Statement Model'!F32/'3-Statement Model'!F107)) -> 71.589913 | J26: =(('3-Statement Model'!F128+'3-Statement Model'!G128)/2)/(('3-Statement Model'!G32/'3-Statement Model'!G107)) -> 72.220646 | K26: =(('3-Statement Model'!G128+'3-Statement Model'!H128)/2)/(('3-Statement Model'!H32/'3-Statement Model'!H107)) -> 64.363298 | L26: =(('3-Statement Model'!H128+'3-Statement Model'!I128)/2)/(('3-Statement Model'!I32/'3-Statement Model'!I107)) -> 66.005494 | M26: =(('3-Statement Model'!I128+'3-Statement Model'!J128)/2)/(('3-Statement Model'!J32/'3-Statement Model'!J107)) -> 68.27794 | N26: =(('3-Statement Model'!J128+'3-Statement Model'!K128)/2)/(('3-Statement Model'!K32/'3-Statement Model'!K107)) -> 63.489063 | O26: =(('3-Statement Model'!K128+'3-Statement Model'!L128)/2)/(('3-Statement Model'!L32/'3-Statement Model'!L107)) -> 62.773261 | P26: =(('3-Statement Model'!L128+'3-Statement Model'!M128)/2)/(('3-Statement Model'!M32/'3-Statement Model'!M107)) -> 62.937808 | ... V26: =(('3-Statement Model'!R128+'3-Statement Model'!S128)/2)/(('3-Statement Model'!S32/'3-Statement Model'!S107)) -> 63.915716
B27: CCC | I27: =I24+I25-I26 -> 67.060468 | J27: =J24+J25-J26 -> 66.580631 | K27: =K24+K25-K26 -> 82.067982 | L27: =L24+L25-L26 -> 87.295501 | M27: =M24+M25-M26 -> 99.648844 | N27: =N24+N25-N26 -> 97.780987 | O27: =O24+O25-O26 -> 89.810045 | P27: =P24+P25-P26 -> 85.957368 | ... V27: =V24+V25-V26 -> 87.292947
B31: FCFF | C31: 2021 | D31: 2022 | E31: 2023 | F31: 2024 | G31: 2025 | H31: 2026 | I31: 2027 | J31: 2028 | K31: 2029
B33: Revenue | C33: ='3-Statement Model'!F24 -> 9252.3 | D33: ='3-Statement Model'!G24 -> 10491.8 | E33: ='3-Statement Model'!H24 -> 11238.6 | F33: ='3-Statement Model'!I24 -> 11763.1 | G33: ='3-Statement Model'!J24 -> 11315.208 | H33: ='3-Statement Model'!K24 -> 11911.479 | I33: ='3-Statement Model'!L24 -> 12706.363 | J33: ='3-Statement Model'!M24 -> 13481.257 | ... M33: ='3-Statement Model'!P24 -> 15593.174
B35: EBIT | C35: ='3-Statement Model'!F72 -> 1371.4 | D35: ='3-Statement Model'!G72 -> 1579.7 | E35: ='3-Statement Model'!H72 -> 1549.1 | F35: ='3-Statement Model'!I72 -> 1713.9 | G35: ='3-Statement Model'!J72 -> 1573.9793 | H35: ='3-Statement Model'!K72 -> 1777.3453 | I35: ='3-Statement Model'!L72 -> 1984.1988 | J35: ='3-Statement Model'!M72 -> 2176.5187 | ... M35: ='3-Statement Model'!P72 -> 2591.7028
B37: Taxes | C37: =C38*C35 -> 299.27709 | D37: =D38*D35 -> 353.96161 | E37: =E38*E35 -> 317.37772 | F37: =F38*F35 -> 345.85033 | G37: =G38*G35 -> 317.61552 | H37: =H38*H35 -> 358.65304 | I37: =I38*I35 -> 400.39431 | J37: =J38*J35 -> 439.2028 | ... M37: =M38*M35 -> 522.98341
B38: % tax rate | C38: ='3-Statement Model'!F96 -> 0.21822742 | D38: ='3-Statement Model'!G96 -> 0.22406888 | E38: ='3-Statement Model'!H96 -> 0.20487878 | F38: ='3-Statement Model'!I96 -> 0.20179143 | G38: ='3-Statement Model'!J96 -> 0.20179143 | H38: ='3-Statement Model'!K96 -> 0.20179143 | I38: ='3-Statement Model'!L96 -> 0.20179143 | J38: ='3-Statement Model'!M96 -> 0.20179143 | ... M38: ='3-Statement Model'!P96 -> 0.20179143
B40: NOPAT | C40: =C35-C37 -> 1072.1229 | D40: =D35-D37 -> 1225.7384 | E40: =E35-E37 -> 1231.7223 | F40: =F35-F37 -> 1368.0497 | G40: =G35-G37 -> 1256.3637 | H40: =H35-H37 -> 1418.6923 | I40: =I35-I37 -> 1583.8045 | J40: =J35-J37 -> 1737.3158 | ... M40: =M35-M37 -> 2068.7194
B42: D&A | C42: ='3-Statement Model'!F66 -> 366.6 | D42: ='3-Statement Model'!G66 -> 384.5 | E42: ='3-Statement Model'!H66 -> 485.3 | F42: ='3-Statement Model'!I66 -> 555.6 | G42: ='3-Statement Model'!J66 -> 598.54062 | H42: ='3-Statement Model'!K66 -> 640.68503 | I42: ='3-Statement Model'!L66 -> 684.13744 | J42: ='3-Statement Model'!M66 -> 694.98905 | ... M42: ='3-Statement Model'!P66 -> 729.64321
B43: Provisions | C43: ='3-Statement Model'!F132-'3-Statement Model'!E132 -> -0.8 | D43: ='3-Statement Model'!G132-'3-Statement Model'!F132 -> 0.9 | E43: ='3-Statement Model'!H132-'3-Statement Model'!G132 -> 19.4 | F43: ='3-Statement Model'!I132-'3-Statement Model'!H132 -> -2.2 | G43: ='3-Statement Model'!J132-'3-Statement Model'!I132 -> -0.62103703 | H43: ='3-Statement Model'!K132-'3-Statement Model'!J132 -> 2.2911886 | I43: ='3-Statement Model'!L132-'3-Statement Model'!K132 -> 3.0543598 | J43: ='3-Statement Model'!M132-'3-Statement Model'!L132 -> 2.9775482 | ... M43: ='3-Statement Model'!P132-'3-Statement Model'!O132 -> 2.5421399
B44: Accounts receivable | C44: ='3-Statement Model'!E112-'3-Statement Model'!F112 -> -215 | D44: ='3-Statement Model'!F112-'3-Statement Model'!G112 -> -142.8 | E44: ='3-Statement Model'!G112-'3-Statement Model'!H112 -> -289.6 | F44: ='3-Statement Model'!H112-'3-Statement Model'!I112 -> -165.8 | G44: ='3-Statement Model'!I112-'3-Statement Model'!J112 -> 35.960731 | H44: ='3-Statement Model'!J112-'3-Statement Model'!K112 -> -47.451476 | I44: ='3-Statement Model'!K112-'3-Statement Model'!L112 -> -73.371208 | J44: ='3-Statement Model'!L112-'3-Statement Model'!M112 -> -137.817 | ... M44: ='3-Statement Model'!O112-'3-Statement Model'!P112 -> -117.66396
B45: Inventories | C45: ='3-Statement Model'!E113-'3-Statement Model'!F113 -> -344.3 | D45: ='3-Statement Model'!F113-'3-Statement Model'!G113 -> -54.5 | E45: ='3-Statement Model'!G113-'3-Statement Model'!H113 -> -27.9 | F45: ='3-Statement Model'!H113-'3-Statement Model'!I113 -> -108.2 | G45: ='3-Statement Model'!I113-'3-Statement Model'!J113 -> -46.12561 | H45: ='3-Statement Model'!J113-'3-Statement Model'!K113 -> -0.086021971 | I45: ='3-Statement Model'!K113-'3-Statement Model'!L113 -> 10.531299 | J45: ='3-Statement Model'!L113-'3-Statement Model'!M113 -> -84.438216 | ... M45: ='3-Statement Model'!O113-'3-Statement Model'!P113 -> -72.090777
B46: Prepaid expense and accrued income | C46: ='3-Statement Model'!E114-'3-Statement Model'!F114 -> -69.7 | D46: ='3-Statement Model'!F114-'3-Statement Model'!G114 -> 0.3 | E46: ='3-Statement Model'!G114-'3-Statement Model'!H114 -> -53.7 | F46: ='3-Statement Model'!H114-'3-Statement Model'!I114 -> -29.7 | G46: ='3-Statement Model'!I114-'3-Statement Model'!J114 -> 24.698368 | H46: ='3-Statement Model'!J114-'3-Statement Model'!K114 -> -13.110972 | I46: ='3-Statement Model'!K114-'3-Statement Model'!L114 -> -17.478101 | J46: ='3-Statement Model'!L114-'3-Statement Model'!M114 -> -17.038558 | ... M46: ='3-Statement Model'!O114-'3-Statement Model'!P114 -> -14.547002
B47: Other current assets | C47: ='3-Statement Model'!E115-'3-Statement Model'!F115 -> -11.5 | D47: ='3-Statement Model'!F115-'3-Statement Model'!G115 -> 5.4 | E47: ='3-Statement Model'!G115-'3-Statement Model'!H115 -> -38.3 | F47: ='3-Statement Model'!H115-'3-Statement Model'!I115 -> 5.4 | G47: ='3-Statement Model'!I115-'3-Statement Model'!J115 -> 0 | H47: ='3-Statement Model'!J115-'3-Statement Model'!K115 -> 0 | I47: ='3-Statement Model'!K115-'3-Statement Model'!L115 -> 0 | J47: ='3-Statement Model'!L115-'3-Statement Model'!M115 -> 0 | ... M47: ='3-Statement Model'!O115-'3-Statement Model'!P115 -> 0
B48: Accounts payable | C48: ='3-Statement Model'!F128-'3-Statement Model'!E128 -> 186.9 | D48: ='3-Statement Model'!G128-'3-Statement Model'!F128 -> -16.6 | E48: ='3-Statement Model'!H128-'3-Statement Model'!G128 -> 91.6 | F48: ='3-Statement Model'!I128-'3-Statement Model'!H128 -> 104.1 | G48: ='3-Statement Model'!J128-'3-Statement Model'!I128 -> -96.279512 | H48: ='3-Statement Model'!K128-'3-Statement Model'!J128 -> 47.064606 | I48: ='3-Statement Model'!L128-'3-Statement Model'!K128 -> 77.615656 | J48: ='3-Statement Model'!M128-'3-Statement Model'!L128 -> 75.663763 | ... M48: ='3-Statement Model'!P128-'3-Statement Model'!O128 -> 64.599416
B49: Accrued expenses and deferred income | C49: ='3-Statement Model'!F129-'3-Statement Model'!E129 -> 65.9 | D49: ='3-Statement Model'!G129-'3-Statement Model'!F129 -> -30.9 | E49: ='3-Statement Model'!H129-'3-Statement Model'!G129 -> 189.2 | F49: ='3-Statement Model'!I129-'3-Statement Model'!H129 -> -54.3 | G49: ='3-Statement Model'!J129-'3-Statement Model'!I129 -> 2.3605938 | H49: ='3-Statement Model'!K129-'3-Statement Model'!J129 -> 33.001734 | I49: ='3-Statement Model'!L129-'3-Statement Model'!K129 -> 43.994269 | J49: ='3-Statement Model'!M129-'3-Statement Model'!L129 -> 42.887893 | ... M49: ='3-Statement Model'!P129-'3-Statement Model'!O129 -> 36.616376
B50: Income tax liabilities | C50: ='3-Statement Model'!F131-'3-Statement Model'!E131 -> 7 | D50: ='3-Statement Model'!G131-'3-Statement Model'!F131 -> 35.6 | E50: ='3-Statement Model'!H131-'3-Statement Model'!G131 -> 159.5 | F50: ='3-Statement Model'!I131-'3-Statement Model'!H131 -> 2.3 | G50: ='3-Statement Model'!J131-'3-Statement Model'!I131 -> 0 | H50: ='3-Statement Model'!K131-'3-Statement Model'!J131 -> 0 | I50: ='3-Statement Model'!L131-'3-Statement Model'!K131 -> 0 | J50: ='3-Statement Model'!M131-'3-Statement Model'!L131 -> 0 | ... M50: ='3-Statement Model'!P131-'3-Statement Model'!O131 -> 0
B52: CapEx property, plant and equipment | C52: =-Assumptions!F135-Assumptions!F137 -> -233 | D52: =-Assumptions!G135-Assumptions!G137 -> -342.5 | E52: =-Assumptions!H135-Assumptions!H137 -> -376.8 | F52: =-Assumptions!I135-Assumptions!I137 -> -465.4 | G52: =-Assumptions!J135-Assumptions!J137 -> -498.20841 | H52: =-Assumptions!K135-Assumptions!K137 -> -522.68374 | I52: =-Assumptions!L135-Assumptions!L137 -> -555.31155 | J52: =-Assumptions!M135-Assumptions!M137 -> -587.11882 | ... M52: =-Assumptions!P135-Assumptions!P137 -> -565.62112
B53: CapEx intangibles | C53: =-Assumptions!F139 -> -13.5 | D53: =-Assumptions!G139 -> -28 | E53: =-Assumptions!H139 -> -23.1 | F53: =-Assumptions!I139 -> -27.9 | G53: =-Assumptions!J139 -> -25.04757 | H53: =-Assumptions!K139 -> -26.367489 | I53: =-Assumptions!L139 -> -28.127059 | J53: =-Assumptions!M139 -> -29.842379 | ... M53: =-Assumptions!P139 -> -34.517361
B54: Bolt-on M&A | C54: -304.4 | D54: -142.7 | E54: -35.5 | F54: -256.9 | G54: =-Assumptions!J146 -> -253.7802 | H54: =-Assumptions!K146 -> -317.03763 | I54: =-Assumptions!L146 -> -333.7444 | J54: =-Assumptions!M146 -> -356.01602 | K54: =-Assumptions!N146 -> -377.72755 | L54: =-Assumptions!O146 -> -341.38546 | M54: =-Assumptions!P146 -> -298.63187
B56: FCFF | C56: =C40+SUM(C42:C50)+SUM(C52:C54) -> 506.32291 | D56: =D40+SUM(D42:D50)+SUM(D52:D54) -> 894.43839 | E56: =E40+SUM(E42:E50)+SUM(E52:E54) -> 1331.8223 | F56: =F40+SUM(F42:F50)+SUM(F52:F54) -> 925.04967 | G56: =G40+SUM(G42:G50)+SUM(G52:G54) -> 997.86171 | H56: =H40+SUM(H42:H50)+SUM(H52:H54) -> 1214.9975 | I56: =I40+SUM(I42:I50)+SUM(I52:I54) -> 1395.1052 | J56: =J40+SUM(J42:J50)+SUM(J52:J54) -> 1341.5631 | ... M56: =M40+SUM(M42:M50)+SUM(M52:M54) -> 1799.0485
B57: FCFF ex M&A | C57: =C56-C54 -> 810.72291 | D57: =D56-D54 -> 1037.1384 | E57: =E56-E54 -> 1367.3223 | F57: =F56-F54 -> 1181.9497 | G57: =G56-G54 -> 1251.6419 | H57: =H56-H54 -> 1532.0351 | I57: =I56-I54 -> 1728.8496 | J57: =J56-J54 -> 1697.5791 | ... M57: =M56-M54 -> 2097.6803
B59: FCFF Margin | C59: =C56/C33 -> 0.054724005 | D59: =D56/D33 -> 0.085251185 | E59: =E56/E33 -> 0.11850429 | F59: =F56/F33 -> 0.078639957 | G59: =G56/G33 -> 0.088187662 | H59: =H56/H33 -> 0.10200223 | I59: =I56/I33 -> 0.10979579 | J59: =J56/J33 -> 0.099513207 | ... M59: =M56/M33 -> 0.1153741
B60: FCFF Conversion | C60: =C56/(C35+C42) -> 0.29132503 | D60: =D56/(D35+D42) -> 0.45537032 | E60: =E56/(E35+E42) -> 0.65465114 | F60: =F56/(F35+F42) -> 0.40760065 | G60: =G56/(G35+G42) -> 0.45931074 | H60: =H56/(H35+H42) -> 0.50247404 | I60: =I56/(I35+I42) -> 0.52283711 | J60: =J56/(J35+J42) -> 0.46719815 | ... M60: =M56/(M35+M42) -> 0.54166246
B62: FCFF Margin | C62: =C57/C33 -> 0.087623932 | D62: =D57/D33 -> 0.098852283 | E62: =E57/E33 -> 0.12166304 | F62: =F57/F33 -> 0.10047944 | G62: =G57/G33 -> 0.1106159 | H62: =H57/H33 -> 0.12861837 | I62: =I57/I33 -> 0.13606172 | J62: =J57/J33 -> 0.12592143 | ... M62: =M57/M33 -> 0.13452555
B63: FCFF Conversion | C63: =C57/(C35+C42) -> 0.46646888 | D63: =D57/(D35+D42) -> 0.52802076 | E63: =E57/(E35+E42) -> 0.672101 | F63: =F57/(F35+F42) -> 0.52079739 | G63: =G57/(G35+G42) -> 0.57612449 | H63: =H57/(H35+H42) -> 0.63358805 | I63: =I57/(I35+I42) -> 0.64791295 | J63: =J57/(J35+J42) -> 0.59118042 | ... M63: =M57/(M35+M42) -> 0.63157537
B65: Cash & cash equivalents | D65: 1318.7 | E65: 1175 | F65: 1873.3 | G65: 643.9 | H65: 707.5 | I65: 987.49964 | J65: 1325.8385 | K65: 1676.2599 | L65: 2041.8153 | M65: 2394.1568 | N65: 2802.8129 | O65: 3306.5492 | P65: 3942.1665 | Q65: 4718.6359 | R65: 5430.6121
B66: Financial liabilities current | D66: 334.7 | E66: 334.9 | F66: 303 | G66: 1217.9 | H66: 337.4 | I66: 337.4 | J66: 337.4 | K66: 337.4 | L66: 337.4 | M66: 337.4 | N66: 337.4 | O66: 337.4 | P66: 337.4 | Q66: 337.4 | R66: 337.4
B67: Financial liabilities non-current | D67: 3851.9 | E67: 3393.9 | F67: 3634.2 | G67: 4732 | H67: 5424.8 | I67: 5350.3754 | J67: 5221.5052 | K67: 5037.8096 | L67: 5037.8096 | M67: 5037.8096 | N67: 5037.8096 | O67: 5037.8096 | P67: 5037.8096 | Q67: 5037.8096 | R67: 5037.8096
B68: Employee benefits obligations | D68: 319.5 | E68: 322.9 | F68: 239.9 | G68: 328.6 | H68: 357.2 | I68: 357.2 | J68: 357.2 | K68: 357.2 | L68: 357.2 | M68: 357.2 | N68: 357.2 | O68: 357.2 | P68: 357.2 | Q68: 357.2 | R68: 357.2
B69: Net Debt | D69: 3187.4 | E69: 2876.7 | F69: 2303.8 | G69: 5634.6 | H69: 5411.9 | I69: 5057.4758 | J69: 4590.2668 | K69: 4056.1497 | L69: 3690.5943 | M69: 3338.2528 | N69: 2929.5967 | O69: 2425.8604 | P69: 1790.2431 | Q69: 1013.7738 | R69: 301.79752
B71: EBITDA | D71: 1497.7 | E71: 1738 | F71: 1964.2 | G71: 2044.7 | H71: 2269.5 | I71: 2172.5199 | J71: 2418.0303 | K71: 2668.3362 | L71: 2871.5077 | M71: 3029.796 | N71: 3180.4294 | O71: 3321.346 | P71: 3450.5287 | Q71: 3566.0513 | R71: 3666.1257
B73: Net Debt/EBITDA | D73: 2.1281966 | E73: 1.6551784 | F73: 1.1728948 | G73: 2.7557099 | H73: 2.3846222 | I73: 2.3279307 | J73: 1.8983495 | K73: 1.5201044 | L73: 1.2852462 | M73: 1.1018078 | N73: 0.92113246 | O73: 0.73038471 | P73: 0.51883153 | Q73: 0.28428468 | R73: 0.08232056
B75: Capex | E75: 170.8 | F75: 266 | G75: 279.9 | H75: 359 | I75: 398.2538 | J75: 417.46187
B76: Normalized EBITDA | E76: 1751.7 | F76: 1957.6 | G76: 2158.8 | H76: 2279 | I76: 2262.5199 | J76: 2418.0303
B77: Capex/EBITDA | E77: 0.097505281 | F77: 0.13588067 | G77: 0.12965536 | H77: 0.15752523 | I77: 0.17602223 | J77: 0.17264542
